Workbook

Sheet Instructions
A1: PROJECT TASK TRACKER - DAILY, DATE-WISE
A3: HOW THIS WORKBOOK WORKS
A4: 1. Enter every task ONCE on the 'Task Log' sheet. Never retype a task on a new day.
A5: 2. Fill only the coloured columns. White columns are formulas - do not type in them.
A6: 3. If a task is not marked Completed by its Due Date, it is carried forward automatically:
A7: its 'Active Date' rolls to today and it keeps appearing on 'Today's Plan'.
A8: 4. Set Status = Completed and enter the Completed Date - the task closes on that date
A9: and stops rolling forward.
A10: 5. 'Dashboard' is live. Every count and chart recalculates on its own.
A12: TWO DIFFERENT DATES - USE BOTH
A13: Due Date - when YOUR step has to be finished (send quote, prepare kit, follow up DGCA).
A14: Execution / Event Date - the committed date the project itself must happen: the demo date,
... A61: - The web app uses these exact columns, so Excel and the app import/export cleanly.

Sheet Task Log
A1: Task ID | B1: Date Logged | C1: Vertical | D1: Task Description | E1: Client / Customer | F1: Order Type | G1: Priority | H1: Due Date | I1: Execution / Event Date | J1: Event Type | K1: Status | L1: Completed Date | M1: Active Date | N1: Day Status | O1: Days to Event | P1: Ageing (Days) | Q1: Open Seq | R1: Remarks | S1: Assigned To
A2: =IF($D2="","",ROW()-1) | B2: 46274 | C2: Tenders | D2: Submit technical bid documents for surveillance drone tender | E2: State Police Dept | F2: Tender / Bid | G2: High | H2: 46278 | I2: 46284 | J2: Tender Submission | K2: In Progress | M2: =IF($D2="","",IF($K2="Completed",IF($L2="",$H2,$L2),IF($H2="","",IF($H2<TODAY(),TODAY(),$H2)))) | N2: =IF($D2="","",IF($K2="Completed","Completed",IF($H2="","No Due Date",IF($H2<TODAY(),"Carried Forward",IF($H2=TODAY(),"Due Today","Upcoming"))))) | O2: =IF($D2="","",IF($I2="","",IF($K2="Completed","",$I2-TODAY()))) | P2: =IF($D2="","",IF($B2="","",IF($K2="Completed",IF($L2="","",$L2-$B2),TODAY()-$B2))) | Q2: =IF($D2="","",IF($K2="Completed","",MAX($Q$1:$Q1)+1)) | R2: SAMPLE - overdue step, carried forward automatically
A3: =IF($D3="","",ROW()-1) | B3: 46276 | C3: Defence | D3: Arrange flight demo of VTOL unit for evaluation team | E3: MoD - Army Wing | F3: Drone Sale - Govt Order | G3: High | H3: 46280 | I3: 46286 | J3: Demo | K3: In Progress | M3: =IF($D3="","",IF($K3="Completed",IF($L3="",$H3,$L3),IF($H3="","",IF($H3<TODAY(),TODAY(),$H3)))) | N3: =IF($D3="","",IF($K3="Completed","Completed",IF($H3="","No Due Date",IF($H3<TODAY(),"Carried Forward",IF($H3=TODAY(),"Due Today","Upcoming"))))) | O3: =IF($D3="","",IF($I3="","",IF($K3="Completed","",$I3-TODAY()))) | P3: =IF($D3="","",IF($B3="","",IF($K3="Completed",IF($L3="","",$L3-$B3),TODAY()-$B3))) | Q3: =IF($D3="","",IF($K3="Completed","",MAX($Q$1:$Q2)+1)) | R3: SAMPLE - demo date is the committed date
A4: =IF($D4="","",ROW()-1) | B4: 46276 | C4: RPTO Establishment | D4: Follow up DGCA file for new RPTO site approval | E4: Internal | F4: Internal / Admin | G4: Medium | H4: 46283 | I4: 46301 | J4: Go-Live | K4: Not Started | M4: =IF($D4="","",IF($K4="Completed",IF($L4="",$H4,$L4),IF($H4="","",IF($H4<TODAY(),TODAY(),$H4)))) | N4: =IF($D4="","",IF($K4="Completed","Completed",IF($H4="","No Due Date",IF($H4<TODAY(),"Carried Forward",IF($H4=TODAY(),"Due Today","Upcoming"))))) | O4: =IF($D4="","",IF($I4="","",IF($K4="Completed","",$I4-TODAY()))) | P4: =IF($D4="","",IF($B4="","",IF($K4="Completed",IF($L4="","",$L4-$B4),TODAY()-$B4))) | Q4: =IF($D4="","",IF($K4="Completed","",MAX($Q$1:$Q3)+1)) | R4: SAMPLE
A5: =IF($D5="","",ROW()-1) | B5: 46272 | C5: Agri Services | D5: Schedule spraying crew for 120 acre paddy block | E5: Farmer Producer Org | F5: Service / DaaS | G5: Medium | H5: 46275 | I5: 46275 | J5: Site Survey | K5: Completed | L5: 46275 | M5: =IF($D5="","",IF($K5="Completed",IF($L5="",$H5,$L5),IF($H5="","",IF($H5<TODAY(),TODAY(),$H5)))) | N5: =IF($D5="","",IF($K5="Completed","Completed",IF($H5="","No Due Date",IF($H5<TODAY(),"Carried Forward",IF($H5=TODAY(),"Due Today","Upcoming"))))) | O5: =IF($D5="","",IF($I5="","",IF($K5="Completed","",$I5-TODAY()))) | P5: =IF($D5="","",IF($B5="","",IF($K5="Completed",IF($L5="","",$L5-$B5),TODAY()-$B5))) | Q5: =IF($D5="","",IF($K5="Completed","",MAX($Q$1:$Q4)+1)) | R5: SAMPLE - closed, stops rolling
A6: =IF($D6="","",ROW()-1) | B6: 46278 | C6: Redington | D6: Share updated price list and channel margin sheet | E6: Redington India | F6: Drone Sale - Private | G6: Low | H6: 46285 | K6: Not Started | M6: =IF($D6="","",IF($K6="Completed",IF($L6="",$H6,$L6),IF($H6="","",IF($H6<TODAY(),TODAY(),$H6)))) | N6: =IF($D6="","",IF($K6="Completed","Completed",IF($H6="","No Due Date",IF($H6<TODAY(),"Carried Forward",IF($H6=TODAY(),"Due Today","Upcoming"))))) | O6: =IF($D6="","",IF($I6="","",IF($K6="Completed","",$I6-TODAY()))) | P6: =IF($D6="","",IF($B6="","",IF($K6="Completed",IF($L6="","",$L6-$B6),TODAY()-$B6))) | Q6: =IF($D6="","",IF($K6="Completed","",MAX($Q$1:$Q5)+1)) | R6: SAMPLE - no event date, only a due date
A7: =IF($D7="","",ROW()-1) | B7: 46279 | C7: DaaS | D7: Raise invoice for September survey mandays | E7: Private Infra Co | F7: Service / DaaS | G7: High | H7: 46281 | I7: 46282 | J7: Payment / Invoice | K7: In Progress | M7: =IF($D7="","",IF($K7="Completed",IF($L7="",$H7,$L7),IF($H7="","",IF($H7<TODAY(),TODAY(),$H7)))) | N7: =IF($D7="","",IF($K7="Completed","Completed",IF($H7="","No Due Date",IF($H7<TODAY(),"Carried Forward",IF($H7=TODAY(),"Due Today","Upcoming"))))) | O7: =IF($D7="","",IF($I7="","",IF($K7="Completed","",$I7-TODAY()))) | P7: =IF($D7="","",IF($B7="","",IF($K7="Completed",IF($L7="","",$L7-$B7),TODAY()-$B7))) | Q7: =IF($D7="","",IF($K7="Completed","",MAX($Q$1:$Q6)+1)) | R7: SAMPLE
A8: =IF($D8="","",ROW()-1) | M8: =IF($D8="","",IF($K8="Completed",IF($L8="",$H8,$L8),IF($H8="","",IF($H8<TODAY(),TODAY(),$H8)))) | N8: =IF($D8="","",IF($K8="Completed","Completed",IF($H8="","No Due Date",IF($H8<TODAY(),"Carried Forward",IF($H8=TODAY(),"Due Today","Upcoming"))))) | O8: =IF($D8="","",IF($I8="","",IF($K8="Completed","",$I8-TODAY()))) | P8: =IF($D8="","",IF($B8="","",IF($K8="Completed",IF($L8="","",$L8-$B8),TODAY()-$B8))) | Q8: =IF($D8="","",IF($K8="Completed","",MAX($Q$1:$Q7)+1))
A9: =IF($D9="","",ROW()-1) | M9: =IF($D9="","",IF($K9="Completed",IF($L9="",$H9,$L9),IF($H9="","",IF($H9<TODAY(),TODAY(),$H9)))) | N9: =IF($D9="","",IF($K9="Completed","Completed",IF($H9="","No Due Date",IF($H9<TODAY(),"Carried Forward",IF($H9=TODAY(),"Due Today","Upcoming"))))) | O9: =IF($D9="","",IF($I9="","",IF($K9="Completed","",$I9-TODAY()))) | P9: =IF($D9="","",IF($B9="","",IF($K9="Completed",IF($L9="","",$L9-$B9),TODAY()-$B9))) | Q9: =IF($D9="","",IF($K9="Completed","",MAX($Q$1:$Q8)+1))
A10: =IF($D10="","",ROW()-1) | M10: =IF($D10="","",IF($K10="Completed",IF($L10="",$H10,$L10),IF($H10="","",IF($H10<TODAY(),TODAY(),$H10)))) | N10: =IF($D10="","",IF($K10="Completed","Completed",IF($H10="","No Due Date",IF($H10<TODAY(),"Carried Forward",IF($H10=TODAY(),"Due Today","Upcoming"))))) | O10: =IF($D10="","",IF($I10="","",IF($K10="Completed","",$I10-TODAY()))) | P10: =IF($D10="","",IF($B10="","",IF($K10="Completed",IF($L10="","",$L10-$B10),TODAY()-$B10))) | Q10: =IF($D10="","",IF($K10="Completed","",MAX($Q$1:$Q9)+1))
A11: =IF($D11="","",ROW()-1) | M11: =IF($D11="","",IF($K11="Completed",IF($L11="",$H11,$L11),IF($H11="","",IF($H11<TODAY(),TODAY(),$H11)))) | N11: =IF($D11="","",IF($K11="Completed","Completed",IF($H11="","No Due Date",IF($H11<TODAY(),"Carried Forward",IF($H11=TODAY(),"Due Today","Upcoming"))))) | O11: =IF($D11="","",IF($I11="","",IF($K11="Completed","",$I11-TODAY()))) | P11: =IF($D11="","",IF($B11="","",IF($K11="Completed",IF($L11="","",$L11-$B11),TODAY()-$B11))) | Q11: =IF($D11="","",IF($K11="Completed","",MAX($Q$1:$Q10)+1))
A12: =IF($D12="","",ROW()-1) | M12: =IF($D12="","",IF($K12="Completed",IF($L12="",$H12,$L12),IF($H12="","",IF($H12<TODAY(),TODAY(),$H12)))) | N12: =IF($D12="","",IF($K12="Completed","Completed",IF($H12="","No Due Date",IF($H12<TODAY(),"Carried Forward",IF($H12=TODAY(),"Due Today","Upcoming"))))) | O12: =IF($D12="","",IF($I12="","",IF($K12="Completed","",$I12-TODAY()))) | P12: =IF($D12="","",IF($B12="","",IF($K12="Completed",IF($L12="","",$L12-$B12),TODAY()-$B12))) | Q12: =IF($D12="","",IF($K12="Completed","",MAX($Q$1:$Q11)+1))
A13: =IF($D13="","",ROW()-1) | M13: =IF($D13="","",IF($K13="Completed",IF($L13="",$H13,$L13),IF($H13="","",IF($H13<TODAY(),TODAY(),$H13)))) | N13: =IF($D13="","",IF($K13="Completed","Completed",IF($H13="","No Due Date",IF($H13<TODAY(),"Carried Forward",IF($H13=TODAY(),"Due Today","Upcoming"))))) | O13: =IF($D13="","",IF($I13="","",IF($K13="Completed","",$I13-TODAY()))) | P13: =IF($D13="","",IF($B13="","",IF($K13="Completed",IF($L13="","",$L13-$B13),TODAY()-$B13))) | Q13: =IF($D13="","",IF($K13="Completed","",MAX($Q$1:$Q12)+1))
A14: =IF($D14="","",ROW()-1) | M14: =IF($D14="","",IF($K14="Completed",IF($L14="",$H14,$L14),IF($H14="","",IF($H14<TODAY(),TODAY(),$H14)))) | N14: =IF($D14="","",IF($K14="Completed","Completed",IF($H14="","No Due Date",IF($H14<TODAY(),"Carried Forward",IF($H14=TODAY(),"Due Today","Upcoming"))))) | O14: =IF($D14="","",IF($I14="","",IF($K14="Completed","",$I14-TODAY()))) | P14: =IF($D14="","",IF($B14="","",IF($K14="Completed",IF($L14="","",$L14-$B14),TODAY()-$B14))) | Q14: =IF($D14="","",IF($K14="Completed","",MAX($Q$1:$Q13)+1))
A15: =IF($D15="","",ROW()-1) | M15: =IF($D15="","",IF($K15="Completed",IF($L15="",$H15,$L15),IF($H15="","",IF($H15<TODAY(),TODAY(),$H15)))) | N15: =IF($D15="","",IF($K15="Completed","Completed",IF($H15="","No Due Date",IF($H15<TODAY(),"Carried Forward",IF($H15=TODAY(),"Due Today","Upcoming"))))) | O15: =IF($D15="","",IF($I15="","",IF($K15="Completed","",$I15-TODAY()))) | P15: =IF($D15="","",IF($B15="","",IF($K15="Completed",IF($L15="","",$L15-$B15),TODAY()-$B15))) | Q15: =IF($D15="","",IF($K15="Completed","",MAX($Q$1:$Q14)+1))
A16: =IF($D16="","",ROW()-1) | M16: =IF($D16="","",IF($K16="Completed",IF($L16="",$H16,$L16),IF($H16="","",IF($H16<TODAY(),TODAY(),$H16)))) | N16: =IF($D16="","",IF($K16="Completed","Completed",IF($H16="","No Due Date",IF($H16<TODAY(),"Carried Forward",IF($H16=TODAY(),"Due Today","Upcoming"))))) | O16: =IF($D16="","",IF($I16="","",IF($K16="Completed","",$I16-TODAY()))) | P16: =IF($D16="","",IF($B16="","",IF($K16="Completed",IF($L16="","",$L16-$B16),TODAY()-$B16))) | Q16: =IF($D16="","",IF($K16="Completed","",MAX($Q$1:$Q15)+1))
A17: =IF($D17="","",ROW()-1) | M17: =IF($D17="","",IF($K17="Completed",IF($L17="",$H17,$L17),IF($H17="","",IF($H17<TODAY(),TODAY(),$H17)))) | N17: =IF($D17="","",IF($K17="Completed","Completed",IF($H17="","No Due Date",IF($H17<TODAY(),"Carried Forward",IF($H17=TODAY(),"Due Today","Upcoming"))))) | O17: =IF($D17="","",IF($I17="","",IF($K17="Completed","",$I17-TODAY()))) | P17: =IF($D17="","",IF($B17="","",IF($K17="Completed",IF($L17="","",$L17-$B17),TODAY()-$B17))) | Q17: =IF($D17="","",IF($K17="Completed","",MAX($Q$1:$Q16)+1))
A18: =IF($D18="","",ROW()-1) | M18: =IF($D18="","",IF($K18="Completed",IF($L18="",$H18,$L18),IF($H18="","",IF($H18<TODAY(),TODAY(),$H18)))) | N18: =IF($D18="","",IF($K18="Completed","Completed",IF($H18="","No Due Date",IF($H18<TODAY(),"Carried Forward",IF($H18=TODAY(),"Due Today","Upcoming"))))) | O18: =IF($D18="","",IF($I18="","",IF($K18="Completed","",$I18-TODAY()))) | P18: =IF($D18="","",IF($B18="","",IF($K18="Completed",IF($L18="","",$L18-$B18),TODAY()-$B18))) | Q18: =IF($D18="","",IF($K18="Completed","",MAX($Q$1:$Q17)+1))
A19: =IF($D19="","",ROW()-1) | M19: =IF($D19="","",IF($K19="Completed",IF($L19="",$H19,$L19),IF($H19="","",IF($H19<TODAY(),TODAY(),$H19)))) | N19: =IF($D19="","",IF($K19="Completed","Completed",IF($H19="","No Due Date",IF($H19<TODAY(),"Carried Forward",IF($H19=TODAY(),"Due Today","Upcoming"))))) | O19: =IF($D19="","",IF($I19="","",IF($K19="Completed","",$I19-TODAY()))) | P19: =IF($D19="","",IF($B19="","",IF($K19="Completed",IF($L19="","",$L19-$B19),TODAY()-$B19))) | Q19: =IF($D19="","",IF($K19="Completed","",MAX($Q$1:$Q18)+1))
... A500: =IF($D500="","",ROW()-1) | M500: =IF($D500="","",IF($K500="Completed",IF($L500="",$H500,$L500),IF($H500="","",IF($H500<TODAY(),TODAY(),$H500)))) | N500: =IF($D500="","",IF($K500="Completed","Completed",IF($H500="","No Due Date",IF($H500<TODAY(),"Carried Forward",IF($H500=TODAY(),"Due Today","Upcoming"))))) | O500: =IF($D500="","",IF($I500="","",IF($K500="Completed","",$I500-TODAY()))) | P500: =IF($D500="","",IF($B500="","",IF($K500="Completed",IF($L500="","",$L500-$B500),TODAY()-$B500))) | Q500: =IF($D500="","",IF($K500="Completed","",MAX($Q$1:$Q499)+1))

Sheet Projects
A1: Project ID | B1: Project Name | C1: Vertical | D1: Requirements | E1: Start Date | F1: End Date | G1: L1 | H1: BOQ | I1: TEC | J1: Awarded | K1: Procurement | L1: Inventory | M1: Production | N1: QC | O1: Testing | P1: Dispatch | Q1: Delivered | R1: Payment | S1: Documentation | T1: Failed | U1: % Complete | V1: Overall Status
A2: PRJ-001 | B2: VTOL Unit — MoD Surveillance Order | C2: Defence | D2: 20kg payload VTOL, thermal + EO camera, 2hr endurance | E2: 46266 | F2: 46371 | G2: Done | H2: Done | I2: Done | J2: Done | K2: Pending | U2: =IF($B2="","",IF(COUNTIF(G2:T2,"<>")=0,0,ROUND(COUNTIF(G2:T2,"Done")/COUNTIF(G2:T2,"<>")*100,0))) | V2: =IF($B2="","",IF($T2="Done","Failed",IF(U2=100,"Completed","In Progress")))
A3: PRJ-002 | B3: Agri Drone Batch — Redington Channel | C3: Redington | D3: 6 units, spraying config, dealer training included | E3: 46249 | F3: 46305 | G3: Done | H3: Done | I3: Done | J3: Done | K3: Done | L3: Done | M3: Pending | R3: Pending | S3: Pending | U3: =IF($B3="","",IF(COUNTIF(G3:T3,"<>")=0,0,ROUND(COUNTIF(G3:T3,"Done")/COUNTIF(G3:T3,"<>")*100,0))) | V3: =IF($B3="","",IF($T3="Done","Failed",IF(U3=100,"Completed","In Progress")))
U4: =IF($B4="","",IF(COUNTIF(G4:T4,"<>")=0,0,ROUND(COUNTIF(G4:T4,"Done")/COUNTIF(G4:T4,"<>")*100,0))) | V4: =IF($B4="","",IF($T4="Done","Failed",IF(U4=100,"Completed","In Progress")))
U5: =IF($B5="","",IF(COUNTIF(G5:T5,"<>")=0,0,ROUND(COUNTIF(G5:T5,"Done")/COUNTIF(G5:T5,"<>")*100,0))) | V5: =IF($B5="","",IF($T5="Done","Failed",IF(U5=100,"Completed","In Progress")))
U6: =IF($B6="","",IF(COUNTIF(G6:T6,"<>")=0,0,ROUND(COUNTIF(G6:T6,"Done")/COUNTIF(G6:T6,"<>")*100,0))) | V6: =IF($B6="","",IF($T6="Done","Failed",IF(U6=100,"Completed","In Progress")))
U7: =IF($B7="","",IF(COUNTIF(G7:T7,"<>")=0,0,ROUND(COUNTIF(G7:T7,"Done")/COUNTIF(G7:T7,"<>")*100,0))) | V7: =IF($B7="","",IF($T7="Done","Failed",IF(U7=100,"Completed","In Progress")))
U8: =IF($B8="","",IF(COUNTIF(G8:T8,"<>")=0,0,ROUND(COUNTIF(G8:T8,"Done")/COUNTIF(G8:T8,"<>")*100,0))) | V8: =IF($B8="","",IF($T8="Done","Failed",IF(U8=100,"Completed","In Progress")))
U9: =IF($B9="","",IF(COUNTIF(G9:T9,"<>")=0,0,ROUND(COUNTIF(G9:T9,"Done")/COUNTIF(G9:T9,"<>")*100,0))) | V9: =IF($B9="","",IF($T9="Done","Failed",IF(U9=100,"Completed","In Progress")))
U10: =IF($B10="","",IF(COUNTIF(G10:T10,"<>")=0,0,ROUND(COUNTIF(G10:T10,"Done")/COUNTIF(G10:T10,"<>")*100,0))) | V10: =IF($B10="","",IF($T10="Done","Failed",IF(U10=100,"Completed","In Progress")))
U11: =IF($B11="","",IF(COUNTIF(G11:T11,"<>")=0,0,ROUND(COUNTIF(G11:T11,"Done")/COUNTIF(G11:T11,"<>")*100,0))) | V11: =IF($B11="","",IF($T11="Done","Failed",IF(U11=100,"Completed","In Progress")))
U12: =IF($B12="","",IF(COUNTIF(G12:T12,"<>")=0,0,ROUND(COUNTIF(G12:T12,"Done")/COUNTIF(G12:T12,"<>")*100,0))) | V12: =IF($B12="","",IF($T12="Done","Failed",IF(U12=100,"Completed","In Progress")))
U13: =IF($B13="","",IF(COUNTIF(G13:T13,"<>")=0,0,ROUND(COUNTIF(G13:T13,"Done")/COUNTIF(G13:T13,"<>")*100,0))) | V13: =IF($B13="","",IF($T13="Done","Failed",IF(U13=100,"Completed","In Progress")))
U14: =IF($B14="","",IF(COUNTIF(G14:T14,"<>")=0,0,ROUND(COUNTIF(G14:T14,"Done")/COUNTIF(G14:T14,"<>")*100,0))) | V14: =IF($B14="","",IF($T14="Done","Failed",IF(U14=100,"Completed","In Progress")))
U15: =IF($B15="","",IF(COUNTIF(G15:T15,"<>")=0,0,ROUND(COUNTIF(G15:T15,"Done")/COUNTIF(G15:T15,"<>")*100,0))) | V15: =IF($B15="","",IF($T15="Done","Failed",IF(U15=100,"Completed","In Progress")))
... U500: =IF($B500="","",IF(COUNTIF(G500:T500,"<>")=0,0,ROUND(COUNTIF(G500:T500,"Done")/COUNTIF(G500:T500,"<>")*100,0))) | V500: =IF($B500="","",IF($T500="Done","Failed",IF(U500=100,"Completed","In Progress")))

Sheet Today's Plan
A1: TODAY'S PLAN - every open task as on | E1: =TODAY()
A2: Auto-generated from the Task Log. Overdue tasks stay here until marked Completed. Nothing to type on this sheet.
A4: S.No | B4: Vertical | C4: Task Description | D4: Client / Customer | E4: Priority | F4: Due Date | G4: Event Date | H4: Event Type | I4: Days to Event | J4: Status | K4: Day Status | L4: Ageing (Days)
A5: =IFERROR(IF(MATCH(1,'Task Log'!$Q$2:$Q$500,0)>0,1,""),"") | B5: =IFERROR(IF(INDEX('Task Log'!$C$2:$C$500,MATCH(1,'Task Log'!$Q$2:$Q$500,0))="","",INDEX('Task Log'!$C$2:$C$500,MATCH(1,'Task Log'!$Q$2:$Q$500,0))),"") | C5: =IFERROR(IF(INDEX('Task Log'!$D$2:$D$500,MATCH(1,'Task Log'!$Q$2:$Q$500,0))="","",INDEX('Task Log'!$D$2:$D$500,MATCH(1,'Task Log'!$Q$2:$Q$500,0))),"") | D5: =IFERROR(IF(INDEX('Task Log'!$E$2:$E$500,MATCH(1,'Task Log'!$Q$2:$Q$500,0))="","",INDEX('Task Log'!$E$2:$E$500,MATCH(1,'Task Log'!$Q$2:$Q$500,0))),"") | E5: =IFERROR(IF(INDEX('Task Log'!$G$2:$G$500,MATCH(1,'Task Log'!$Q$2:$Q$500,0))="","",INDEX('Task Log'!$G$2:$G$500,MATCH(1,'Task Log'!$Q$2:$Q$500,0))),"") | F5: =IFERROR(IF(INDEX('Task Log'!$H$2:$H$500,MATCH(1,'Task Log'!$Q$2:$Q$500,0))="","",INDEX('Task Log'!$H$2:$H$500,MATCH(1,'Task Log'!$Q$2:$Q$500,0))),"") | G5: =IFERROR(IF(INDEX('Task Log'!$I$2:$I$500,MATCH(1,'Task Log'!$Q$2:$Q$500,0))="","",INDEX('Task Log'!$I$2:$I$500,MATCH(1,'Task Log'!$Q$2:$Q$500,0))),"") | H5: =IFERROR(IF(INDEX('Task Log'!$J$2:$J$500,MATCH(1,'Task Log'!$Q$2:$Q$500,0))="","",INDEX('Task Log'!$J$2:$J$500,MATCH(1,'Task Log'!$Q$2:$Q$500,0))),"") | I5: =IFERROR(IF(INDEX('Task Log'!$O$2:$O$500,MATCH(1,'Task Log'!$Q$2:$Q$500,0))="","",INDEX('Task Log'!$O$2:$O$500,MATCH(1,'Task Log'!$Q$2:$Q$500,0))),"") | J5: =IFERROR(IF(INDEX('Task Log'!$K$2:$K$500,MATCH(1,'Task Log'!$Q$2:$Q$500,0))="","",INDEX('Task Log'!$K$2:$K$500,MATCH(1,'Task Log'!$Q$2:$Q$500,0))),"") | K5: =IFERROR(IF(INDEX('Task Log'!$N$2:$N$500,MATCH(1,'Task Log'!$Q$2:$Q$500,0))="","",INDEX('Task Log'!$N$2:$N$500,MATCH(1,'Task Log'!$Q$2:$Q$500,0))),"") | L5: =IFERROR(IF(INDEX('Task Log'!$P$2:$P$500,MATCH(1,'Task Log'!$Q$2:$Q$500,0))="","",INDEX('Task Log'!$P$2:$P$500,MATCH(1,'Task Log'!$Q$2:$Q$500,0))),"")
A6: =IFERROR(IF(MATCH(2,'Task Log'!$Q$2:$Q$500,0)>0,2,""),"") | B6: =IFERROR(IF(INDEX('Task Log'!$C$2:$C$500,MATCH(2,'Task Log'!$Q$2:$Q$500,0))="","",INDEX('Task Log'!$C$2:$C$500,MATCH(2,'Task Log'!$Q$2:$Q$500,0))),"") | C6: =IFERROR(IF(INDEX('Task Log'!$D$2:$D$500,MATCH(2,'Task Log'!$Q$2:$Q$500,0))="","",INDEX('Task Log'!$D$2:$D$500,MATCH(2,'Task Log'!$Q$2:$Q$500,0))),"") | D6: =IFERROR(IF(INDEX('Task Log'!$E$2:$E$500,MATCH(2,'Task Log'!$Q$2:$Q$500,0))="","",INDEX('Task Log'!$E$2:$E$500,MATCH(2,'Task Log'!$Q$2:$Q$500,0))),"") | E6: =IFERROR(IF(INDEX('Task Log'!$G$2:$G$500,MATCH(2,'Task Log'!$Q$2:$Q$500,0))="","",INDEX('Task Log'!$G$2:$G$500,MATCH(2,'Task Log'!$Q$2:$Q$500,0))),"") | F6: =IFERROR(IF(INDEX('Task Log'!$H$2:$H$500,MATCH(2,'Task Log'!$Q$2:$Q$500,0))="","",INDEX('Task Log'!$H$2:$H$500,MATCH(2,'Task Log'!$Q$2:$Q$500,0))),"") | G6: =IFERROR(IF(INDEX('Task Log'!$I$2:$I$500,MATCH(2,'Task Log'!$Q$2:$Q$500,0))="","",INDEX('Task Log'!$I$2:$I$500,MATCH(2,'Task Log'!$Q$2:$Q$500,0))),"") | H6: =IFERROR(IF(INDEX('Task Log'!$J$2:$J$500,MATCH(2,'Task Log'!$Q$2:$Q$500,0))="","",INDEX('Task Log'!$J$2:$J$500,MATCH(2,'Task Log'!$Q$2:$Q$500,0))),"") | I6: =IFERROR(IF(INDEX('Task Log'!$O$2:$O$500,MATCH(2,'Task Log'!$Q$2:$Q$500,0))="","",INDEX('Task Log'!$O$2:$O$500,MATCH(2,'Task Log'!$Q$2:$Q$500,0))),"") | J6: =IFERROR(IF(INDEX('Task Log'!$K$2:$K$500,MATCH(2,'Task Log'!$Q$2:$Q$500,0))="","",INDEX('Task Log'!$K$2:$K$500,MATCH(2,'Task Log'!$Q$2:$Q$500,0))),"") | K6: =IFERROR(IF(INDEX('Task Log'!$N$2:$N$500,MATCH(2,'Task Log'!$Q$2:$Q$500,0))="","",INDEX('Task Log'!$N$2:$N$500,MATCH(2,'Task Log'!$Q$2:$Q$500,0))),"") | L6: =IFERROR(IF(INDEX('Task Log'!$P$2:$P$500,MATCH(2,'Task Log'!$Q$2:$Q$500,0))="","",INDEX('Task Log'!$P$2:$P$500,MATCH(2,'Task Log'!$Q$2:$Q$500,0))),"")
A7: =IFERROR(IF(MATCH(3,'Task Log'!$Q$2:$Q$500,0)>0,3,""),"") | B7: =IFERROR(IF(INDEX('Task Log'!$C$2:$C$500,MATCH(3,'Task Log'!$Q$2:$Q$500,0))="","",INDEX('Task Log'!$C$2:$C$500,MATCH(3,'Task Log'!$Q$2:$Q$500,0))),"") | C7: =IFERROR(IF(INDEX('Task Log'!$D$2:$D$500,MATCH(3,'Task Log'!$Q$2:$Q$500,0))="","",INDEX('Task Log'!$D$2:$D$500,MATCH(3,'Task Log'!$Q$2:$Q$500,0))),"") | D7: =IFERROR(IF(INDEX('Task Log'!$E$2:$E$500,MATCH(3,'Task Log'!$Q$2:$Q$500,0))="","",INDEX('Task Log'!$E$2:$E$500,MATCH(3,'Task Log'!$Q$2:$Q$500,0))),"") | E7: =IFERROR(IF(INDEX('Task Log'!$G$2:$G$500,MATCH(3,'Task Log'!$Q$2:$Q$500,0))="","",INDEX('Task Log'!$G$2:$G$500,MATCH(3,'Task Log'!$Q$2:$Q$500,0))),"") | F7: =IFERROR(IF(INDEX('Task Log'!$H$2:$H$500,MATCH(3,'Task Log'!$Q$2:$Q$500,0))="","",INDEX('Task Log'!$H$2:$H$500,MATCH(3,'Task Log'!$Q$2:$Q$500,0))),"") | G7: =IFERROR(IF(INDEX('Task Log'!$I$2:$I$500,MATCH(3,'Task Log'!$Q$2:$Q$500,0))="","",INDEX('Task Log'!$I$2:$I$500,MATCH(3,'Task Log'!$Q$2:$Q$500,0))),"") | H7: =IFERROR(IF(INDEX('Task Log'!$J$2:$J$500,MATCH(3,'Task Log'!$Q$2:$Q$500,0))="","",INDEX('Task Log'!$J$2:$J$500,MATCH(3,'Task Log'!$Q$2:$Q$500,0))),"") | I7: =IFERROR(IF(INDEX('Task Log'!$O$2:$O$500,MATCH(3,'Task Log'!$Q$2:$Q$500,0))="","",INDEX('Task Log'!$O$2:$O$500,MATCH(3,'Task Log'!$Q$2:$Q$500,0))),"") | J7: =IFERROR(IF(INDEX('Task Log'!$K$2:$K$500,MATCH(3,'Task Log'!$Q$2:$Q$500,0))="","",INDEX('Task Log'!$K$2:$K$500,MATCH(3,'Task Log'!$Q$2:$Q$500,0))),"") | K7: =IFERROR(IF(INDEX('Task Log'!$N$2:$N$500,MATCH(3,'Task Log'!$Q$2:$Q$500,0))="","",INDEX('Task Log'!$N$2:$N$500,MATCH(3,'Task Log'!$Q$2:$Q$500,0))),"") | L7: =IFERROR(IF(INDEX('Task Log'!$P$2:$P$500,MATCH(3,'Task Log'!$Q$2:$Q$500,0))="","",INDEX('Task Log'!$P$2:$P$500,MATCH(3,'Task Log'!$Q$2:$Q$500,0))),"")
A8: =IFERROR(IF(MATCH(4,'Task Log'!$Q$2:$Q$500,0)>0,4,""),"") | B8: =IFERROR(IF(INDEX('Task Log'!$C$2:$C$500,MATCH(4,'Task Log'!$Q$2:$Q$500,0))="","",INDEX('Task Log'!$C$2:$C$500,MATCH(4,'Task Log'!$Q$2:$Q$500,0))),"") | C8: =IFERROR(IF(INDEX('Task Log'!$D$2:$D$500,MATCH(4,'Task Log'!$Q$2:$Q$500,0))="","",INDEX('Task Log'!$D$2:$D$500,MATCH(4,'Task Log'!$Q$2:$Q$500,0))),"") | D8: =IFERROR(IF(INDEX('Task Log'!$E$2:$E$500,MATCH(4,'Task Log'!$Q$2:$Q$500,0))="","",INDEX('Task Log'!$E$2:$E$500,MATCH(4,'Task Log'!$Q$2:$Q$500,0))),"") | E8: =IFERROR(IF(INDEX('Task Log'!$G$2:$G$500,MATCH(4,'Task Log'!$Q$2:$Q$500,0))="","",INDEX('Task Log'!$G$2:$G$500,MATCH(4,'Task Log'!$Q$2:$Q$500,0))),"") | F8: =IFERROR(IF(INDEX('Task Log'!$H$2:$H$500,MATCH(4,'Task Log'!$Q$2:$Q$500,0))="","",INDEX('Task Log'!$H$2:$H$500,MATCH(4,'Task Log'!$Q$2:$Q$500,0))),"") | G8: =IFERROR(IF(INDEX('Task Log'!$I$2:$I$500,MATCH(4,'Task Log'!$Q$2:$Q$500,0))="","",INDEX('Task Log'!$I$2:$I$500,MATCH(4,'Task Log'!$Q$2:$Q$500,0))),"") | H8: =IFERROR(IF(INDEX('Task Log'!$J$2:$J$500,MATCH(4,'Task Log'!$Q$2:$Q$500,0))="","",INDEX('Task Log'!$J$2:$J$500,MATCH(4,'Task Log'!$Q$2:$Q$500,0))),"") | I8: =IFERROR(IF(INDEX('Task Log'!$O$2:$O$500,MATCH(4,'Task Log'!$Q$2:$Q$500,0))="","",INDEX('Task Log'!$O$2:$O$500,MATCH(4,'Task Log'!$Q$2:$Q$500,0))),"") | J8: =IFERROR(IF(INDEX('Task Log'!$K$2:$K$500,MATCH(4,'Task Log'!$Q$2:$Q$500,0))="","",INDEX('Task Log'!$K$2:$K$500,MATCH(4,'Task Log'!$Q$2:$Q$500,0))),"") | K8: =IFERROR(IF(INDEX('Task Log'!$N$2:$N$500,MATCH(4,'Task Log'!$Q$2:$Q$500,0))="","",INDEX('Task Log'!$N$2:$N$500,MATCH(4,'Task Log'!$Q$2:$Q$500,0))),"") | L8: =IFERROR(IF(INDEX('Task Log'!$P$2:$P$500,MATCH(4,'Task Log'!$Q$2:$Q$500,0))="","",INDEX('Task Log'!$P$2:$P$500,MATCH(4,'Task Log'!$Q$2:$Q$500,0))),"")
A9: =IFERROR(IF(MATCH(5,'Task Log'!$Q$2:$Q$500,0)>0,5,""),"") | B9: =IFERROR(IF(INDEX('Task Log'!$C$2:$C$500,MATCH(5,'Task Log'!$Q$2:$Q$500,0))="","",INDEX('Task Log'!$C$2:$C$500,MATCH(5,'Task Log'!$Q$2:$Q$500,0))),"") | C9: =IFERROR(IF(INDEX('Task Log'!$D$2:$D$500,MATCH(5,'Task Log'!$Q$2:$Q$500,0))="","",INDEX('Task Log'!$D$2:$D$500,MATCH(5,'Task Log'!$Q$2:$Q$500,0))),"") | D9: =IFERROR(IF(INDEX('Task Log'!$E$2:$E$500,MATCH(5,'Task Log'!$Q$2:$Q$500,0))="","",INDEX('Task Log'!$E$2:$E$500,MATCH(5,'Task Log'!$Q$2:$Q$500,0))),"") | E9: =IFERROR(IF(INDEX('Task Log'!$G$2:$G$500,MATCH(5,'Task Log'!$Q$2:$Q$500,0))="","",INDEX('Task Log'!$G$2:$G$500,MATCH(5,'Task Log'!$Q$2:$Q$500,0))),"") | F9: =IFERROR(IF(INDEX('Task Log'!$H$2:$H$500,MATCH(5,'Task Log'!$Q$2:$Q$500,0))="","",INDEX('Task Log'!$H$2:$H$500,MATCH(5,'Task Log'!$Q$2:$Q$500,0))),"") | G9: =IFERROR(IF(INDEX('Task Log'!$I$2:$I$500,MATCH(5,'Task Log'!$Q$2:$Q$500,0))="","",INDEX('Task Log'!$I$2:$I$500,MATCH(5,'Task Log'!$Q$2:$Q$500,0))),"") | H9: =IFERROR(IF(INDEX('Task Log'!$J$2:$J$500,MATCH(5,'Task Log'!$Q$2:$Q$500,0))="","",INDEX('Task Log'!$J$2:$J$500,MATCH(5,'Task Log'!$Q$2:$Q$500,0))),"") | I9: =IFERROR(IF(INDEX('Task Log'!$O$2:$O$500,MATCH(5,'Task Log'!$Q$2:$Q$500,0))="","",INDEX('Task Log'!$O$2:$O$500,MATCH(5,'Task Log'!$Q$2:$Q$500,0))),"") | J9: =IFERROR(IF(INDEX('Task Log'!$K$2:$K$500,MATCH(5,'Task Log'!$Q$2:$Q$500,0))="","",INDEX('Task Log'!$K$2:$K$500,MATCH(5,'Task Log'!$Q$2:$Q$500,0))),"") | K9: =IFERROR(IF(INDEX('Task Log'!$N$2:$N$500,MATCH(5,'Task Log'!$Q$2:$Q$500,0))="","",INDEX('Task Log'!$N$2:$N$500,MATCH(5,'Task Log'!$Q$2:$Q$500,0))),"") | L9: =IFERROR(IF(INDEX('Task Log'!$P$2:$P$500,MATCH(5,'Task Log'!$Q$2:$Q$500,0))="","",INDEX('Task Log'!$P$2:$P$500,MATCH(5,'Task Log'!$Q$2:$Q$500,0))),"")
A10: =IFERROR(IF(MATCH(6,'Task Log'!$Q$2:$Q$500,0)>0,6,""),"") | B10: =IFERROR(IF(INDEX('Task Log'!$C$2:$C$500,MATCH(6,'Task Log'!$Q$2:$Q$500,0))="","",INDEX('Task Log'!$C$2:$C$500,MATCH(6,'Task Log'!$Q$2:$Q$500,0))),"") | C10: =IFERROR(IF(INDEX('Task Log'!$D$2:$D$500,MATCH(6,'Task Log'!$Q$2:$Q$500,0))="","",INDEX('Task Log'!$D$2:$D$500,MATCH(6,'Task Log'!$Q$2:$Q$500,0))),"") | D10: =IFERROR(IF(INDEX('Task Log'!$E$2:$E$500,MATCH(6,'Task Log'!$Q$2:$Q$500,0))="","",INDEX('Task Log'!$E$2:$E$500,MATCH(6,'Task Log'!$Q$2:$Q$500,0))),"") | E10: =IFERROR(IF(INDEX('Task Log'!$G$2:$G$500,MATCH(6,'Task Log'!$Q$2:$Q$500,0))="","",INDEX('Task Log'!$G$2:$G$500,MATCH(6,'Task Log'!$Q$2:$Q$500,0))),"") | F10: =IFERROR(IF(INDEX('Task Log'!$H$2:$H$500,MATCH(6,'Task Log'!$Q$2:$Q$500,0))="","",INDEX('Task Log'!$H$2:$H$500,MATCH(6,'Task Log'!$Q$2:$Q$500,0))),"") | G10: =IFERROR(IF(INDEX('Task Log'!$I$2:$I$500,MATCH(6,'Task Log'!$Q$2:$Q$500,0))="","",INDEX('Task Log'!$I$2:$I$500,MATCH(6,'Task Log'!$Q$2:$Q$500,0))),"") | H10: =IFERROR(IF(INDEX('Task Log'!$J$2:$J$500,MATCH(6,'Task Log'!$Q$2:$Q$500,0))="","",INDEX('Task Log'!$J$2:$J$500,MATCH(6,'Task Log'!$Q$2:$Q$500,0))),"") | I10: =IFERROR(IF(INDEX('Task Log'!$O$2:$O$500,MATCH(6,'Task Log'!$Q$2:$Q$500,0))="","",INDEX('Task Log'!$O$2:$O$500,MATCH(6,'Task Log'!$Q$2:$Q$500,0))),"") | J10: =IFERROR(IF(INDEX('Task Log'!$K$2:$K$500,MATCH(6,'Task Log'!$Q$2:$Q$500,0))="","",INDEX('Task Log'!$K$2:$K$500,MATCH(6,'Task Log'!$Q$2:$Q$500,0))),"") | K10: =IFERROR(IF(INDEX('Task Log'!$N$2:$N$500,MATCH(6,'Task Log'!$Q$2:$Q$500,0))="","",INDEX('Task Log'!$N$2:$N$500,MATCH(6,'Task Log'!$Q$2:$Q$500,0))),"") | L10: =IFERROR(IF(INDEX('Task Log'!$P$2:$P$500,MATCH(6,'Task Log'!$Q$2:$Q$500,0))="","",INDEX('Task Log'!$P$2:$P$500,MATCH(6,'Task Log'!$Q$2:$Q$500,0))),"")
A11: =IFERROR(IF(MATCH(7,'Task Log'!$Q$2:$Q$500,0)>0,7,""),"") | B11: =IFERROR(IF(INDEX('Task Log'!$C$2:$C$500,MATCH(7,'Task Log'!$Q$2:$Q$500,0))="","",INDEX('Task Log'!$C$2:$C$500,MATCH(7,'Task Log'!$Q$2:$Q$500,0))),"") | C11: =IFERROR(IF(INDEX('Task Log'!$D$2:$D$500,MATCH(7,'Task Log'!$Q$2:$Q$500,0))="","",INDEX('Task Log'!$D$2:$D$500,MATCH(7,'Task Log'!$Q$2:$Q$500,0))),"") | D11: =IFERROR(IF(INDEX('Task Log'!$E$2:$E$500,MATCH(7,'Task Log'!$Q$2:$Q$500,0))="","",INDEX('Task Log'!$E$2:$E$500,MATCH(7,'Task Log'!$Q$2:$Q$500,0))),"") | E11: =IFERROR(IF(INDEX('Task Log'!$G$2:$G$500,MATCH(7,'Task Log'!$Q$2:$Q$500,0))="","",INDEX('Task Log'!$G$2:$G$500,MATCH(7,'Task Log'!$Q$2:$Q$500,0))),"") | F11: =IFERROR(IF(INDEX('Task Log'!$H$2:$H$500,MATCH(7,'Task Log'!$Q$2:$Q$500,0))="","",INDEX('Task Log'!$H$2:$H$500,MATCH(7,'Task Log'!$Q$2:$Q$500,0))),"") | G11: =IFERROR(IF(INDEX('Task Log'!$I$2:$I$500,MATCH(7,'Task Log'!$Q$2:$Q$500,0))="","",INDEX('Task Log'!$I$2:$I$500,MATCH(7,'Task Log'!$Q$2:$Q$500,0))),"") | H11: =IFERROR(IF(INDEX('Task Log'!$J$2:$J$500,MATCH(7,'Task Log'!$Q$2:$Q$500,0))="","",INDEX('Task Log'!$J$2:$J$500,MATCH(7,'Task Log'!$Q$2:$Q$500,0))),"") | I11: =IFERROR(IF(INDEX('Task Log'!$O$2:$O$500,MATCH(7,'Task Log'!$Q$2:$Q$500,0))="","",INDEX('Task Log'!$O$2:$O$500,MATCH(7,'Task Log'!$Q$2:$Q$500,0))),"") | J11: =IFERROR(IF(INDEX('Task Log'!$K$2:$K$500,MATCH(7,'Task Log'!$Q$2:$Q$500,0))="","",INDEX('Task Log'!$K$2:$K$500,MATCH(7,'Task Log'!$Q$2:$Q$500,0))),"") | K11: =IFERROR(IF(INDEX('Task Log'!$N$2:$N$500,MATCH(7,'Task Log'!$Q$2:$Q$500,0))="","",INDEX('Task Log'!$N$2:$N$500,MATCH(7,'Task Log'!$Q$2:$Q$500,0))),"") | L11: =IFERROR(IF(INDEX('Task Log'!$P$2:$P$500,MATCH(7,'Task Log'!$Q$2:$Q$500,0))="","",INDEX('Task Log'!$P$2:$P$500,MATCH(7,'Task Log'!$Q$2:$Q$500,0))),"")
A12: =IFERROR(IF(MATCH(8,'Task Log'!$Q$2:$Q$500,0)>0,8,""),"") | B12: =IFERROR(IF(INDEX('Task Log'!$C$2:$C$500,MATCH(8,'Task Log'!$Q$2:$Q$500,0))="","",INDEX('Task Log'!$C$2:$C$500,MATCH(8,'Task Log'!$Q$2:$Q$500,0))),"") | C12: =IFERROR(IF(INDEX('Task Log'!$D$2:$D$500,MATCH(8,'Task Log'!$Q$2:$Q$500,0))="","",INDEX('Task Log'!$D$2:$D$500,MATCH(8,'Task Log'!$Q$2:$Q$500,0))),"") | D12: =IFERROR(IF(INDEX('Task Log'!$E$2:$E$500,MATCH(8,'Task Log'!$Q$2:$Q$500,0))="","",INDEX('Task Log'!$E$2:$E$500,MATCH(8,'Task Log'!$Q$2:$Q$500,0))),"") | E12: =IFERROR(IF(INDEX('Task Log'!$G$2:$G$500,MATCH(8,'Task Log'!$Q$2:$Q$500,0))="","",INDEX('Task Log'!$G$2:$G$500,MATCH(8,'Task Log'!$Q$2:$Q$500,0))),"") | F12: =IFERROR(IF(INDEX('Task Log'!$H$2:$H$500,MATCH(8,'Task Log'!$Q$2:$Q$500,0))="","",INDEX('Task Log'!$H$2:$H$500,MATCH(8,'Task Log'!$Q$2:$Q$500,0))),"") | G12: =IFERROR(IF(INDEX('Task Log'!$I$2:$I$500,MATCH(8,'Task Log'!$Q$2:$Q$500,0))="","",INDEX('Task Log'!$I$2:$I$500,MATCH(8,'Task Log'!$Q$2:$Q$500,0))),"") | H12: =IFERROR(IF(INDEX('Task Log'!$J$2:$J$500,MATCH(8,'Task Log'!$Q$2:$Q$500,0))="","",INDEX('Task Log'!$J$2:$J$500,MATCH(8,'Task Log'!$Q$2:$Q$500,0))),"") | I12: =IFERROR(IF(INDEX('Task Log'!$O$2:$O$500,MATCH(8,'Task Log'!$Q$2:$Q$500,0))="","",INDEX('Task Log'!$O$2:$O$500,MATCH(8,'Task Log'!$Q$2:$Q$500,0))),"") | J12: =IFERROR(IF(INDEX('Task Log'!$K$2:$K$500,MATCH(8,'Task Log'!$Q$2:$Q$500,0))="","",INDEX('Task Log'!$K$2:$K$500,MATCH(8,'Task Log'!$Q$2:$Q$500,0))),"") | K12: =IFERROR(IF(INDEX('Task Log'!$N$2:$N$500,MATCH(8,'Task Log'!$Q$2:$Q$500,0))="","",INDEX('Task Log'!$N$2:$N$500,MATCH(8,'Task Log'!$Q$2:$Q$500,0))),"") | L12: =IFERROR(IF(INDEX('Task Log'!$P$2:$P$500,MATCH(8,'Task Log'!$Q$2:$Q$500,0))="","",INDEX('Task Log'!$P$2:$P$500,MATCH(8,'Task Log'!$Q$2:$Q$500,0))),"")
A13: =IFERROR(IF(MATCH(9,'Task Log'!$Q$2:$Q$500,0)>0,9,""),"") | B13: =IFERROR(IF(INDEX('Task Log'!$C$2:$C$500,MATCH(9,'Task Log'!$Q$2:$Q$500,0))="","",INDEX('Task Log'!$C$2:$C$500,MATCH(9,'Task Log'!$Q$2:$Q$500,0))),"") | C13: =IFERROR(IF(INDEX('Task Log'!$D$2:$D$500,MATCH(9,'Task Log'!$Q$2:$Q$500,0))="","",INDEX('Task Log'!$D$2:$D$500,MATCH(9,'Task Log'!$Q$2:$Q$500,0))),"") | D13: =IFERROR(IF(INDEX('Task Log'!$E$2:$E$500,MATCH(9,'Task Log'!$Q$2:$Q$500,0))="","",INDEX('Task Log'!$E$2:$E$500,MATCH(9,'Task Log'!$Q$2:$Q$500,0))),"") | E13: =IFERROR(IF(INDEX('Task Log'!$G$2:$G$500,MATCH(9,'Task Log'!$Q$2:$Q$500,0))="","",INDEX('Task Log'!$G$2:$G$500,MATCH(9,'Task Log'!$Q$2:$Q$500,0))),"") | F13: =IFERROR(IF(INDEX('Task Log'!$H$2:$H$500,MATCH(9,'Task Log'!$Q$2:$Q$500,0))="","",INDEX('Task Log'!$H$2:$H$500,MATCH(9,'Task Log'!$Q$2:$Q$500,0))),"") | G13: =IFERROR(IF(INDEX('Task Log'!$I$2:$I$500,MATCH(9,'Task Log'!$Q$2:$Q$500,0))="","",INDEX('Task Log'!$I$2:$I$500,MATCH(9,'Task Log'!$Q$2:$Q$500,0))),"") | H13: =IFERROR(IF(INDEX('Task Log'!$J$2:$J$500,MATCH(9,'Task Log'!$Q$2:$Q$500,0))="","",INDEX('Task Log'!$J$2:$J$500,MATCH(9,'Task Log'!$Q$2:$Q$500,0))),"") | I13: =IFERROR(IF(INDEX('Task Log'!$O$2:$O$500,MATCH(9,'Task Log'!$Q$2:$Q$500,0))="","",INDEX('Task Log'!$O$2:$O$500,MATCH(9,'Task Log'!$Q$2:$Q$500,0))),"") | J13: =IFERROR(IF(INDEX('Task Log'!$K$2:$K$500,MATCH(9,'Task Log'!$Q$2:$Q$500,0))="","",INDEX('Task Log'!$K$2:$K$500,MATCH(9,'Task Log'!$Q$2:$Q$500,0))),"") | K13: =IFERROR(IF(INDEX('Task Log'!$N$2:$N$500,MATCH(9,'Task Log'!$Q$2:$Q$500,0))="","",INDEX('Task Log'!$N$2:$N$500,MATCH(9,'Task Log'!$Q$2:$Q$500,0))),"") | L13: =IFERROR(IF(INDEX('Task Log'!$P$2:$P$500,MATCH(9,'Task Log'!$Q$2:$Q$500,0))="","",INDEX('Task Log'!$P$2:$P$500,MATCH(9,'Task Log'!$Q$2:$Q$500,0))),"")
A14: =IFERROR(IF(MATCH(10,'Task Log'!$Q$2:$Q$500,0)>0,10,""),"") | B14: =IFERROR(IF(INDEX('Task Log'!$C$2:$C$500,MATCH(10,'Task Log'!$Q$2:$Q$500,0))="","",INDEX('Task Log'!$C$2:$C$500,MATCH(10,'Task Log'!$Q$2:$Q$500,0))),"") | C14: =IFERROR(IF(INDEX('Task Log'!$D$2:$D$500,MATCH(10,'Task Log'!$Q$2:$Q$500,0))="","",INDEX('Task Log'!$D$2:$D$500,MATCH(10,'Task Log'!$Q$2:$Q$500,0))),"") | D14: =IFERROR(IF(INDEX('Task Log'!$E$2:$E$500,MATCH(10,'Task Log'!$Q$2:$Q$500,0))="","",INDEX('Task Log'!$E$2:$E$500,MATCH(10,'Task Log'!$Q$2:$Q$500,0))),"") | E14: =IFERROR(IF(INDEX('Task Log'!$G$2:$G$500,MATCH(10,'Task Log'!$Q$2:$Q$500,0))="","",INDEX('Task Log'!$G$2:$G$500,MATCH(10,'Task Log'!$Q$2:$Q$500,0))),"") | F14: =IFERROR(IF(INDEX('Task Log'!$H$2:$H$500,MATCH(10,'Task Log'!$Q$2:$Q$500,0))="","",INDEX('Task Log'!$H$2:$H$500,MATCH(10,'Task Log'!$Q$2:$Q$500,0))),"") | G14: =IFERROR(IF(INDEX('Task Log'!$I$2:$I$500,MATCH(10,'Task Log'!$Q$2:$Q$500,0))="","",INDEX('Task Log'!$I$2:$I$500,MATCH(10,'Task Log'!$Q$2:$Q$500,0))),"") | H14: =IFERROR(IF(INDEX('Task Log'!$J$2:$J$500,MATCH(10,'Task Log'!$Q$2:$Q$500,0))="","",INDEX('Task Log'!$J$2:$J$500,MATCH(10,'Task Log'!$Q$2:$Q$500,0))),"") | I14: =IFERROR(IF(INDEX('Task Log'!$O$2:$O$500,MATCH(10,'Task Log'!$Q$2:$Q$500,0))="","",INDEX('Task Log'!$O$2:$O$500,MATCH(10,'Task Log'!$Q$2:$Q$500,0))),"") | J14: =IFERROR(IF(INDEX('Task Log'!$K$2:$K$500,MATCH(10,'Task Log'!$Q$2:$Q$500,0))="","",INDEX('Task Log'!$K$2:$K$500,MATCH(10,'Task Log'!$Q$2:$Q$500,0))),"") | K14: =IFERROR(IF(INDEX('Task Log'!$N$2:$N$500,MATCH(10,'Task Log'!$Q$2:$Q$500,0))="","",INDEX('Task Log'!$N$2:$N$500,MATCH(10,'Task Log'!$Q$2:$Q$500,0))),"") | L14: =IFERROR(IF(INDEX('Task Log'!$P$2:$P$500,MATCH(10,'Task Log'!$Q$2:$Q$500,0))="","",INDEX('Task Log'!$P$2:$P$500,MATCH(10,'Task Log'!$Q$2:$Q$500,0))),"")
A15: =IFERROR(IF(MATCH(11,'Task Log'!$Q$2:$Q$500,0)>0,11,""),"") | B15: =IFERROR(IF(INDEX('Task Log'!$C$2:$C$500,MATCH(11,'Task Log'!$Q$2:$Q$500,0))="","",INDEX('Task Log'!$C$2:$C$500,MATCH(11,'Task Log'!$Q$2:$Q$500,0))),"") | C15: =IFERROR(IF(INDEX('Task Log'!$D$2:$D$500,MATCH(11,'Task Log'!$Q$2:$Q$500,0))="","",INDEX('Task Log'!$D$2:$D$500,MATCH(11,'Task Log'!$Q$2:$Q$500,0))),"") | D15: =IFERROR(IF(INDEX('Task Log'!$E$2:$E$500,MATCH(11,'Task Log'!$Q$2:$Q$500,0))="","",INDEX('Task Log'!$E$2:$E$500,MATCH(11,'Task Log'!$Q$2:$Q$500,0))),"") | E15: =IFERROR(IF(INDEX('Task Log'!$G$2:$G$500,MATCH(11,'Task Log'!$Q$2:$Q$500,0))="","",INDEX('Task Log'!$G$2:$G$500,MATCH(11,'Task Log'!$Q$2:$Q$500,0))),"") | F15: =IFERROR(IF(INDEX('Task Log'!$H$2:$H$500,MATCH(11,'Task Log'!$Q$2:$Q$500,0))="","",INDEX('Task Log'!$H$2:$H$500,MATCH(11,'Task Log'!$Q$2:$Q$500,0))),"") | G15: =IFERROR(IF(INDEX('Task Log'!$I$2:$I$500,MATCH(11,'Task Log'!$Q$2:$Q$500,0))="","",INDEX('Task Log'!$I$2:$I$500,MATCH(11,'Task Log'!$Q$2:$Q$500,0))),"") | H15: =IFERROR(IF(INDEX('Task Log'!$J$2:$J$500,MATCH(11,'Task Log'!$Q$2:$Q$500,0))="","",INDEX('Task Log'!$J$2:$J$500,MATCH(11,'Task Log'!$Q$2:$Q$500,0))),"") | I15: =IFERROR(IF(INDEX('Task Log'!$O$2:$O$500,MATCH(11,'Task Log'!$Q$2:$Q$500,0))="","",INDEX('Task Log'!$O$2:$O$500,MATCH(11,'Task Log'!$Q$2:$Q$500,0))),"") | J15: =IFERROR(IF(INDEX('Task Log'!$K$2:$K$500,MATCH(11,'Task Log'!$Q$2:$Q$500,0))="","",INDEX('Task Log'!$K$2:$K$500,MATCH(11,'Task Log'!$Q$2:$Q$500,0))),"") | K15: =IFERROR(IF(INDEX('Task Log'!$N$2:$N$500,MATCH(11,'Task Log'!$Q$2:$Q$500,0))="","",INDEX('Task Log'!$N$2:$N$500,MATCH(11,'Task Log'!$Q$2:$Q$500,0))),"") | L15: =IFERROR(IF(INDEX('Task Log'!$P$2:$P$500,MATCH(11,'Task Log'!$Q$2:$Q$500,0))="","",INDEX('Task Log'!$P$2:$P$500,MATCH(11,'Task Log'!$Q$2:$Q$500,0))),"")
A16: =IFERROR(IF(MATCH(12,'Task Log'!$Q$2:$Q$500,0)>0,12,""),"") | B16: =IFERROR(IF(INDEX('Task Log'!$C$2:$C$500,MATCH(12,'Task Log'!$Q$2:$Q$500,0))="","",INDEX('Task Log'!$C$2:$C$500,MATCH(12,'Task Log'!$Q$2:$Q$500,0))),"") | C16: =IFERROR(IF(INDEX('Task Log'!$D$2:$D$500,MATCH(12,'Task Log'!$Q$2:$Q$500,0))="","",INDEX('Task Log'!$D$2:$D$500,MATCH(12,'Task Log'!$Q$2:$Q$500,0))),"") | D16: =IFERROR(IF(INDEX('Task Log'!$E$2:$E$500,MATCH(12,'Task Log'!$Q$2:$Q$500,0))="","",INDEX('Task Log'!$E$2:$E$500,MATCH(12,'Task Log'!$Q$2:$Q$500,0))),"") | E16: =IFERROR(IF(INDEX('Task Log'!$G$2:$G$500,MATCH(12,'Task Log'!$Q$2:$Q$500,0))="","",INDEX('Task Log'!$G$2:$G$500,MATCH(12,'Task Log'!$Q$2:$Q$500,0))),"") | F16: =IFERROR(IF(INDEX('Task Log'!$H$2:$H$500,MATCH(12,'Task Log'!$Q$2:$Q$500,0))="","",INDEX('Task Log'!$H$2:$H$500,MATCH(12,'Task Log'!$Q$2:$Q$500,0))),"") | G16: =IFERROR(IF(INDEX('Task Log'!$I$2:$I$500,MATCH(12,'Task Log'!$Q$2:$Q$500,0))="","",INDEX('Task Log'!$I$2:$I$500,MATCH(12,'Task Log'!$Q$2:$Q$500,0))),"") | H16: =IFERROR(IF(INDEX('Task Log'!$J$2:$J$500,MATCH(12,'Task Log'!$Q$2:$Q$500,0))="","",INDEX('Task Log'!$J$2:$J$500,MATCH(12,'Task Log'!$Q$2:$Q$500,0))),"") | I16: =IFERROR(IF(INDEX('Task Log'!$O$2:$O$500,MATCH(12,'Task Log'!$Q$2:$Q$500,0))="","",INDEX('Task Log'!$O$2:$O$500,MATCH(12,'Task Log'!$Q$2:$Q$500,0))),"") | J16: =IFERROR(IF(INDEX('Task Log'!$K$2:$K$500,MATCH(12,'Task Log'!$Q$2:$Q$500,0))="","",INDEX('Task Log'!$K$2:$K$500,MATCH(12,'Task Log'!$Q$2:$Q$500,0))),"") | K16: =IFERROR(IF(INDEX('Task Log'!$N$2:$N$500,MATCH(12,'Task Log'!$Q$2:$Q$500,0))="","",INDEX('Task Log'!$N$2:$N$500,MATCH(12,'Task Log'!$Q$2:$Q$500,0))),"") | L16: =IFERROR(IF(INDEX('Task Log'!$P$2:$P$500,MATCH(12,'Task Log'!$Q$2:$Q$500,0))="","",INDEX('Task Log'!$P$2:$P$500,MATCH(12,'Task Log'!$Q$2:$Q$500,0))),"")
A17: =IFERROR(IF(MATCH(13,'Task Log'!$Q$2:$Q$500,0)>0,13,""),"") | B17: =IFERROR(IF(INDEX('Task Log'!$C$2:$C$500,MATCH(13,'Task Log'!$Q$2:$Q$500,0))="","",INDEX('Task Log'!$C$2:$C$500,MATCH(13,'Task Log'!$Q$2:$Q$500,0))),"") | C17: =IFERROR(IF(INDEX('Task Log'!$D$2:$D$500,MATCH(13,'Task Log'!$Q$2:$Q$500,0))="","",INDEX('Task Log'!$D$2:$D$500,MATCH(13,'Task Log'!$Q$2:$Q$500,0))),"") | D17: =IFERROR(IF(INDEX('Task Log'!$E$2:$E$500,MATCH(13,'Task Log'!$Q$2:$Q$500,0))="","",INDEX('Task Log'!$E$2:$E$500,MATCH(13,'Task Log'!$Q$2:$Q$500,0))),"") | E17: =IFERROR(IF(INDEX('Task Log'!$G$2:$G$500,MATCH(13,'Task Log'!$Q$2:$Q$500,0))="","",INDEX('Task Log'!$G$2:$G$500,MATCH(13,'Task Log'!$Q$2:$Q$500,0))),"") | F17: =IFERROR(IF(INDEX('Task Log'!$H$2:$H$500,MATCH(13,'Task Log'!$Q$2:$Q$500,0))="","",INDEX('Task Log'!$H$2:$H$500,MATCH(13,'Task Log'!$Q$2:$Q$500,0))),"") | G17: =IFERROR(IF(INDEX('Task Log'!$I$2:$I$500,MATCH(13,'Task Log'!$Q$2:$Q$500,0))="","",INDEX('Task Log'!$I$2:$I$500,MATCH(13,'Task Log'!$Q$2:$Q$500,0))),"") | H17: =IFERROR(IF(INDEX('Task Log'!$J$2:$J$500,MATCH(13,'Task Log'!$Q$2:$Q$500,0))="","",INDEX('Task Log'!$J$2:$J$500,MATCH(13,'Task Log'!$Q$2:$Q$500,0))),"") | I17: =IFERROR(IF(INDEX('Task Log'!$O$2:$O$500,MATCH(13,'Task Log'!$Q$2:$Q$500,0))="","",INDEX('Task Log'!$O$2:$O$500,MATCH(13,'Task Log'!$Q$2:$Q$500,0))),"") | J17: =IFERROR(IF(INDEX('Task Log'!$K$2:$K$500,MATCH(13,'Task Log'!$Q$2:$Q$500,0))="","",INDEX('Task Log'!$K$2:$K$500,MATCH(13,'Task Log'!$Q$2:$Q$500,0))),"") | K17: =IFERROR(IF(INDEX('Task Log'!$N$2:$N$500,MATCH(13,'Task Log'!$Q$2:$Q$500,0))="","",INDEX('Task Log'!$N$2:$N$500,MATCH(13,'Task Log'!$Q$2:$Q$500,0))),"") | L17: =IFERROR(IF(INDEX('Task Log'!$P$2:$P$500,MATCH(13,'Task Log'!$Q$2:$Q$500,0))="","",INDEX('Task Log'!$P$2:$P$500,MATCH(13,'Task Log'!$Q$2:$Q$500,0))),"")
A18: =IFERROR(IF(MATCH(14,'Task Log'!$Q$2:$Q$500,0)>0,14,""),"") | B18: =IFERROR(IF(INDEX('Task Log'!$C$2:$C$500,MATCH(14,'Task Log'!$Q$2:$Q$500,0))="","",INDEX('Task Log'!$C$2:$C$500,MATCH(14,'Task Log'!$Q$2:$Q$500,0))),"") | C18: =IFERROR(IF(INDEX('Task Log'!$D$2:$D$500,MATCH(14,'Task Log'!$Q$2:$Q$500,0))="","",INDEX('Task Log'!$D$2:$D$500,MATCH(14,'Task Log'!$Q$2:$Q$500,0))),"") | D18: =IFERROR(IF(INDEX('Task Log'!$E$2:$E$500,MATCH(14,'Task Log'!$Q$2:$Q$500,0))="","",INDEX('Task Log'!$E$2:$E$500,MATCH(14,'Task Log'!$Q$2:$Q$500,0))),"") | E18: =IFERROR(IF(INDEX('Task Log'!$G$2:$G$500,MATCH(14,'Task Log'!$Q$2:$Q$500,0))="","",INDEX('Task Log'!$G$2:$G$500,MATCH(14,'Task Log'!$Q$2:$Q$500,0))),"") | F18: =IFERROR(IF(INDEX('Task Log'!$H$2:$H$500,MATCH(14,'Task Log'!$Q$2:$Q$500,0))="","",INDEX('Task Log'!$H$2:$H$500,MATCH(14,'Task Log'!$Q$2:$Q$500,0))),"") | G18: =IFERROR(IF(INDEX('Task Log'!$I$2:$I$500,MATCH(14,'Task Log'!$Q$2:$Q$500,0))="","",INDEX('Task Log'!$I$2:$I$500,MATCH(14,'Task Log'!$Q$2:$Q$500,0))),"") | H18: =IFERROR(IF(INDEX('Task Log'!$J$2:$J$500,MATCH(14,'Task Log'!$Q$2:$Q$500,0))="","",INDEX('Task Log'!$J$2:$J$500,MATCH(14,'Task Log'!$Q$2:$Q$500,0))),"") | I18: =IFERROR(IF(INDEX('Task Log'!$O$2:$O$500,MATCH(14,'Task Log'!$Q$2:$Q$500,0))="","",INDEX('Task Log'!$O$2:$O$500,MATCH(14,'Task Log'!$Q$2:$Q$500,0))),"") | J18: =IFERROR(IF(INDEX('Task Log'!$K$2:$K$500,MATCH(14,'Task Log'!$Q$2:$Q$500,0))="","",INDEX('Task Log'!$K$2:$K$500,MATCH(14,'Task Log'!$Q$2:$Q$500,0))),"") | K18: =IFERROR(IF(INDEX('Task Log'!$N$2:$N$500,MATCH(14,'Task Log'!$Q$2:$Q$500,0))="","",INDEX('Task Log'!$N$2:$N$500,MATCH(14,'Task Log'!$Q$2:$Q$500,0))),"") | L18: =IFERROR(IF(INDEX('Task Log'!$P$2:$P$500,MATCH(14,'Task Log'!$Q$2:$Q$500,0))="","",INDEX('Task Log'!$P$2:$P$500,MATCH(14,'Task Log'!$Q$2:$Q$500,0))),"")
A19: =IFERROR(IF(MATCH(15,'Task Log'!$Q$2:$Q$500,0)>0,15,""),"") | B19: =IFERROR(IF(INDEX('Task Log'!$C$2:$C$500,MATCH(15,'Task Log'!$Q$2:$Q$500,0))="","",INDEX('Task Log'!$C$2:$C$500,MATCH(15,'Task Log'!$Q$2:$Q$500,0))),"") | C19: =IFERROR(IF(INDEX('Task Log'!$D$2:$D$500,MATCH(15,'Task Log'!$Q$2:$Q$500,0))="","",INDEX('Task Log'!$D$2:$D$500,MATCH(15,'Task Log'!$Q$2:$Q$500,0))),"") | D19: =IFERROR(IF(INDEX('Task Log'!$E$2:$E$500,MATCH(15,'Task Log'!$Q$2:$Q$500,0))="","",INDEX('Task Log'!$E$2:$E$500,MATCH(15,'Task Log'!$Q$2:$Q$500,0))),"") | E19: =IFERROR(IF(INDEX('Task Log'!$G$2:$G$500,MATCH(15,'Task Log'!$Q$2:$Q$500,0))="","",INDEX('Task Log'!$G$2:$G$500,MATCH(15,'Task Log'!$Q$2:$Q$500,0))),"") | F19: =IFERROR(IF(INDEX('Task Log'!$H$2:$H$500,MATCH(15,'Task Log'!$Q$2:$Q$500,0))="","",INDEX('Task Log'!$H$2:$H$500,MATCH(15,'Task Log'!$Q$2:$Q$500,0))),"") | G19: =IFERROR(IF(INDEX('Task Log'!$I$2:$I$500,MATCH(15,'Task Log'!$Q$2:$Q$500,0))="","",INDEX('Task Log'!$I$2:$I$500,MATCH(15,'Task Log'!$Q$2:$Q$500,0))),"") | H19: =IFERROR(IF(INDEX('Task Log'!$J$2:$J$500,MATCH(15,'Task Log'!$Q$2:$Q$500,0))="","",INDEX('Task Log'!$J$2:$J$500,MATCH(15,'Task Log'!$Q$2:$Q$500,0))),"") | I19: =IFERROR(IF(INDEX('Task Log'!$O$2:$O$500,MATCH(15,'Task Log'!$Q$2:$Q$500,0))="","",INDEX('Task Log'!$O$2:$O$500,MATCH(15,'Task Log'!$Q$2:$Q$500,0))),"") | J19: =IFERROR(IF(INDEX('Task Log'!$K$2:$K$500,MATCH(15,'Task Log'!$Q$2:$Q$500,0))="","",INDEX('Task Log'!$K$2:$K$500,MATCH(15,'Task Log'!$Q$2:$Q$500,0))),"") | K19: =IFERROR(IF(INDEX('Task Log'!$N$2:$N$500,MATCH(15,'Task Log'!$Q$2:$Q$500,0))="","",INDEX('Task Log'!$N$2:$N$500,MATCH(15,'Task Log'!$Q$2:$Q$500,0))),"") | L19: =IFERROR(IF(INDEX('Task Log'!$P$2:$P$500,MATCH(15,'Task Log'!$Q$2:$Q$500,0))="","",INDEX('Task Log'!$P$2:$P$500,MATCH(15,'Task Log'!$Q$2:$Q$500,0))),"")
A20: =IFERROR(IF(MATCH(16,'Task Log'!$Q$2:$Q$500,0)>0,16,""),"") | B20: =IFERROR(IF(INDEX('Task Log'!$C$2:$C$500,MATCH(16,'Task Log'!$Q$2:$Q$500,0))="","",INDEX('Task Log'!$C$2:$C$500,MATCH(16,'Task Log'!$Q$2:$Q$500,0))),"") | C20: =IFERROR(IF(INDEX('Task Log'!$D$2:$D$500,MATCH(16,'Task Log'!$Q$2:$Q$500,0))="","",INDEX('Task Log'!$D$2:$D$500,MATCH(16,'Task Log'!$Q$2:$Q$500,0))),"") | D20: =IFERROR(IF(INDEX('Task Log'!$E$2:$E$500,MATCH(16,'Task Log'!$Q$2:$Q$500,0))="","",INDEX('Task Log'!$E$2:$E$500,MATCH(16,'Task Log'!$Q$2:$Q$500,0))),"") | E20: =IFERROR(IF(INDEX('Task Log'!$G$2:$G$500,MATCH(16,'Task Log'!$Q$2:$Q$500,0))="","",INDEX('Task Log'!$G$2:$G$500,MATCH(16,'Task Log'!$Q$2:$Q$500,0))),"") | F20: =IFERROR(IF(INDEX('Task Log'!$H$2:$H$500,MATCH(16,'Task Log'!$Q$2:$Q$500,0))="","",INDEX('Task Log'!$H$2:$H$500,MATCH(16,'Task Log'!$Q$2:$Q$500,0))),"") | G20: =IFERROR(IF(INDEX('Task Log'!$I$2:$I$500,MATCH(16,'Task Log'!$Q$2:$Q$500,0))="","",INDEX('Task Log'!$I$2:$I$500,MATCH(16,'Task Log'!$Q$2:$Q$500,0))),"") | H20: =IFERROR(IF(INDEX('Task Log'!$J$2:$J$500,MATCH(16,'Task Log'!$Q$2:$Q$500,0))="","",INDEX('Task Log'!$J$2:$J$500,MATCH(16,'Task Log'!$Q$2:$Q$500,0))),"") | I20: =IFERROR(IF(INDEX('Task Log'!$O$2:$O$500,MATCH(16,'Task Log'!$Q$2:$Q$500,0))="","",INDEX('Task Log'!$O$2:$O$500,MATCH(16,'Task Log'!$Q$2:$Q$500,0))),"") | J20: =IFERROR(IF(INDEX('Task Log'!$K$2:$K$500,MATCH(16,'Task Log'!$Q$2:$Q$500,0))="","",INDEX('Task Log'!$K$2:$K$500,MATCH(16,'Task Log'!$Q$2:$Q$500,0))),"") | K20: =IFERROR(IF(INDEX('Task Log'!$N$2:$N$500,MATCH(16,'Task Log'!$Q$2:$Q$500,0))="","",INDEX('Task Log'!$N$2:$N$500,MATCH(16,'Task Log'!$Q$2:$Q$500,0))),"") | L20: =IFERROR(IF(INDEX('Task Log'!$P$2:$P$500,MATCH(16,'Task Log'!$Q$2:$Q$500,0))="","",INDEX('Task Log'!$P$2:$P$500,MATCH(16,'Task Log'!$Q$2:$Q$500,0))),"")
A21: =IFERROR(IF(MATCH(17,'Task Log'!$Q$2:$Q$500,0)>0,17,""),"") | B21: =IFERROR(IF(INDEX('Task Log'!$C$2:$C$500,MATCH(17,'Task Log'!$Q$2:$Q$500,0))="","",INDEX('Task Log'!$C$2:$C$500,MATCH(17,'Task Log'!$Q$2:$Q$500,0))),"") | C21: =IFERROR(IF(INDEX('Task Log'!$D$2:$D$500,MATCH(17,'Task Log'!$Q$2:$Q$500,0))="","",INDEX('Task Log'!$D$2:$D$500,MATCH(17,'Task Log'!$Q$2:$Q$500,0))),"") | D21: =IFERROR(IF(INDEX('Task Log'!$E$2:$E$500,MATCH(17,'Task Log'!$Q$2:$Q$500,0))="","",INDEX('Task Log'!$E$2:$E$500,MATCH(17,'Task Log'!$Q$2:$Q$500,0))),"") | E21: =IFERROR(IF(INDEX('Task Log'!$G$2:$G$500,MATCH(17,'Task Log'!$Q$2:$Q$500,0))="","",INDEX('Task Log'!$G$2:$G$500,MATCH(17,'Task Log'!$Q$2:$Q$500,0))),"") | F21: =IFERROR(IF(INDEX('Task Log'!$H$2:$H$500,MATCH(17,'Task Log'!$Q$2:$Q$500,0))="","",INDEX('Task Log'!$H$2:$H$500,MATCH(17,'Task Log'!$Q$2:$Q$500,0))),"") | G21: =IFERROR(IF(INDEX('Task Log'!$I$2:$I$500,MATCH(17,'Task Log'!$Q$2:$Q$500,0))="","",INDEX('Task Log'!$I$2:$I$500,MATCH(17,'Task Log'!$Q$2:$Q$500,0))),"") | H21: =IFERROR(IF(INDEX('Task Log'!$J$2:$J$500,MATCH(17,'Task Log'!$Q$2:$Q$500,0))="","",INDEX('Task Log'!$J$2:$J$500,MATCH(17,'Task Log'!$Q$2:$Q$500,0))),"") | I21: =IFERROR(IF(INDEX('Task Log'!$O$2:$O$500,MATCH(17,'Task Log'!$Q$2:$Q$500,0))="","",INDEX('Task Log'!$O$2:$O$500,MATCH(17,'Task Log'!$Q$2:$Q$500,0))),"") | J21: =IFERROR(IF(INDEX('Task Log'!$K$2:$K$500,MATCH(17,'Task Log'!$Q$2:$Q$500,0))="","",INDEX('Task Log'!$K$2:$K$500,MATCH(17,'Task Log'!$Q$2:$Q$500,0))),"") | K21: =IFERROR(IF(INDEX('Task Log'!$N$2:$N$500,MATCH(17,'Task Log'!$Q$2:$Q$500,0))="","",INDEX('Task Log'!$N$2:$N$500,MATCH(17,'Task Log'!$Q$2:$Q$500,0))),"") | L21: =IFERROR(IF(INDEX('Task Log'!$P$2:$P$500,MATCH(17,'Task Log'!$Q$2:$Q$500,0))="","",INDEX('Task Log'!$P$2:$P$500,MATCH(17,'Task Log'!$Q$2:$Q$500,0))),"")
A22: =IFERROR(IF(MATCH(18,'Task Log'!$Q$2:$Q$500,0)>0,18,""),"") | B22: =IFERROR(IF(INDEX('Task Log'!$C$2:$C$500,MATCH(18,'Task Log'!$Q$2:$Q$500,0))="","",INDEX('Task Log'!$C$2:$C$500,MATCH(18,'Task Log'!$Q$2:$Q$500,0))),"") | C22: =IFERROR(IF(INDEX('Task Log'!$D$2:$D$500,MATCH(18,'Task Log'!$Q$2:$Q$500,0))="","",INDEX('Task Log'!$D$2:$D$500,MATCH(18,'Task Log'!$Q$2:$Q$500,0))),"") | D22: =IFERROR(IF(INDEX('Task Log'!$E$2:$E$500,MATCH(18,'Task Log'!$Q$2:$Q$500,0))="","",INDEX('Task Log'!$E$2:$E$500,MATCH(18,'Task Log'!$Q$2:$Q$500,0))),"") | E22: =IFERROR(IF(INDEX('Task Log'!$G$2:$G$500,MATCH(18,'Task Log'!$Q$2:$Q$500,0))="","",INDEX('Task Log'!$G$2:$G$500,MATCH(18,'Task Log'!$Q$2:$Q$500,0))),"") | F22: =IFERROR(IF(INDEX('Task Log'!$H$2:$H$500,MATCH(18,'Task Log'!$Q$2:$Q$500,0))="","",INDEX('Task Log'!$H$2:$H$500,MATCH(18,'Task Log'!$Q$2:$Q$500,0))),"") | G22: =IFERROR(IF(INDEX('Task Log'!$I$2:$I$500,MATCH(18,'Task Log'!$Q$2:$Q$500,0))="","",INDEX('Task Log'!$I$2:$I$500,MATCH(18,'Task Log'!$Q$2:$Q$500,0))),"") | H22: =IFERROR(IF(INDEX('Task Log'!$J$2:$J$500,MATCH(18,'Task Log'!$Q$2:$Q$500,0))="","",INDEX('Task Log'!$J$2:$J$500,MATCH(18,'Task Log'!$Q$2:$Q$500,0))),"") | I22: =IFERROR(IF(INDEX('Task Log'!$O$2:$O$500,MATCH(18,'Task Log'!$Q$2:$Q$500,0))="","",INDEX('Task Log'!$O$2:$O$500,MATCH(18,'Task Log'!$Q$2:$Q$500,0))),"") | J22: =IFERROR(IF(INDEX('Task Log'!$K$2:$K$500,MATCH(18,'Task Log'!$Q$2:$Q$500,0))="","",INDEX('Task Log'!$K$2:$K$500,MATCH(18,'Task Log'!$Q$2:$Q$500,0))),"") | K22: =IFERROR(IF(INDEX('Task Log'!$N$2:$N$500,MATCH(18,'Task Log'!$Q$2:$Q$500,0))="","",INDEX('Task Log'!$N$2:$N$500,MATCH(18,'Task Log'!$Q$2:$Q$500,0))),"") | L22: =IFERROR(IF(INDEX('Task Log'!$P$2:$P$500,MATCH(18,'Task Log'!$Q$2:$Q$500,0))="","",INDEX('Task Log'!$P$2:$P$500,MATCH(18,'Task Log'!$Q$2:$Q$500,0))),"")
A23: =IFERROR(IF(MATCH(19,'Task Log'!$Q$2:$Q$500,0)>0,19,""),"") | B23: =IFERROR(IF(INDEX('Task Log'!$C$2:$C$500,MATCH(19,'Task Log'!$Q$2:$Q$500,0))="","",INDEX('Task Log'!$C$2:$C$500,MATCH(19,'Task Log'!$Q$2:$Q$500,0))),"") | C23: =IFERROR(IF(INDEX('Task Log'!$D$2:$D$500,MATCH(19,'Task Log'!$Q$2:$Q$500,0))="","",INDEX('Task Log'!$D$2:$D$500,MATCH(19,'Task Log'!$Q$2:$Q$500,0))),"") | D23: =IFERROR(IF(INDEX('Task Log'!$E$2:$E$500,MATCH(19,'Task Log'!$Q$2:$Q$500,0))="","",INDEX('Task Log'!$E$2:$E$500,MATCH(19,'Task Log'!$Q$2:$Q$500,0))),"") | E23: =IFERROR(IF(INDEX('Task Log'!$G$2:$G$500,MATCH(19,'Task Log'!$Q$2:$Q$500,0))="","",INDEX('Task Log'!$G$2:$G$500,MATCH(19,'Task Log'!$Q$2:$Q$500,0))),"") | F23: =IFERROR(IF(INDEX('Task Log'!$H$2:$H$500,MATCH(19,'Task Log'!$Q$2:$Q$500,0))="","",INDEX('Task Log'!$H$2:$H$500,MATCH(19,'Task Log'!$Q$2:$Q$500,0))),"") | G23: =IFERROR(IF(INDEX('Task Log'!$I$2:$I$500,MATCH(19,'Task Log'!$Q$2:$Q$500,0))="","",INDEX('Task Log'!$I$2:$I$500,MATCH(19,'Task Log'!$Q$2:$Q$500,0))),"") | H23: =IFERROR(IF(INDEX('Task Log'!$J$2:$J$500,MATCH(19,'Task Log'!$Q$2:$Q$500,0))="","",INDEX('Task Log'!$J$2:$J$500,MATCH(19,'Task Log'!$Q$2:$Q$500,0))),"") | I23: =IFERROR(IF(INDEX('Task Log'!$O$2:$O$500,MATCH(19,'Task Log'!$Q$2:$Q$500,0))="","",INDEX('Task Log'!$O$2:$O$500,MATCH(19,'Task Log'!$Q$2:$Q$500,0))),"") | J23: =IFERROR(IF(INDEX('Task Log'!$K$2:$K$500,MATCH(19,'Task Log'!$Q$2:$Q$500,0))="","",INDEX('Task Log'!$K$2:$K$500,MATCH(19,'Task Log'!$Q$2:$Q$500,0))),"") | K23: =IFERROR(IF(INDEX('Task Log'!$N$2:$N$500,MATCH(19,'Task Log'!$Q$2:$Q$500,0))="","",INDEX('Task Log'!$N$2:$N$500,MATCH(19,'Task Log'!$Q$2:$Q$500,0))),"") | L23: =IFERROR(IF(INDEX('Task Log'!$P$2:$P$500,MATCH(19,'Task Log'!$Q$2:$Q$500,0))="","",INDEX('Task Log'!$P$2:$P$500,MATCH(19,'Task Log'!$Q$2:$Q$500,0))),"")
A24: =IFERROR(IF(MATCH(20,'Task Log'!$Q$2:$Q$500,0)>0,20,""),"") | B24: =IFERROR(IF(INDEX('Task Log'!$C$2:$C$500,MATCH(20,'Task Log'!$Q$2:$Q$500,0))="","",INDEX('Task Log'!$C$2:$C$500,MATCH(20,'Task Log'!$Q$2:$Q$500,0))),"") | C24: =IFERROR(IF(INDEX('Task Log'!$D$2:$D$500,MATCH(20,'Task Log'!$Q$2:$Q$500,0))="","",INDEX('Task Log'!$D$2:$D$500,MATCH(20,'Task Log'!$Q$2:$Q$500,0))),"") | D24: =IFERROR(IF(INDEX('Task Log'!$E$2:$E$500,MATCH(20,'Task Log'!$Q$2:$Q$500,0))="","",INDEX('Task Log'!$E$2:$E$500,MATCH(20,'Task Log'!$Q$2:$Q$500,0))),"") | E24: =IFERROR(IF(INDEX('Task Log'!$G$2:$G$500,MATCH(20,'Task Log'!$Q$2:$Q$500,0))="","",INDEX('Task Log'!$G$2:$G$500,MATCH(20,'Task Log'!$Q$2:$Q$500,0))),"") | F24: =IFERROR(IF(INDEX('Task Log'!$H$2:$H$500,MATCH(20,'Task Log'!$Q$2:$Q$500,0))="","",INDEX('Task Log'!$H$2:$H$500,MATCH(20,'Task Log'!$Q$2:$Q$500,0))),"") | G24: =IFERROR(IF(INDEX('Task Log'!$I$2:$I$500,MATCH(20,'Task Log'!$Q$2:$Q$500,0))="","",INDEX('Task Log'!$I$2:$I$500,MATCH(20,'Task Log'!$Q$2:$Q$500,0))),"") | H24: =IFERROR(IF(INDEX('Task Log'!$J$2:$J$500,MATCH(20,'Task Log'!$Q$2:$Q$500,0))="","",INDEX('Task Log'!$J$2:$J$500,MATCH(20,'Task Log'!$Q$2:$Q$500,0))),"") | I24: =IFERROR(IF(INDEX('Task Log'!$O$2:$O$500,MATCH(20,'Task Log'!$Q$2:$Q$500,0))="","",INDEX('Task Log'!$O$2:$O$500,MATCH(20,'Task Log'!$Q$2:$Q$500,0))),"") | J24: =IFERROR(IF(INDEX('Task Log'!$K$2:$K$500,MATCH(20,'Task Log'!$Q$2:$Q$500,0))="","",INDEX('Task Log'!$K$2:$K$500,MATCH(20,'Task Log'!$Q$2:$Q$500,0))),"") | K24: =IFERROR(IF(INDEX('Task Log'!$N$2:$N$500,MATCH(20,'Task Log'!$Q$2:$Q$500,0))="","",INDEX('Task Log'!$N$2:$N$500,MATCH(20,'Task Log'!$Q$2:$Q$500,0))),"") | L24: =IFERROR(IF(INDEX('Task Log'!$P$2:$P$500,MATCH(20,'Task Log'!$Q$2:$Q$500,0))="","",INDEX('Task Log'!$P$2:$P$500,MATCH(20,'Task Log'!$Q$2:$Q$500,0))),"")
A25: =IFERROR(IF(MATCH(21,'Task Log'!$Q$2:$Q$500,0)>0,21,""),"") | B25: =IFERROR(IF(INDEX('Task Log'!$C$2:$C$500,MATCH(21,'Task Log'!$Q$2:$Q$500,0))="","",INDEX('Task Log'!$C$2:$C$500,MATCH(21,'Task Log'!$Q$2:$Q$500,0))),"") | C25: =IFERROR(IF(INDEX('Task Log'!$D$2:$D$500,MATCH(21,'Task Log'!$Q$2:$Q$500,0))="","",INDEX('Task Log'!$D$2:$D$500,MATCH(21,'Task Log'!$Q$2:$Q$500,0))),"") | D25: =IFERROR(IF(INDEX('Task Log'!$E$2:$E$500,MATCH(21,'Task Log'!$Q$2:$Q$500,0))="","",INDEX('Task Log'!$E$2:$E$500,MATCH(21,'Task Log'!$Q$2:$Q$500,0))),"") | E25: =IFERROR(IF(INDEX('Task Log'!$G$2:$G$500,MATCH(21,'Task Log'!$Q$2:$Q$500,0))="","",INDEX('Task Log'!$G$2:$G$500,MATCH(21,'Task Log'!$Q$2:$Q$500,0))),"") | F25: =IFERROR(IF(INDEX('Task Log'!$H$2:$H$500,MATCH(21,'Task Log'!$Q$2:$Q$500,0))="","",INDEX('Task Log'!$H$2:$H$500,MATCH(21,'Task Log'!$Q$2:$Q$500,0))),"") | G25: =IFERROR(IF(INDEX('Task Log'!$I$2:$I$500,MATCH(21,'Task Log'!$Q$2:$Q$500,0))="","",INDEX('Task Log'!$I$2:$I$500,MATCH(21,'Task Log'!$Q$2:$Q$500,0))),"") | H25: =IFERROR(IF(INDEX('Task Log'!$J$2:$J$500,MATCH(21,'Task Log'!$Q$2:$Q$500,0))="","",INDEX('Task Log'!$J$2:$J$500,MATCH(21,'Task Log'!$Q$2:$Q$500,0))),"") | I25: =IFERROR(IF(INDEX('Task Log'!$O$2:$O$500,MATCH(21,'Task Log'!$Q$2:$Q$500,0))="","",INDEX('Task Log'!$O$2:$O$500,MATCH(21,'Task Log'!$Q$2:$Q$500,0))),"") | J25: =IFERROR(IF(INDEX('Task Log'!$K$2:$K$500,MATCH(21,'Task Log'!$Q$2:$Q$500,0))="","",INDEX('Task Log'!$K$2:$K$500,MATCH(21,'Task Log'!$Q$2:$Q$500,0))),"") | K25: =IFERROR(IF(INDEX('Task Log'!$N$2:$N$500,MATCH(21,'Task Log'!$Q$2:$Q$500,0))="","",INDEX('Task Log'!$N$2:$N$500,MATCH(21,'Task Log'!$Q$2:$Q$500,0))),"") | L25: =IFERROR(IF(INDEX('Task Log'!$P$2:$P$500,MATCH(21,'Task Log'!$Q$2:$Q$500,0))="","",INDEX('Task Log'!$P$2:$P$500,MATCH(21,'Task Log'!$Q$2:$Q$500,0))),"")
A26: =IFERROR(IF(MATCH(22,'Task Log'!$Q$2:$Q$500,0)>0,22,""),"") | B26: =IFERROR(IF(INDEX('Task Log'!$C$2:$C$500,MATCH(22,'Task Log'!$Q$2:$Q$500,0))="","",INDEX('Task Log'!$C$2:$C$500,MATCH(22,'Task Log'!$Q$2:$Q$500,0))),"") | C26: =IFERROR(IF(INDEX('Task Log'!$D$2:$D$500,MATCH(22,'Task Log'!$Q$2:$Q$500,0))="","",INDEX('Task Log'!$D$2:$D$500,MATCH(22,'Task Log'!$Q$2:$Q$500,0))),"") | D26: =IFERROR(IF(INDEX('Task Log'!$E$2:$E$500,MATCH(22,'Task Log'!$Q$2:$Q$500,0))="","",INDEX('Task Log'!$E$2:$E$500,MATCH(22,'Task Log'!$Q$2:$Q$500,0))),"") | E26: =IFERROR(IF(INDEX('Task Log'!$G$2:$G$500,MATCH(22,'Task Log'!$Q$2:$Q$500,0))="","",INDEX('Task Log'!$G$2:$G$500,MATCH(22,'Task Log'!$Q$2:$Q$500,0))),"") | F26: =IFERROR(IF(INDEX('Task Log'!$H$2:$H$500,MATCH(22,'Task Log'!$Q$2:$Q$500,0))="","",INDEX('Task Log'!$H$2:$H$500,MATCH(22,'Task Log'!$Q$2:$Q$500,0))),"") | G26: =IFERROR(IF(INDEX('Task Log'!$I$2:$I$500,MATCH(22,'Task Log'!$Q$2:$Q$500,0))="","",INDEX('Task Log'!$I$2:$I$500,MATCH(22,'Task Log'!$Q$2:$Q$500,0))),"") | H26: =IFERROR(IF(INDEX('Task Log'!$J$2:$J$500,MATCH(22,'Task Log'!$Q$2:$Q$500,0))="","",INDEX('Task Log'!$J$2:$J$500,MATCH(22,'Task Log'!$Q$2:$Q$500,0))),"") | I26: =IFERROR(IF(INDEX('Task Log'!$O$2:$O$500,MATCH(22,'Task Log'!$Q$2:$Q$500,0))="","",INDEX('Task Log'!$O$2:$O$500,MATCH(22,'Task Log'!$Q$2:$Q$500,0))),"") | J26: =IFERROR(IF(INDEX('Task Log'!$K$2:$K$500,MATCH(22,'Task Log'!$Q$2:$Q$500,0))="","",INDEX('Task Log'!$K$2:$K$500,MATCH(22,'Task Log'!$Q$2:$Q$500,0))),"") | K26: =IFERROR(IF(INDEX('Task Log'!$N$2:$N$500,MATCH(22,'Task Log'!$Q$2:$Q$500,0))="","",INDEX('Task Log'!$N$2:$N$500,MATCH(22,'Task Log'!$Q$2:$Q$500,0))),"") | L26: =IFERROR(IF(INDEX('Task Log'!$P$2:$P$500,MATCH(22,'Task Log'!$Q$2:$Q$500,0))="","",INDEX('Task Log'!$P$2:$P$500,MATCH(22,'Task Log'!$Q$2:$Q$500,0))),"")
A27: =IFERROR(IF(MATCH(23,'Task Log'!$Q$2:$Q$500,0)>0,23,""),"") | B27: =IFERROR(IF(INDEX('Task Log'!$C$2:$C$500,MATCH(23,'Task Log'!$Q$2:$Q$500,0))="","",INDEX('Task Log'!$C$2:$C$500,MATCH(23,'Task Log'!$Q$2:$Q$500,0))),"") | C27: =IFERROR(IF(INDEX('Task Log'!$D$2:$D$500,MATCH(23,'Task Log'!$Q$2:$Q$500,0))="","",INDEX('Task Log'!$D$2:$D$500,MATCH(23,'Task Log'!$Q$2:$Q$500,0))),"") | D27: =IFERROR(IF(INDEX('Task Log'!$E$2:$E$500,MATCH(23,'Task Log'!$Q$2:$Q$500,0))="","",INDEX('Task Log'!$E$2:$E$500,MATCH(23,'Task Log'!$Q$2:$Q$500,0))),"") | E27: =IFERROR(IF(INDEX('Task Log'!$G$2:$G$500,MATCH(23,'Task Log'!$Q$2:$Q$500,0))="","",INDEX('Task Log'!$G$2:$G$500,MATCH(23,'Task Log'!$Q$2:$Q$500,0))),"") | F27: =IFERROR(IF(INDEX('Task Log'!$H$2:$H$500,MATCH(23,'Task Log'!$Q$2:$Q$500,0))="","",INDEX('Task Log'!$H$2:$H$500,MATCH(23,'Task Log'!$Q$2:$Q$500,0))),"") | G27: =IFERROR(IF(INDEX('Task Log'!$I$2:$I$500,MATCH(23,'Task Log'!$Q$2:$Q$500,0))="","",INDEX('Task Log'!$I$2:$I$500,MATCH(23,'Task Log'!$Q$2:$Q$500,0))),"") | H27: =IFERROR(IF(INDEX('Task Log'!$J$2:$J$500,MATCH(23,'Task Log'!$Q$2:$Q$500,0))="","",INDEX('Task Log'!$J$2:$J$500,MATCH(23,'Task Log'!$Q$2:$Q$500,0))),"") | I27: =IFERROR(IF(INDEX('Task Log'!$O$2:$O$500,MATCH(23,'Task Log'!$Q$2:$Q$500,0))="","",INDEX('Task Log'!$O$2:$O$500,MATCH(23,'Task Log'!$Q$2:$Q$500,0))),"") | J27: =IFERROR(IF(INDEX('Task Log'!$K$2:$K$500,MATCH(23,'Task Log'!$Q$2:$Q$500,0))="","",INDEX('Task Log'!$K$2:$K$500,MATCH(23,'Task Log'!$Q$2:$Q$500,0))),"") | K27: =IFERROR(IF(INDEX('Task Log'!$N$2:$N$500,MATCH(23,'Task Log'!$Q$2:$Q$500,0))="","",INDEX('Task Log'!$N$2:$N$500,MATCH(23,'Task Log'!$Q$2:$Q$500,0))),"") | L27: =IFERROR(IF(INDEX('Task Log'!$P$2:$P$500,MATCH(23,'Task Log'!$Q$2:$Q$500,0))="","",INDEX('Task Log'!$P$2:$P$500,MATCH(23,'Task Log'!$Q$2:$Q$500,0))),"")
A28: =IFERROR(IF(MATCH(24,'Task Log'!$Q$2:$Q$500,0)>0,24,""),"") | B28: =IFERROR(IF(INDEX('Task Log'!$C$2:$C$500,MATCH(24,'Task Log'!$Q$2:$Q$500,0))="","",INDEX('Task Log'!$C$2:$C$500,MATCH(24,'Task Log'!$Q$2:$Q$500,0))),"") | C28: =IFERROR(IF(INDEX('Task Log'!$D$2:$D$500,MATCH(24,'Task Log'!$Q$2:$Q$500,0))="","",INDEX('Task Log'!$D$2:$D$500,MATCH(24,'Task Log'!$Q$2:$Q$500,0))),"") | D28: =IFERROR(IF(INDEX('Task Log'!$E$2:$E$500,MATCH(24,'Task Log'!$Q$2:$Q$500,0))="","",INDEX('Task Log'!$E$2:$E$500,MATCH(24,'Task Log'!$Q$2:$Q$500,0))),"") | E28: =IFERROR(IF(INDEX('Task Log'!$G$2:$G$500,MATCH(24,'Task Log'!$Q$2:$Q$500,0))="","",INDEX('Task Log'!$G$2:$G$500,MATCH(24,'Task Log'!$Q$2:$Q$500,0))),"") | F28: =IFERROR(IF(INDEX('Task Log'!$H$2:$H$500,MATCH(24,'Task Log'!$Q$2:$Q$500,0))="","",INDEX('Task Log'!$H$2:$H$500,MATCH(24,'Task Log'!$Q$2:$Q$500,0))),"") | G28: =IFERROR(IF(INDEX('Task Log'!$I$2:$I$500,MATCH(24,'Task Log'!$Q$2:$Q$500,0))="","",INDEX('Task Log'!$I$2:$I$500,MATCH(24,'Task Log'!$Q$2:$Q$500,0))),"") | H28: =IFERROR(IF(INDEX('Task Log'!$J$2:$J$500,MATCH(24,'Task Log'!$Q$2:$Q$500,0))="","",INDEX('Task Log'!$J$2:$J$500,MATCH(24,'Task Log'!$Q$2:$Q$500,0))),"") | I28: =IFERROR(IF(INDEX('Task Log'!$O$2:$O$500,MATCH(24,'Task Log'!$Q$2:$Q$500,0))="","",INDEX('Task Log'!$O$2:$O$500,MATCH(24,'Task Log'!$Q$2:$Q$500,0))),"") | J28: =IFERROR(IF(INDEX('Task Log'!$K$2:$K$500,MATCH(24,'Task Log'!$Q$2:$Q$500,0))="","",INDEX('Task Log'!$K$2:$K$500,MATCH(24,'Task Log'!$Q$2:$Q$500,0))),"") | K28: =IFERROR(IF(INDEX('Task Log'!$N$2:$N$500,MATCH(24,'Task Log'!$Q$2:$Q$500,0))="","",INDEX('Task Log'!$N$2:$N$500,MATCH(24,'Task Log'!$Q$2:$Q$500,0))),"") | L28: =IFERROR(IF(INDEX('Task Log'!$P$2:$P$500,MATCH(24,'Task Log'!$Q$2:$Q$500,0))="","",INDEX('Task Log'!$P$2:$P$500,MATCH(24,'Task Log'!$Q$2:$Q$500,0))),"")
A29: =IFERROR(IF(MATCH(25,'Task Log'!$Q$2:$Q$500,0)>0,25,""),"") | B29: =IFERROR(IF(INDEX('Task Log'!$C$2:$C$500,MATCH(25,'Task Log'!$Q$2:$Q$500,0))="","",INDEX('Task Log'!$C$2:$C$500,MATCH(25,'Task Log'!$Q$2:$Q$500,0))),"") | C29: =IFERROR(IF(INDEX('Task Log'!$D$2:$D$500,MATCH(25,'Task Log'!$Q$2:$Q$500,0))="","",INDEX('Task Log'!$D$2:$D$500,MATCH(25,'Task Log'!$Q$2:$Q$500,0))),"") | D29: =IFERROR(IF(INDEX('Task Log'!$E$2:$E$500,MATCH(25,'Task Log'!$Q$2:$Q$500,0))="","",INDEX('Task Log'!$E$2:$E$500,MATCH(25,'Task Log'!$Q$2:$Q$500,0))),"") | E29: =IFERROR(IF(INDEX('Task Log'!$G$2:$G$500,MATCH(25,'Task Log'!$Q$2:$Q$500,0))="","",INDEX('Task Log'!$G$2:$G$500,MATCH(25,'Task Log'!$Q$2:$Q$500,0))),"") | F29: =IFERROR(IF(INDEX('Task Log'!$H$2:$H$500,MATCH(25,'Task Log'!$Q$2:$Q$500,0))="","",INDEX('Task Log'!$H$2:$H$500,MATCH(25,'Task Log'!$Q$2:$Q$500,0))),"") | G29: =IFERROR(IF(INDEX('Task Log'!$I$2:$I$500,MATCH(25,'Task Log'!$Q$2:$Q$500,0))="","",INDEX('Task Log'!$I$2:$I$500,MATCH(25,'Task Log'!$Q$2:$Q$500,0))),"") | H29: =IFERROR(IF(INDEX('Task Log'!$J$2:$J$500,MATCH(25,'Task Log'!$Q$2:$Q$500,0))="","",INDEX('Task Log'!$J$2:$J$500,MATCH(25,'Task Log'!$Q$2:$Q$500,0))),"") | I29: =IFERROR(IF(INDEX('Task Log'!$O$2:$O$500,MATCH(25,'Task Log'!$Q$2:$Q$500,0))="","",INDEX('Task Log'!$O$2:$O$500,MATCH(25,'Task Log'!$Q$2:$Q$500,0))),"") | J29: =IFERROR(IF(INDEX('Task Log'!$K$2:$K$500,MATCH(25,'Task Log'!$Q$2:$Q$500,0))="","",INDEX('Task Log'!$K$2:$K$500,MATCH(25,'Task Log'!$Q$2:$Q$500,0))),"") | K29: =IFERROR(IF(INDEX('Task Log'!$N$2:$N$500,MATCH(25,'Task Log'!$Q$2:$Q$500,0))="","",INDEX('Task Log'!$N$2:$N$500,MATCH(25,'Task Log'!$Q$2:$Q$500,0))),"") | L29: =IFERROR(IF(INDEX('Task Log'!$P$2:$P$500,MATCH(25,'Task Log'!$Q$2:$Q$500,0))="","",INDEX('Task Log'!$P$2:$P$500,MATCH(25,'Task Log'!$Q$2:$Q$500,0))),"")
A30: =IFERROR(IF(MATCH(26,'Task Log'!$Q$2:$Q$500,0)>0,26,""),"") | B30: =IFERROR(IF(INDEX('Task Log'!$C$2:$C$500,MATCH(26,'Task Log'!$Q$2:$Q$500,0))="","",INDEX('Task Log'!$C$2:$C$500,MATCH(26,'Task Log'!$Q$2:$Q$500,0))),"") | C30: =IFERROR(IF(INDEX('Task Log'!$D$2:$D$500,MATCH(26,'Task Log'!$Q$2:$Q$500,0))="","",INDEX('Task Log'!$D$2:$D$500,MATCH(26,'Task Log'!$Q$2:$Q$500,0))),"") | D30: =IFERROR(IF(INDEX('Task Log'!$E$2:$E$500,MATCH(26,'Task Log'!$Q$2:$Q$500,0))="","",INDEX('Task Log'!$E$2:$E$500,MATCH(26,'Task Log'!$Q$2:$Q$500,0))),"") | E30: =IFERROR(IF(INDEX('Task Log'!$G$2:$G$500,MATCH(26,'Task Log'!$Q$2:$Q$500,0))="","",INDEX('Task Log'!$G$2:$G$500,MATCH(26,'Task Log'!$Q$2:$Q$500,0))),"") | F30: =IFERROR(IF(INDEX('Task Log'!$H$2:$H$500,MATCH(26,'Task Log'!$Q$2:$Q$500,0))="","",INDEX('Task Log'!$H$2:$H$500,MATCH(26,'Task Log'!$Q$2:$Q$500,0))),"") | G30: =IFERROR(IF(INDEX('Task Log'!$I$2:$I$500,MATCH(26,'Task Log'!$Q$2:$Q$500,0))="","",INDEX('Task Log'!$I$2:$I$500,MATCH(26,'Task Log'!$Q$2:$Q$500,0))),"") | H30: =IFERROR(IF(INDEX('Task Log'!$J$2:$J$500,MATCH(26,'Task Log'!$Q$2:$Q$500,0))="","",INDEX('Task Log'!$J$2:$J$500,MATCH(26,'Task Log'!$Q$2:$Q$500,0))),"") | I30: =IFERROR(IF(INDEX('Task Log'!$O$2:$O$500,MATCH(26,'Task Log'!$Q$2:$Q$500,0))="","",INDEX('Task Log'!$O$2:$O$500,MATCH(26,'Task Log'!$Q$2:$Q$500,0))),"") | J30: =IFERROR(IF(INDEX('Task Log'!$K$2:$K$500,MATCH(26,'Task Log'!$Q$2:$Q$500,0))="","",INDEX('Task Log'!$K$2:$K$500,MATCH(26,'Task Log'!$Q$2:$Q$500,0))),"") | K30: =IFERROR(IF(INDEX('Task Log'!$N$2:$N$500,MATCH(26,'Task Log'!$Q$2:$Q$500,0))="","",INDEX('Task Log'!$N$2:$N$500,MATCH(26,'Task Log'!$Q$2:$Q$500,0))),"") | L30: =IFERROR(IF(INDEX('Task Log'!$P$2:$P$500,MATCH(26,'Task Log'!$Q$2:$Q$500,0))="","",INDEX('Task Log'!$P$2:$P$500,MATCH(26,'Task Log'!$Q$2:$Q$500,0))),"")
A31: =IFERROR(IF(MATCH(27,'Task Log'!$Q$2:$Q$500,0)>0,27,""),"") | B31: =IFERROR(IF(INDEX('Task Log'!$C$2:$C$500,MATCH(27,'Task Log'!$Q$2:$Q$500,0))="","",INDEX('Task Log'!$C$2:$C$500,MATCH(27,'Task Log'!$Q$2:$Q$500,0))),"") | C31: =IFERROR(IF(INDEX('Task Log'!$D$2:$D$500,MATCH(27,'Task Log'!$Q$2:$Q$500,0))="","",INDEX('Task Log'!$D$2:$D$500,MATCH(27,'Task Log'!$Q$2:$Q$500,0))),"") | D31: =IFERROR(IF(INDEX('Task Log'!$E$2:$E$500,MATCH(27,'Task Log'!$Q$2:$Q$500,0))="","",INDEX('Task Log'!$E$2:$E$500,MATCH(27,'Task Log'!$Q$2:$Q$500,0))),"") | E31: =IFERROR(IF(INDEX('Task Log'!$G$2:$G$500,MATCH(27,'Task Log'!$Q$2:$Q$500,0))="","",INDEX('Task Log'!$G$2:$G$500,MATCH(27,'Task Log'!$Q$2:$Q$500,0))),"") | F31: =IFERROR(IF(INDEX('Task Log'!$H$2:$H$500,MATCH(27,'Task Log'!$Q$2:$Q$500,0))="","",INDEX('Task Log'!$H$2:$H$500,MATCH(27,'Task Log'!$Q$2:$Q$500,0))),"") | G31: =IFERROR(IF(INDEX('Task Log'!$I$2:$I$500,MATCH(27,'Task Log'!$Q$2:$Q$500,0))="","",INDEX('Task Log'!$I$2:$I$500,MATCH(27,'Task Log'!$Q$2:$Q$500,0))),"") | H31: =IFERROR(IF(INDEX('Task Log'!$J$2:$J$500,MATCH(27,'Task Log'!$Q$2:$Q$500,0))="","",INDEX('Task Log'!$J$2:$J$500,MATCH(27,'Task Log'!$Q$2:$Q$500,0))),"") | I31: =IFERROR(IF(INDEX('Task Log'!$O$2:$O$500,MATCH(27,'Task Log'!$Q$2:$Q$500,0))="","",INDEX('Task Log'!$O$2:$O$500,MATCH(27,'Task Log'!$Q$2:$Q$500,0))),"") | J31: =IFERROR(IF(INDEX('Task Log'!$K$2:$K$500,MATCH(27,'Task Log'!$Q$2:$Q$500,0))="","",INDEX('Task Log'!$K$2:$K$500,MATCH(27,'Task Log'!$Q$2:$Q$500,0))),"") | K31: =IFERROR(IF(INDEX('Task Log'!$N$2:$N$500,MATCH(27,'Task Log'!$Q$2:$Q$500,0))="","",INDEX('Task Log'!$N$2:$N$500,MATCH(27,'Task Log'!$Q$2:$Q$500,0))),"") | L31: =IFERROR(IF(INDEX('Task Log'!$P$2:$P$500,MATCH(27,'Task Log'!$Q$2:$Q$500,0))="","",INDEX('Task Log'!$P$2:$P$500,MATCH(27,'Task Log'!$Q$2:$Q$500,0))),"")
A32: =IFERROR(IF(MATCH(28,'Task Log'!$Q$2:$Q$500,0)>0,28,""),"") | B32: =IFERROR(IF(INDEX('Task Log'!$C$2:$C$500,MATCH(28,'Task Log'!$Q$2:$Q$500,0))="","",INDEX('Task Log'!$C$2:$C$500,MATCH(28,'Task Log'!$Q$2:$Q$500,0))),"") | C32: =IFERROR(IF(INDEX('Task Log'!$D$2:$D$500,MATCH(28,'Task Log'!$Q$2:$Q$500,0))="","",INDEX('Task Log'!$D$2:$D$500,MATCH(28,'Task Log'!$Q$2:$Q$500,0))),"") | D32: =IFERROR(IF(INDEX('Task Log'!$E$2:$E$500,MATCH(28,'Task Log'!$Q$2:$Q$500,0))="","",INDEX('Task Log'!$E$2:$E$500,MATCH(28,'Task Log'!$Q$2:$Q$500,0))),"") | E32: =IFERROR(IF(INDEX('Task Log'!$G$2:$G$500,MATCH(28,'Task Log'!$Q$2:$Q$500,0))="","",INDEX('Task Log'!$G$2:$G$500,MATCH(28,'Task Log'!$Q$2:$Q$500,0))),"") | F32: =IFERROR(IF(INDEX('Task Log'!$H$2:$H$500,MATCH(28,'Task Log'!$Q$2:$Q$500,0))="","",INDEX('Task Log'!$H$2:$H$500,MATCH(28,'Task Log'!$Q$2:$Q$500,0))),"") | G32: =IFERROR(IF(INDEX('Task Log'!$I$2:$I$500,MATCH(28,'Task Log'!$Q$2:$Q$500,0))="","",INDEX('Task Log'!$I$2:$I$500,MATCH(28,'Task Log'!$Q$2:$Q$500,0))),"") | H32: =IFERROR(IF(INDEX('Task Log'!$J$2:$J$500,MATCH(28,'Task Log'!$Q$2:$Q$500,0))="","",INDEX('Task Log'!$J$2:$J$500,MATCH(28,'Task Log'!$Q$2:$Q$500,0))),"") | I32: =IFERROR(IF(INDEX('Task Log'!$O$2:$O$500,MATCH(28,'Task Log'!$Q$2:$Q$500,0))="","",INDEX('Task Log'!$O$2:$O$500,MATCH(28,'Task Log'!$Q$2:$Q$500,0))),"") | J32: =IFERROR(IF(INDEX('Task Log'!$K$2:$K$500,MATCH(28,'Task Log'!$Q$2:$Q$500,0))="","",INDEX('Task Log'!$K$2:$K$500,MATCH(28,'Task Log'!$Q$2:$Q$500,0))),"") | K32: =IFERROR(IF(INDEX('Task Log'!$N$2:$N$500,MATCH(28,'Task Log'!$Q$2:$Q$500,0))="","",INDEX('Task Log'!$N$2:$N$500,MATCH(28,'Task Log'!$Q$2:$Q$500,0))),"") | L32: =IFERROR(IF(INDEX('Task Log'!$P$2:$P$500,MATCH(28,'Task Log'!$Q$2:$Q$500,0))="","",INDEX('Task Log'!$P$2:$P$500,MATCH(28,'Task Log'!$Q$2:$Q$500,0))),"")
A33: =IFERROR(IF(MATCH(29,'Task Log'!$Q$2:$Q$500,0)>0,29,""),"") | B33: =IFERROR(IF(INDEX('Task Log'!$C$2:$C$500,MATCH(29,'Task Log'!$Q$2:$Q$500,0))="","",INDEX('Task Log'!$C$2:$C$500,MATCH(29,'Task Log'!$Q$2:$Q$500,0))),"") | C33: =IFERROR(IF(INDEX('Task Log'!$D$2:$D$500,MATCH(29,'Task Log'!$Q$2:$Q$500,0))="","",INDEX('Task Log'!$D$2:$D$500,MATCH(29,'Task Log'!$Q$2:$Q$500,0))),"") | D33: =IFERROR(IF(INDEX('Task Log'!$E$2:$E$500,MATCH(29,'Task Log'!$Q$2:$Q$500,0))="","",INDEX('Task Log'!$E$2:$E$500,MATCH(29,'Task Log'!$Q$2:$Q$500,0))),"") | E33: =IFERROR(IF(INDEX('Task Log'!$G$2:$G$500,MATCH(29,'Task Log'!$Q$2:$Q$500,0))="","",INDEX('Task Log'!$G$2:$G$500,MATCH(29,'Task Log'!$Q$2:$Q$500,0))),"") | F33: =IFERROR(IF(INDEX('Task Log'!$H$2:$H$500,MATCH(29,'Task Log'!$Q$2:$Q$500,0))="","",INDEX('Task Log'!$H$2:$H$500,MATCH(29,'Task Log'!$Q$2:$Q$500,0))),"") | G33: =IFERROR(IF(INDEX('Task Log'!$I$2:$I$500,MATCH(29,'Task Log'!$Q$2:$Q$500,0))="","",INDEX('Task Log'!$I$2:$I$500,MATCH(29,'Task Log'!$Q$2:$Q$500,0))),"") | H33: =IFERROR(IF(INDEX('Task Log'!$J$2:$J$500,MATCH(29,'Task Log'!$Q$2:$Q$500,0))="","",INDEX('Task Log'!$J$2:$J$500,MATCH(29,'Task Log'!$Q$2:$Q$500,0))),"") | I33: =IFERROR(IF(INDEX('Task Log'!$O$2:$O$500,MATCH(29,'Task Log'!$Q$2:$Q$500,0))="","",INDEX('Task Log'!$O$2:$O$500,MATCH(29,'Task Log'!$Q$2:$Q$500,0))),"") | J33: =IFERROR(IF(INDEX('Task Log'!$K$2:$K$500,MATCH(29,'Task Log'!$Q$2:$Q$500,0))="","",INDEX('Task Log'!$K$2:$K$500,MATCH(29,'Task Log'!$Q$2:$Q$500,0))),"") | K33: =IFERROR(IF(INDEX('Task Log'!$N$2:$N$500,MATCH(29,'Task Log'!$Q$2:$Q$500,0))="","",INDEX('Task Log'!$N$2:$N$500,MATCH(29,'Task Log'!$Q$2:$Q$500,0))),"") | L33: =IFERROR(IF(INDEX('Task Log'!$P$2:$P$500,MATCH(29,'Task Log'!$Q$2:$Q$500,0))="","",INDEX('Task Log'!$P$2:$P$500,MATCH(29,'Task Log'!$Q$2:$Q$500,0))),"")
A34: =IFERROR(IF(MATCH(30,'Task Log'!$Q$2:$Q$500,0)>0,30,""),"") | B34: =IFERROR(IF(INDEX('Task Log'!$C$2:$C$500,MATCH(30,'Task Log'!$Q$2:$Q$500,0))="","",INDEX('Task Log'!$C$2:$C$500,MATCH(30,'Task Log'!$Q$2:$Q$500,0))),"") | C34: =IFERROR(IF(INDEX('Task Log'!$D$2:$D$500,MATCH(30,'Task Log'!$Q$2:$Q$500,0))="","",INDEX('Task Log'!$D$2:$D$500,MATCH(30,'Task Log'!$Q$2:$Q$500,0))),"") | D34: =IFERROR(IF(INDEX('Task Log'!$E$2:$E$500,MATCH(30,'Task Log'!$Q$2:$Q$500,0))="","",INDEX('Task Log'!$E$2:$E$500,MATCH(30,'Task Log'!$Q$2:$Q$500,0))),"") | E34: =IFERROR(IF(INDEX('Task Log'!$G$2:$G$500,MATCH(30,'Task Log'!$Q$2:$Q$500,0))="","",INDEX('Task Log'!$G$2:$G$500,MATCH(30,'Task Log'!$Q$2:$Q$500,0))),"") | F34: =IFERROR(IF(INDEX('Task Log'!$H$2:$H$500,MATCH(30,'Task Log'!$Q$2:$Q$500,0))="","",INDEX('Task Log'!$H$2:$H$500,MATCH(30,'Task Log'!$Q$2:$Q$500,0))),"") | G34: =IFERROR(IF(INDEX('Task Log'!$I$2:$I$500,MATCH(30,'Task Log'!$Q$2:$Q$500,0))="","",INDEX('Task Log'!$I$2:$I$500,MATCH(30,'Task Log'!$Q$2:$Q$500,0))),"") | H34: =IFERROR(IF(INDEX('Task Log'!$J$2:$J$500,MATCH(30,'Task Log'!$Q$2:$Q$500,0))="","",INDEX('Task Log'!$J$2:$J$500,MATCH(30,'Task Log'!$Q$2:$Q$500,0))),"") | I34: =IFERROR(IF(INDEX('Task Log'!$O$2:$O$500,MATCH(30,'Task Log'!$Q$2:$Q$500,0))="","",INDEX('Task Log'!$O$2:$O$500,MATCH(30,'Task Log'!$Q$2:$Q$500,0))),"") | J34: =IFERROR(IF(INDEX('Task Log'!$K$2:$K$500,MATCH(30,'Task Log'!$Q$2:$Q$500,0))="","",INDEX('Task Log'!$K$2:$K$500,MATCH(30,'Task Log'!$Q$2:$Q$500,0))),"") | K34: =IFERROR(IF(INDEX('Task Log'!$N$2:$N$500,MATCH(30,'Task Log'!$Q$2:$Q$500,0))="","",INDEX('Task Log'!$N$2:$N$500,MATCH(30,'Task Log'!$Q$2:$Q$500,0))),"") | L34: =IFERROR(IF(INDEX('Task Log'!$P$2:$P$500,MATCH(30,'Task Log'!$Q$2:$Q$500,0))="","",INDEX('Task Log'!$P$2:$P$500,MATCH(30,'Task Log'!$Q$2:$Q$500,0))),"")
A35: =IFERROR(IF(MATCH(31,'Task Log'!$Q$2:$Q$500,0)>0,31,""),"") | B35: =IFERROR(IF(INDEX('Task Log'!$C$2:$C$500,MATCH(31,'Task Log'!$Q$2:$Q$500,0))="","",INDEX('Task Log'!$C$2:$C$500,MATCH(31,'Task Log'!$Q$2:$Q$500,0))),"") | C35: =IFERROR(IF(INDEX('Task Log'!$D$2:$D$500,MATCH(31,'Task Log'!$Q$2:$Q$500,0))="","",INDEX('Task Log'!$D$2:$D$500,MATCH(31,'Task Log'!$Q$2:$Q$500,0))),"") | D35: =IFERROR(IF(INDEX('Task Log'!$E$2:$E$500,MATCH(31,'Task Log'!$Q$2:$Q$500,0))="","",INDEX('Task Log'!$E$2:$E$500,MATCH(31,'Task Log'!$Q$2:$Q$500,0))),"") | E35: =IFERROR(IF(INDEX('Task Log'!$G$2:$G$500,MATCH(31,'Task Log'!$Q$2:$Q$500,0))="","",INDEX('Task Log'!$G$2:$G$500,MATCH(31,'Task Log'!$Q$2:$Q$500,0))),"") | F35: =IFERROR(IF(INDEX('Task Log'!$H$2:$H$500,MATCH(31,'Task Log'!$Q$2:$Q$500,0))="","",INDEX('Task Log'!$H$2:$H$500,MATCH(31,'Task Log'!$Q$2:$Q$500,0))),"") | G35: =IFERROR(IF(INDEX('Task Log'!$I$2:$I$500,MATCH(31,'Task Log'!$Q$2:$Q$500,0))="","",INDEX('Task Log'!$I$2:$I$500,MATCH(31,'Task Log'!$Q$2:$Q$500,0))),"") | H35: =IFERROR(IF(INDEX('Task Log'!$J$2:$J$500,MATCH(31,'Task Log'!$Q$2:$Q$500,0))="","",INDEX('Task Log'!$J$2:$J$500,MATCH(31,'Task Log'!$Q$2:$Q$500,0))),"") | I35: =IFERROR(IF(INDEX('Task Log'!$O$2:$O$500,MATCH(31,'Task Log'!$Q$2:$Q$500,0))="","",INDEX('Task Log'!$O$2:$O$500,MATCH(31,'Task Log'!$Q$2:$Q$500,0))),"") | J35: =IFERROR(IF(INDEX('Task Log'!$K$2:$K$500,MATCH(31,'Task Log'!$Q$2:$Q$500,0))="","",INDEX('Task Log'!$K$2:$K$500,MATCH(31,'Task Log'!$Q$2:$Q$500,0))),"") | K35: =IFERROR(IF(INDEX('Task Log'!$N$2:$N$500,MATCH(31,'Task Log'!$Q$2:$Q$500,0))="","",INDEX('Task Log'!$N$2:$N$500,MATCH(31,'Task Log'!$Q$2:$Q$500,0))),"") | L35: =IFERROR(IF(INDEX('Task Log'!$P$2:$P$500,MATCH(31,'Task Log'!$Q$2:$Q$500,0))="","",INDEX('Task Log'!$P$2:$P$500,MATCH(31,'Task Log'!$Q$2:$Q$500,0))),"")
A36: =IFERROR(IF(MATCH(32,'Task Log'!$Q$2:$Q$500,0)>0,32,""),"") | B36: =IFERROR(IF(INDEX('Task Log'!$C$2:$C$500,MATCH(32,'Task Log'!$Q$2:$Q$500,0))="","",INDEX('Task Log'!$C$2:$C$500,MATCH(32,'Task Log'!$Q$2:$Q$500,0))),"") | C36: =IFERROR(IF(INDEX('Task Log'!$D$2:$D$500,MATCH(32,'Task Log'!$Q$2:$Q$500,0))="","",INDEX('Task Log'!$D$2:$D$500,MATCH(32,'Task Log'!$Q$2:$Q$500,0))),"") | D36: =IFERROR(IF(INDEX('Task Log'!$E$2:$E$500,MATCH(32,'Task Log'!$Q$2:$Q$500,0))="","",INDEX('Task Log'!$E$2:$E$500,MATCH(32,'Task Log'!$Q$2:$Q$500,0))),"") | E36: =IFERROR(IF(INDEX('Task Log'!$G$2:$G$500,MATCH(32,'Task Log'!$Q$2:$Q$500,0))="","",INDEX('Task Log'!$G$2:$G$500,MATCH(32,'Task Log'!$Q$2:$Q$500,0))),"") | F36: =IFERROR(IF(INDEX('Task Log'!$H$2:$H$500,MATCH(32,'Task Log'!$Q$2:$Q$500,0))="","",INDEX('Task Log'!$H$2:$H$500,MATCH(32,'Task Log'!$Q$2:$Q$500,0))),"") | G36: =IFERROR(IF(INDEX('Task Log'!$I$2:$I$500,MATCH(32,'Task Log'!$Q$2:$Q$500,0))="","",INDEX('Task Log'!$I$2:$I$500,MATCH(32,'Task Log'!$Q$2:$Q$500,0))),"") | H36: =IFERROR(IF(INDEX('Task Log'!$J$2:$J$500,MATCH(32,'Task Log'!$Q$2:$Q$500,0))="","",INDEX('Task Log'!$J$2:$J$500,MATCH(32,'Task Log'!$Q$2:$Q$500,0))),"") | I36: =IFERROR(IF(INDEX('Task Log'!$O$2:$O$500,MATCH(32,'Task Log'!$Q$2:$Q$500,0))="","",INDEX('Task Log'!$O$2:$O$500,MATCH(32,'Task Log'!$Q$2:$Q$500,0))),"") | J36: =IFERROR(IF(INDEX('Task Log'!$K$2:$K$500,MATCH(32,'Task Log'!$Q$2:$Q$500,0))="","",INDEX('Task Log'!$K$2:$K$500,MATCH(32,'Task Log'!$Q$2:$Q$500,0))),"") | K36: =IFERROR(IF(INDEX('Task Log'!$N$2:$N$500,MATCH(32,'Task Log'!$Q$2:$Q$500,0))="","",INDEX('Task Log'!$N$2:$N$500,MATCH(32,'Task Log'!$Q$2:$Q$500,0))),"") | L36: =IFERROR(IF(INDEX('Task Log'!$P$2:$P$500,MATCH(32,'Task Log'!$Q$2:$Q$500,0))="","",INDEX('Task Log'!$P$2:$P$500,MATCH(32,'Task Log'!$Q$2:$Q$500,0))),"")
A37: =IFERROR(IF(MATCH(33,'Task Log'!$Q$2:$Q$500,0)>0,33,""),"") | B37: =IFERROR(IF(INDEX('Task Log'!$C$2:$C$500,MATCH(33,'Task Log'!$Q$2:$Q$500,0))="","",INDEX('Task Log'!$C$2:$C$500,MATCH(33,'Task Log'!$Q$2:$Q$500,0))),"") | C37: =IFERROR(IF(INDEX('Task Log'!$D$2:$D$500,MATCH(33,'Task Log'!$Q$2:$Q$500,0))="","",INDEX('Task Log'!$D$2:$D$500,MATCH(33,'Task Log'!$Q$2:$Q$500,0))),"") | D37: =IFERROR(IF(INDEX('Task Log'!$E$2:$E$500,MATCH(33,'Task Log'!$Q$2:$Q$500,0))="","",INDEX('Task Log'!$E$2:$E$500,MATCH(33,'Task Log'!$Q$2:$Q$500,0))),"") | E37: =IFERROR(IF(INDEX('Task Log'!$G$2:$G$500,MATCH(33,'Task Log'!$Q$2:$Q$500,0))="","",INDEX('Task Log'!$G$2:$G$500,MATCH(33,'Task Log'!$Q$2:$Q$500,0))),"") | F37: =IFERROR(IF(INDEX('Task Log'!$H$2:$H$500,MATCH(33,'Task Log'!$Q$2:$Q$500,0))="","",INDEX('Task Log'!$H$2:$H$500,MATCH(33,'Task Log'!$Q$2:$Q$500,0))),"") | G37: =IFERROR(IF(INDEX('Task Log'!$I$2:$I$500,MATCH(33,'Task Log'!$Q$2:$Q$500,0))="","",INDEX('Task Log'!$I$2:$I$500,MATCH(33,'Task Log'!$Q$2:$Q$500,0))),"") | H37: =IFERROR(IF(INDEX('Task Log'!$J$2:$J$500,MATCH(33,'Task Log'!$Q$2:$Q$500,0))="","",INDEX('Task Log'!$J$2:$J$500,MATCH(33,'Task Log'!$Q$2:$Q$500,0))),"") | I37: =IFERROR(IF(INDEX('Task Log'!$O$2:$O$500,MATCH(33,'Task Log'!$Q$2:$Q$500,0))="","",INDEX('Task Log'!$O$2:$O$500,MATCH(33,'Task Log'!$Q$2:$Q$500,0))),"") | J37: =IFERROR(IF(INDEX('Task Log'!$K$2:$K$500,MATCH(33,'Task Log'!$Q$2:$Q$500,0))="","",INDEX('Task Log'!$K$2:$K$500,MATCH(33,'Task Log'!$Q$2:$Q$500,0))),"") | K37: =IFERROR(IF(INDEX('Task Log'!$N$2:$N$500,MATCH(33,'Task Log'!$Q$2:$Q$500,0))="","",INDEX('Task Log'!$N$2:$N$500,MATCH(33,'Task Log'!$Q$2:$Q$500,0))),"") | L37: =IFERROR(IF(INDEX('Task Log'!$P$2:$P$500,MATCH(33,'Task Log'!$Q$2:$Q$500,0))="","",INDEX('Task Log'!$P$2:$P$500,MATCH(33,'Task Log'!$Q$2:$Q$500,0))),"")
A38: =IFERROR(IF(MATCH(34,'Task Log'!$Q$2:$Q$500,0)>0,34,""),"") | B38: =IFERROR(IF(INDEX('Task Log'!$C$2:$C$500,MATCH(34,'Task Log'!$Q$2:$Q$500,0))="","",INDEX('Task Log'!$C$2:$C$500,MATCH(34,'Task Log'!$Q$2:$Q$500,0))),"") | C38: =IFERROR(IF(INDEX('Task Log'!$D$2:$D$500,MATCH(34,'Task Log'!$Q$2:$Q$500,0))="","",INDEX('Task Log'!$D$2:$D$500,MATCH(34,'Task Log'!$Q$2:$Q$500,0))),"") | D38: =IFERROR(IF(INDEX('Task Log'!$E$2:$E$500,MATCH(34,'Task Log'!$Q$2:$Q$500,0))="","",INDEX('Task Log'!$E$2:$E$500,MATCH(34,'Task Log'!$Q$2:$Q$500,0))),"") | E38: =IFERROR(IF(INDEX('Task Log'!$G$2:$G$500,MATCH(34,'Task Log'!$Q$2:$Q$500,0))="","",INDEX('Task Log'!$G$2:$G$500,MATCH(34,'Task Log'!$Q$2:$Q$500,0))),"") | F38: =IFERROR(IF(INDEX('Task Log'!$H$2:$H$500,MATCH(34,'Task Log'!$Q$2:$Q$500,0))="","",INDEX('Task Log'!$H$2:$H$500,MATCH(34,'Task Log'!$Q$2:$Q$500,0))),"") | G38: =IFERROR(IF(INDEX('Task Log'!$I$2:$I$500,MATCH(34,'Task Log'!$Q$2:$Q$500,0))="","",INDEX('Task Log'!$I$2:$I$500,MATCH(34,'Task Log'!$Q$2:$Q$500,0))),"") | H38: =IFERROR(IF(INDEX('Task Log'!$J$2:$J$500,MATCH(34,'Task Log'!$Q$2:$Q$500,0))="","",INDEX('Task Log'!$J$2:$J$500,MATCH(34,'Task Log'!$Q$2:$Q$500,0))),"") | I38: =IFERROR(IF(INDEX('Task Log'!$O$2:$O$500,MATCH(34,'Task Log'!$Q$2:$Q$500,0))="","",INDEX('Task Log'!$O$2:$O$500,MATCH(34,'Task Log'!$Q$2:$Q$500,0))),"") | J38: =IFERROR(IF(INDEX('Task Log'!$K$2:$K$500,MATCH(34,'Task Log'!$Q$2:$Q$500,0))="","",INDEX('Task Log'!$K$2:$K$500,MATCH(34,'Task Log'!$Q$2:$Q$500,0))),"") | K38: =IFERROR(IF(INDEX('Task Log'!$N$2:$N$500,MATCH(34,'Task Log'!$Q$2:$Q$500,0))="","",INDEX('Task Log'!$N$2:$N$500,MATCH(34,'Task Log'!$Q$2:$Q$500,0))),"") | L38: =IFERROR(IF(INDEX('Task Log'!$P$2:$P$500,MATCH(34,'Task Log'!$Q$2:$Q$500,0))="","",INDEX('Task Log'!$P$2:$P$500,MATCH(34,'Task Log'!$Q$2:$Q$500,0))),"")
A39: =IFERROR(IF(MATCH(35,'Task Log'!$Q$2:$Q$500,0)>0,35,""),"") | B39: =IFERROR(IF(INDEX('Task Log'!$C$2:$C$500,MATCH(35,'Task Log'!$Q$2:$Q$500,0))="","",INDEX('Task Log'!$C$2:$C$500,MATCH(35,'Task Log'!$Q$2:$Q$500,0))),"") | C39: =IFERROR(IF(INDEX('Task Log'!$D$2:$D$500,MATCH(35,'Task Log'!$Q$2:$Q$500,0))="","",INDEX('Task Log'!$D$2:$D$500,MATCH(35,'Task Log'!$Q$2:$Q$500,0))),"") | D39: =IFERROR(IF(INDEX('Task Log'!$E$2:$E$500,MATCH(35,'Task Log'!$Q$2:$Q$500,0))="","",INDEX('Task Log'!$E$2:$E$500,MATCH(35,'Task Log'!$Q$2:$Q$500,0))),"") | E39: =IFERROR(IF(INDEX('Task Log'!$G$2:$G$500,MATCH(35,'Task Log'!$Q$2:$Q$500,0))="","",INDEX('Task Log'!$G$2:$G$500,MATCH(35,'Task Log'!$Q$2:$Q$500,0))),"") | F39: =IFERROR(IF(INDEX('Task Log'!$H$2:$H$500,MATCH(35,'Task Log'!$Q$2:$Q$500,0))="","",INDEX('Task Log'!$H$2:$H$500,MATCH(35,'Task Log'!$Q$2:$Q$500,0))),"") | G39: =IFERROR(IF(INDEX('Task Log'!$I$2:$I$500,MATCH(35,'Task Log'!$Q$2:$Q$500,0))="","",INDEX('Task Log'!$I$2:$I$500,MATCH(35,'Task Log'!$Q$2:$Q$500,0))),"") | H39: =IFERROR(IF(INDEX('Task Log'!$J$2:$J$500,MATCH(35,'Task Log'!$Q$2:$Q$500,0))="","",INDEX('Task Log'!$J$2:$J$500,MATCH(35,'Task Log'!$Q$2:$Q$500,0))),"") | I39: =IFERROR(IF(INDEX('Task Log'!$O$2:$O$500,MATCH(35,'Task Log'!$Q$2:$Q$500,0))="","",INDEX('Task Log'!$O$2:$O$500,MATCH(35,'Task Log'!$Q$2:$Q$500,0))),"") | J39: =IFERROR(IF(INDEX('Task Log'!$K$2:$K$500,MATCH(35,'Task Log'!$Q$2:$Q$500,0))="","",INDEX('Task Log'!$K$2:$K$500,MATCH(35,'Task Log'!$Q$2:$Q$500,0))),"") | K39: =IFERROR(IF(INDEX('Task Log'!$N$2:$N$500,MATCH(35,'Task Log'!$Q$2:$Q$500,0))="","",INDEX('Task Log'!$N$2:$N$500,MATCH(35,'Task Log'!$Q$2:$Q$500,0))),"") | L39: =IFERROR(IF(INDEX('Task Log'!$P$2:$P$500,MATCH(35,'Task Log'!$Q$2:$Q$500,0))="","",INDEX('Task Log'!$P$2:$P$500,MATCH(35,'Task Log'!$Q$2:$Q$500,0))),"")
A40: =IFERROR(IF(MATCH(36,'Task Log'!$Q$2:$Q$500,0)>0,36,""),"") | B40: =IFERROR(IF(INDEX('Task Log'!$C$2:$C$500,MATCH(36,'Task Log'!$Q$2:$Q$500,0))="","",INDEX('Task Log'!$C$2:$C$500,MATCH(36,'Task Log'!$Q$2:$Q$500,0))),"") | C40: =IFERROR(IF(INDEX('Task Log'!$D$2:$D$500,MATCH(36,'Task Log'!$Q$2:$Q$500,0))="","",INDEX('Task Log'!$D$2:$D$500,MATCH(36,'Task Log'!$Q$2:$Q$500,0))),"") | D40: =IFERROR(IF(INDEX('Task Log'!$E$2:$E$500,MATCH(36,'Task Log'!$Q$2:$Q$500,0))="","",INDEX('Task Log'!$E$2:$E$500,MATCH(36,'Task Log'!$Q$2:$Q$500,0))),"") | E40: =IFERROR(IF(INDEX('Task Log'!$G$2:$G$500,MATCH(36,'Task Log'!$Q$2:$Q$500,0))="","",INDEX('Task Log'!$G$2:$G$500,MATCH(36,'Task Log'!$Q$2:$Q$500,0))),"") | F40: =IFERROR(IF(INDEX('Task Log'!$H$2:$H$500,MATCH(36,'Task Log'!$Q$2:$Q$500,0))="","",INDEX('Task Log'!$H$2:$H$500,MATCH(36,'Task Log'!$Q$2:$Q$500,0))),"") | G40: =IFERROR(IF(INDEX('Task Log'!$I$2:$I$500,MATCH(36,'Task Log'!$Q$2:$Q$500,0))="","",INDEX('Task Log'!$I$2:$I$500,MATCH(36,'Task Log'!$Q$2:$Q$500,0))),"") | H40: =IFERROR(IF(INDEX('Task Log'!$J$2:$J$500,MATCH(36,'Task Log'!$Q$2:$Q$500,0))="","",INDEX('Task Log'!$J$2:$J$500,MATCH(36,'Task Log'!$Q$2:$Q$500,0))),"") | I40: =IFERROR(IF(INDEX('Task Log'!$O$2:$O$500,MATCH(36,'Task Log'!$Q$2:$Q$500,0))="","",INDEX('Task Log'!$O$2:$O$500,MATCH(36,'Task Log'!$Q$2:$Q$500,0))),"") | J40: =IFERROR(IF(INDEX('Task Log'!$K$2:$K$500,MATCH(36,'Task Log'!$Q$2:$Q$500,0))="","",INDEX('Task Log'!$K$2:$K$500,MATCH(36,'Task Log'!$Q$2:$Q$500,0))),"") | K40: =IFERROR(IF(INDEX('Task Log'!$N$2:$N$500,MATCH(36,'Task Log'!$Q$2:$Q$500,0))="","",INDEX('Task Log'!$N$2:$N$500,MATCH(36,'Task Log'!$Q$2:$Q$500,0))),"") | L40: =IFERROR(IF(INDEX('Task Log'!$P$2:$P$500,MATCH(36,'Task Log'!$Q$2:$Q$500,0))="","",INDEX('Task Log'!$P$2:$P$500,MATCH(36,'Task Log'!$Q$2:$Q$500,0))),"")
A41: =IFERROR(IF(MATCH(37,'Task Log'!$Q$2:$Q$500,0)>0,37,""),"") | B41: =IFERROR(IF(INDEX('Task Log'!$C$2:$C$500,MATCH(37,'Task Log'!$Q$2:$Q$500,0))="","",INDEX('Task Log'!$C$2:$C$500,MATCH(37,'Task Log'!$Q$2:$Q$500,0))),"") | C41: =IFERROR(IF(INDEX('Task Log'!$D$2:$D$500,MATCH(37,'Task Log'!$Q$2:$Q$500,0))="","",INDEX('Task Log'!$D$2:$D$500,MATCH(37,'Task Log'!$Q$2:$Q$500,0))),"") | D41: =IFERROR(IF(INDEX('Task Log'!$E$2:$E$500,MATCH(37,'Task Log'!$Q$2:$Q$500,0))="","",INDEX('Task Log'!$E$2:$E$500,MATCH(37,'Task Log'!$Q$2:$Q$500,0))),"") | E41: =IFERROR(IF(INDEX('Task Log'!$G$2:$G$500,MATCH(37,'Task Log'!$Q$2:$Q$500,0))="","",INDEX('Task Log'!$G$2:$G$500,MATCH(37,'Task Log'!$Q$2:$Q$500,0))),"") | F41: =IFERROR(IF(INDEX('Task Log'!$H$2:$H$500,MATCH(37,'Task Log'!$Q$2:$Q$500,0))="","",INDEX('Task Log'!$H$2:$H$500,MATCH(37,'Task Log'!$Q$2:$Q$500,0))),"") | G41: =IFERROR(IF(INDEX('Task Log'!$I$2:$I$500,MATCH(37,'Task Log'!$Q$2:$Q$500,0))="","",INDEX('Task Log'!$I$2:$I$500,MATCH(37,'Task Log'!$Q$2:$Q$500,0))),"") | H41: =IFERROR(IF(INDEX('Task Log'!$J$2:$J$500,MATCH(37,'Task Log'!$Q$2:$Q$500,0))="","",INDEX('Task Log'!$J$2:$J$500,MATCH(37,'Task Log'!$Q$2:$Q$500,0))),"") | I41: =IFERROR(IF(INDEX('Task Log'!$O$2:$O$500,MATCH(37,'Task Log'!$Q$2:$Q$500,0))="","",INDEX('Task Log'!$O$2:$O$500,MATCH(37,'Task Log'!$Q$2:$Q$500,0))),"") | J41: =IFERROR(IF(INDEX('Task Log'!$K$2:$K$500,MATCH(37,'Task Log'!$Q$2:$Q$500,0))="","",INDEX('Task Log'!$K$2:$K$500,MATCH(37,'Task Log'!$Q$2:$Q$500,0))),"") | K41: =IFERROR(IF(INDEX('Task Log'!$N$2:$N$500,MATCH(37,'Task Log'!$Q$2:$Q$500,0))="","",INDEX('Task Log'!$N$2:$N$500,MATCH(37,'Task Log'!$Q$2:$Q$500,0))),"") | L41: =IFERROR(IF(INDEX('Task Log'!$P$2:$P$500,MATCH(37,'Task Log'!$Q$2:$Q$500,0))="","",INDEX('Task Log'!$P$2:$P$500,MATCH(37,'Task Log'!$Q$2:$Q$500,0))),"")
A42: =IFERROR(IF(MATCH(38,'Task Log'!$Q$2:$Q$500,0)>0,38,""),"") | B42: =IFERROR(IF(INDEX('Task Log'!$C$2:$C$500,MATCH(38,'Task Log'!$Q$2:$Q$500,0))="","",INDEX('Task Log'!$C$2:$C$500,MATCH(38,'Task Log'!$Q$2:$Q$500,0))),"") | C42: =IFERROR(IF(INDEX('Task Log'!$D$2:$D$500,MATCH(38,'Task Log'!$Q$2:$Q$500,0))="","",INDEX('Task Log'!$D$2:$D$500,MATCH(38,'Task Log'!$Q$2:$Q$500,0))),"") | D42: =IFERROR(IF(INDEX('Task Log'!$E$2:$E$500,MATCH(38,'Task Log'!$Q$2:$Q$500,0))="","",INDEX('Task Log'!$E$2:$E$500,MATCH(38,'Task Log'!$Q$2:$Q$500,0))),"") | E42: =IFERROR(IF(INDEX('Task Log'!$G$2:$G$500,MATCH(38,'Task Log'!$Q$2:$Q$500,0))="","",INDEX('Task Log'!$G$2:$G$500,MATCH(38,'Task Log'!$Q$2:$Q$500,0))),"") | F42: =IFERROR(IF(INDEX('Task Log'!$H$2:$H$500,MATCH(38,'Task Log'!$Q$2:$Q$500,0))="","",INDEX('Task Log'!$H$2:$H$500,MATCH(38,'Task Log'!$Q$2:$Q$500,0))),"") | G42: =IFERROR(IF(INDEX('Task Log'!$I$2:$I$500,MATCH(38,'Task Log'!$Q$2:$Q$500,0))="","",INDEX('Task Log'!$I$2:$I$500,MATCH(38,'Task Log'!$Q$2:$Q$500,0))),"") | H42: =IFERROR(IF(INDEX('Task Log'!$J$2:$J$500,MATCH(38,'Task Log'!$Q$2:$Q$500,0))="","",INDEX('Task Log'!$J$2:$J$500,MATCH(38,'Task Log'!$Q$2:$Q$500,0))),"") | I42: =IFERROR(IF(INDEX('Task Log'!$O$2:$O$500,MATCH(38,'Task Log'!$Q$2:$Q$500,0))="","",INDEX('Task Log'!$O$2:$O$500,MATCH(38,'Task Log'!$Q$2:$Q$500,0))),"") | J42: =IFERROR(IF(INDEX('Task Log'!$K$2:$K$500,MATCH(38,'Task Log'!$Q$2:$Q$500,0))="","",INDEX('Task Log'!$K$2:$K$500,MATCH(38,'Task Log'!$Q$2:$Q$500,0))),"") | K42: =IFERROR(IF(INDEX('Task Log'!$N$2:$N$500,MATCH(38,'Task Log'!$Q$2:$Q$500,0))="","",INDEX('Task Log'!$N$2:$N$500,MATCH(38,'Task Log'!$Q$2:$Q$500,0))),"") | L42: =IFERROR(IF(INDEX('Task Log'!$P$2:$P$500,MATCH(38,'Task Log'!$Q$2:$Q$500,0))="","",INDEX('Task Log'!$P$2:$P$500,MATCH(38,'Task Log'!$Q$2:$Q$500,0))),"")
A43: =IFERROR(IF(MATCH(39,'Task Log'!$Q$2:$Q$500,0)>0,39,""),"") | B43: =IFERROR(IF(INDEX('Task Log'!$C$2:$C$500,MATCH(39,'Task Log'!$Q$2:$Q$500,0))="","",INDEX('Task Log'!$C$2:$C$500,MATCH(39,'Task Log'!$Q$2:$Q$500,0))),"") | C43: =IFERROR(IF(INDEX('Task Log'!$D$2:$D$500,MATCH(39,'Task Log'!$Q$2:$Q$500,0))="","",INDEX('Task Log'!$D$2:$D$500,MATCH(39,'Task Log'!$Q$2:$Q$500,0))),"") | D43: =IFERROR(IF(INDEX('Task Log'!$E$2:$E$500,MATCH(39,'Task Log'!$Q$2:$Q$500,0))="","",INDEX('Task Log'!$E$2:$E$500,MATCH(39,'Task Log'!$Q$2:$Q$500,0))),"") | E43: =IFERROR(IF(INDEX('Task Log'!$G$2:$G$500,MATCH(39,'Task Log'!$Q$2:$Q$500,0))="","",INDEX('Task Log'!$G$2:$G$500,MATCH(39,'Task Log'!$Q$2:$Q$500,0))),"") | F43: =IFERROR(IF(INDEX('Task Log'!$H$2:$H$500,MATCH(39,'Task Log'!$Q$2:$Q$500,0))="","",INDEX('Task Log'!$H$2:$H$500,MATCH(39,'Task Log'!$Q$2:$Q$500,0))),"") | G43: =IFERROR(IF(INDEX('Task Log'!$I$2:$I$500,MATCH(39,'Task Log'!$Q$2:$Q$500,0))="","",INDEX('Task Log'!$I$2:$I$500,MATCH(39,'Task Log'!$Q$2:$Q$500,0))),"") | H43: =IFERROR(IF(INDEX('Task Log'!$J$2:$J$500,MATCH(39,'Task Log'!$Q$2:$Q$500,0))="","",INDEX('Task Log'!$J$2:$J$500,MATCH(39,'Task Log'!$Q$2:$Q$500,0))),"") | I43: =IFERROR(IF(INDEX('Task Log'!$O$2:$O$500,MATCH(39,'Task Log'!$Q$2:$Q$500,0))="","",INDEX('Task Log'!$O$2:$O$500,MATCH(39,'Task Log'!$Q$2:$Q$500,0))),"") | J43: =IFERROR(IF(INDEX('Task Log'!$K$2:$K$500,MATCH(39,'Task Log'!$Q$2:$Q$500,0))="","",INDEX('Task Log'!$K$2:$K$500,MATCH(39,'Task Log'!$Q$2:$Q$500,0))),"") | K43: =IFERROR(IF(INDEX('Task Log'!$N$2:$N$500,MATCH(39,'Task Log'!$Q$2:$Q$500,0))="","",INDEX('Task Log'!$N$2:$N$500,MATCH(39,'Task Log'!$Q$2:$Q$500,0))),"") | L43: =IFERROR(IF(INDEX('Task Log'!$P$2:$P$500,MATCH(39,'Task Log'!$Q$2:$Q$500,0))="","",INDEX('Task Log'!$P$2:$P$500,MATCH(39,'Task Log'!$Q$2:$Q$500,0))),"")
A44: =IFERROR(IF(MATCH(40,'Task Log'!$Q$2:$Q$500,0)>0,40,""),"") | B44: =IFERROR(IF(INDEX('Task Log'!$C$2:$C$500,MATCH(40,'Task Log'!$Q$2:$Q$500,0))="","",INDEX('Task Log'!$C$2:$C$500,MATCH(40,'Task Log'!$Q$2:$Q$500,0))),"") | C44: =IFERROR(IF(INDEX('Task Log'!$D$2:$D$500,MATCH(40,'Task Log'!$Q$2:$Q$500,0))="","",INDEX('Task Log'!$D$2:$D$500,MATCH(40,'Task Log'!$Q$2:$Q$500,0))),"") | D44: =IFERROR(IF(INDEX('Task Log'!$E$2:$E$500,MATCH(40,'Task Log'!$Q$2:$Q$500,0))="","",INDEX('Task Log'!$E$2:$E$500,MATCH(40,'Task Log'!$Q$2:$Q$500,0))),"") | E44: =IFERROR(IF(INDEX('Task Log'!$G$2:$G$500,MATCH(40,'Task Log'!$Q$2:$Q$500,0))="","",INDEX('Task Log'!$G$2:$G$500,MATCH(40,'Task Log'!$Q$2:$Q$500,0))),"") | F44: =IFERROR(IF(INDEX('Task Log'!$H$2:$H$500,MATCH(40,'Task Log'!$Q$2:$Q$500,0))="","",INDEX('Task Log'!$H$2:$H$500,MATCH(40,'Task Log'!$Q$2:$Q$500,0))),"") | G44: =IFERROR(IF(INDEX('Task Log'!$I$2:$I$500,MATCH(40,'Task Log'!$Q$2:$Q$500,0))="","",INDEX('Task Log'!$I$2:$I$500,MATCH(40,'Task Log'!$Q$2:$Q$500,0))),"") | H44: =IFERROR(IF(INDEX('Task Log'!$J$2:$J$500,MATCH(40,'Task Log'!$Q$2:$Q$500,0))="","",INDEX('Task Log'!$J$2:$J$500,MATCH(40,'Task Log'!$Q$2:$Q$500,0))),"") | I44: =IFERROR(IF(INDEX('Task Log'!$O$2:$O$500,MATCH(40,'Task Log'!$Q$2:$Q$500,0))="","",INDEX('Task Log'!$O$2:$O$500,MATCH(40,'Task Log'!$Q$2:$Q$500,0))),"") | J44: =IFERROR(IF(INDEX('Task Log'!$K$2:$K$500,MATCH(40,'Task Log'!$Q$2:$Q$500,0))="","",INDEX('Task Log'!$K$2:$K$500,MATCH(40,'Task Log'!$Q$2:$Q$500,0))),"") | K44: =IFERROR(IF(INDEX('Task Log'!$N$2:$N$500,MATCH(40,'Task Log'!$Q$2:$Q$500,0))="","",INDEX('Task Log'!$N$2:$N$500,MATCH(40,'Task Log'!$Q$2:$Q$500,0))),"") | L44: =IFERROR(IF(INDEX('Task Log'!$P$2:$P$500,MATCH(40,'Task Log'!$Q$2:$Q$500,0))="","",INDEX('Task Log'!$P$2:$P$500,MATCH(40,'Task Log'!$Q$2:$Q$500,0))),"")
A45: =IFERROR(IF(MATCH(41,'Task Log'!$Q$2:$Q$500,0)>0,41,""),"") | B45: =IFERROR(IF(INDEX('Task Log'!$C$2:$C$500,MATCH(41,'Task Log'!$Q$2:$Q$500,0))="","",INDEX('Task Log'!$C$2:$C$500,MATCH(41,'Task Log'!$Q$2:$Q$500,0))),"") | C45: =IFERROR(IF(INDEX('Task Log'!$D$2:$D$500,MATCH(41,'Task Log'!$Q$2:$Q$500,0))="","",INDEX('Task Log'!$D$2:$D$500,MATCH(41,'Task Log'!$Q$2:$Q$500,0))),"") | D45: =IFERROR(IF(INDEX('Task Log'!$E$2:$E$500,MATCH(41,'Task Log'!$Q$2:$Q$500,0))="","",INDEX('Task Log'!$E$2:$E$500,MATCH(41,'Task Log'!$Q$2:$Q$500,0))),"") | E45: =IFERROR(IF(INDEX('Task Log'!$G$2:$G$500,MATCH(41,'Task Log'!$Q$2:$Q$500,0))="","",INDEX('Task Log'!$G$2:$G$500,MATCH(41,'Task Log'!$Q$2:$Q$500,0))),"") | F45: =IFERROR(IF(INDEX('Task Log'!$H$2:$H$500,MATCH(41,'Task Log'!$Q$2:$Q$500,0))="","",INDEX('Task Log'!$H$2:$H$500,MATCH(41,'Task Log'!$Q$2:$Q$500,0))),"") | G45: =IFERROR(IF(INDEX('Task Log'!$I$2:$I$500,MATCH(41,'Task Log'!$Q$2:$Q$500,0))="","",INDEX('Task Log'!$I$2:$I$500,MATCH(41,'Task Log'!$Q$2:$Q$500,0))),"") | H45: =IFERROR(IF(INDEX('Task Log'!$J$2:$J$500,MATCH(41,'Task Log'!$Q$2:$Q$500,0))="","",INDEX('Task Log'!$J$2:$J$500,MATCH(41,'Task Log'!$Q$2:$Q$500,0))),"") | I45: =IFERROR(IF(INDEX('Task Log'!$O$2:$O$500,MATCH(41,'Task Log'!$Q$2:$Q$500,0))="","",INDEX('Task Log'!$O$2:$O$500,MATCH(41,'Task Log'!$Q$2:$Q$500,0))),"") | J45: =IFERROR(IF(INDEX('Task Log'!$K$2:$K$500,MATCH(41,'Task Log'!$Q$2:$Q$500,0))="","",INDEX('Task Log'!$K$2:$K$500,MATCH(41,'Task Log'!$Q$2:$Q$500,0))),"") | K45: =IFERROR(IF(INDEX('Task Log'!$N$2:$N$500,MATCH(41,'Task Log'!$Q$2:$Q$500,0))="","",INDEX('Task Log'!$N$2:$N$500,MATCH(41,'Task Log'!$Q$2:$Q$500,0))),"") | L45: =IFERROR(IF(INDEX('Task Log'!$P$2:$P$500,MATCH(41,'Task Log'!$Q$2:$Q$500,0))="","",INDEX('Task Log'!$P$2:$P$500,MATCH(41,'Task Log'!$Q$2:$Q$500,0))),"")
A46: =IFERROR(IF(MATCH(42,'Task Log'!$Q$2:$Q$500,0)>0,42,""),"") | B46: =IFERROR(IF(INDEX('Task Log'!$C$2:$C$500,MATCH(42,'Task Log'!$Q$2:$Q$500,0))="","",INDEX('Task Log'!$C$2:$C$500,MATCH(42,'Task Log'!$Q$2:$Q$500,0))),"") | C46: =IFERROR(IF(INDEX('Task Log'!$D$2:$D$500,MATCH(42,'Task Log'!$Q$2:$Q$500,0))="","",INDEX('Task Log'!$D$2:$D$500,MATCH(42,'Task Log'!$Q$2:$Q$500,0))),"") | D46: =IFERROR(IF(INDEX('Task Log'!$E$2:$E$500,MATCH(42,'Task Log'!$Q$2:$Q$500,0))="","",INDEX('Task Log'!$E$2:$E$500,MATCH(42,'Task Log'!$Q$2:$Q$500,0))),"") | E46: =IFERROR(IF(INDEX('Task Log'!$G$2:$G$500,MATCH(42,'Task Log'!$Q$2:$Q$500,0))="","",INDEX('Task Log'!$G$2:$G$500,MATCH(42,'Task Log'!$Q$2:$Q$500,0))),"") | F46: =IFERROR(IF(INDEX('Task Log'!$H$2:$H$500,MATCH(42,'Task Log'!$Q$2:$Q$500,0))="","",INDEX('Task Log'!$H$2:$H$500,MATCH(42,'Task Log'!$Q$2:$Q$500,0))),"") | G46: =IFERROR(IF(INDEX('Task Log'!$I$2:$I$500,MATCH(42,'Task Log'!$Q$2:$Q$500,0))="","",INDEX('Task Log'!$I$2:$I$500,MATCH(42,'Task Log'!$Q$2:$Q$500,0))),"") | H46: =IFERROR(IF(INDEX('Task Log'!$J$2:$J$500,MATCH(42,'Task Log'!$Q$2:$Q$500,0))="","",INDEX('Task Log'!$J$2:$J$500,MATCH(42,'Task Log'!$Q$2:$Q$500,0))),"") | I46: =IFERROR(IF(INDEX('Task Log'!$O$2:$O$500,MATCH(42,'Task Log'!$Q$2:$Q$500,0))="","",INDEX('Task Log'!$O$2:$O$500,MATCH(42,'Task Log'!$Q$2:$Q$500,0))),"") | J46: =IFERROR(IF(INDEX('Task Log'!$K$2:$K$500,MATCH(42,'Task Log'!$Q$2:$Q$500,0))="","",INDEX('Task Log'!$K$2:$K$500,MATCH(42,'Task Log'!$Q$2:$Q$500,0))),"") | K46: =IFERROR(IF(INDEX('Task Log'!$N$2:$N$500,MATCH(42,'Task Log'!$Q$2:$Q$500,0))="","",INDEX('Task Log'!$N$2:$N$500,MATCH(42,'Task Log'!$Q$2:$Q$500,0))),"") | L46: =IFERROR(IF(INDEX('Task Log'!$P$2:$P$500,MATCH(42,'Task Log'!$Q$2:$Q$500,0))="","",INDEX('Task Log'!$P$2:$P$500,MATCH(42,'Task Log'!$Q$2:$Q$500,0))),"")
A47: =IFERROR(IF(MATCH(43,'Task Log'!$Q$2:$Q$500,0)>0,43,""),"") | B47: =IFERROR(IF(INDEX('Task Log'!$C$2:$C$500,MATCH(43,'Task Log'!$Q$2:$Q$500,0))="","",INDEX('Task Log'!$C$2:$C$500,MATCH(43,'Task Log'!$Q$2:$Q$500,0))),"") | C47: =IFERROR(IF(INDEX('Task Log'!$D$2:$D$500,MATCH(43,'Task Log'!$Q$2:$Q$500,0))="","",INDEX('Task Log'!$D$2:$D$500,MATCH(43,'Task Log'!$Q$2:$Q$500,0))),"") | D47: =IFERROR(IF(INDEX('Task Log'!$E$2:$E$500,MATCH(43,'Task Log'!$Q$2:$Q$500,0))="","",INDEX('Task Log'!$E$2:$E$500,MATCH(43,'Task Log'!$Q$2:$Q$500,0))),"") | E47: =IFERROR(IF(INDEX('Task Log'!$G$2:$G$500,MATCH(43,'Task Log'!$Q$2:$Q$500,0))="","",INDEX('Task Log'!$G$2:$G$500,MATCH(43,'Task Log'!$Q$2:$Q$500,0))),"") | F47: =IFERROR(IF(INDEX('Task Log'!$H$2:$H$500,MATCH(43,'Task Log'!$Q$2:$Q$500,0))="","",INDEX('Task Log'!$H$2:$H$500,MATCH(43,'Task Log'!$Q$2:$Q$500,0))),"") | G47: =IFERROR(IF(INDEX('Task Log'!$I$2:$I$500,MATCH(43,'Task Log'!$Q$2:$Q$500,0))="","",INDEX('Task Log'!$I$2:$I$500,MATCH(43,'Task Log'!$Q$2:$Q$500,0))),"") | H47: =IFERROR(IF(INDEX('Task Log'!$J$2:$J$500,MATCH(43,'Task Log'!$Q$2:$Q$500,0))="","",INDEX('Task Log'!$J$2:$J$500,MATCH(43,'Task Log'!$Q$2:$Q$500,0))),"") | I47: =IFERROR(IF(INDEX('Task Log'!$O$2:$O$500,MATCH(43,'Task Log'!$Q$2:$Q$500,0))="","",INDEX('Task Log'!$O$2:$O$500,MATCH(43,'Task Log'!$Q$2:$Q$500,0))),"") | J47: =IFERROR(IF(INDEX('Task Log'!$K$2:$K$500,MATCH(43,'Task Log'!$Q$2:$Q$500,0))="","",INDEX('Task Log'!$K$2:$K$500,MATCH(43,'Task Log'!$Q$2:$Q$500,0))),"") | K47: =IFERROR(IF(INDEX('Task Log'!$N$2:$N$500,MATCH(43,'Task Log'!$Q$2:$Q$500,0))="","",INDEX('Task Log'!$N$2:$N$500,MATCH(43,'Task Log'!$Q$2:$Q$500,0))),"") | L47: =IFERROR(IF(INDEX('Task Log'!$P$2:$P$500,MATCH(43,'Task Log'!$Q$2:$Q$500,0))="","",INDEX('Task Log'!$P$2:$P$500,MATCH(43,'Task Log'!$Q$2:$Q$500,0))),"")
A48: =IFERROR(IF(MATCH(44,'Task Log'!$Q$2:$Q$500,0)>0,44,""),"") | B48: =IFERROR(IF(INDEX('Task Log'!$C$2:$C$500,MATCH(44,'Task Log'!$Q$2:$Q$500,0))="","",INDEX('Task Log'!$C$2:$C$500,MATCH(44,'Task Log'!$Q$2:$Q$500,0))),"") | C48: =IFERROR(IF(INDEX('Task Log'!$D$2:$D$500,MATCH(44,'Task Log'!$Q$2:$Q$500,0))="","",INDEX('Task Log'!$D$2:$D$500,MATCH(44,'Task Log'!$Q$2:$Q$500,0))),"") | D48: =IFERROR(IF(INDEX('Task Log'!$E$2:$E$500,MATCH(44,'Task Log'!$Q$2:$Q$500,0))="","",INDEX('Task Log'!$E$2:$E$500,MATCH(44,'Task Log'!$Q$2:$Q$500,0))),"") | E48: =IFERROR(IF(INDEX('Task Log'!$G$2:$G$500,MATCH(44,'Task Log'!$Q$2:$Q$500,0))="","",INDEX('Task Log'!$G$2:$G$500,MATCH(44,'Task Log'!$Q$2:$Q$500,0))),"") | F48: =IFERROR(IF(INDEX('Task Log'!$H$2:$H$500,MATCH(44,'Task Log'!$Q$2:$Q$500,0))="","",INDEX('Task Log'!$H$2:$H$500,MATCH(44,'Task Log'!$Q$2:$Q$500,0))),"") | G48: =IFERROR(IF(INDEX('Task Log'!$I$2:$I$500,MATCH(44,'Task Log'!$Q$2:$Q$500,0))="","",INDEX('Task Log'!$I$2:$I$500,MATCH(44,'Task Log'!$Q$2:$Q$500,0))),"") | H48: =IFERROR(IF(INDEX('Task Log'!$J$2:$J$500,MATCH(44,'Task Log'!$Q$2:$Q$500,0))="","",INDEX('Task Log'!$J$2:$J$500,MATCH(44,'Task Log'!$Q$2:$Q$500,0))),"") | I48: =IFERROR(IF(INDEX('Task Log'!$O$2:$O$500,MATCH(44,'Task Log'!$Q$2:$Q$500,0))="","",INDEX('Task Log'!$O$2:$O$500,MATCH(44,'Task Log'!$Q$2:$Q$500,0))),"") | J48: =IFERROR(IF(INDEX('Task Log'!$K$2:$K$500,MATCH(44,'Task Log'!$Q$2:$Q$500,0))="","",INDEX('Task Log'!$K$2:$K$500,MATCH(44,'Task Log'!$Q$2:$Q$500,0))),"") | K48: =IFERROR(IF(INDEX('Task Log'!$N$2:$N$500,MATCH(44,'Task Log'!$Q$2:$Q$500,0))="","",INDEX('Task Log'!$N$2:$N$500,MATCH(44,'Task Log'!$Q$2:$Q$500,0))),"") | L48: =IFERROR(IF(INDEX('Task Log'!$P$2:$P$500,MATCH(44,'Task Log'!$Q$2:$Q$500,0))="","",INDEX('Task Log'!$P$2:$P$500,MATCH(44,'Task Log'!$Q$2:$Q$500,0))),"")
A49: =IFERROR(IF(MATCH(45,'Task Log'!$Q$2:$Q$500,0)>0,45,""),"") | B49: =IFERROR(IF(INDEX('Task Log'!$C$2:$C$500,MATCH(45,'Task Log'!$Q$2:$Q$500,0))="","",INDEX('Task Log'!$C$2:$C$500,MATCH(45,'Task Log'!$Q$2:$Q$500,0))),"") | C49: =IFERROR(IF(INDEX('Task Log'!$D$2:$D$500,MATCH(45,'Task Log'!$Q$2:$Q$500,0))="","",INDEX('Task Log'!$D$2:$D$500,MATCH(45,'Task Log'!$Q$2:$Q$500,0))),"") | D49: =IFERROR(IF(INDEX('Task Log'!$E$2:$E$500,MATCH(45,'Task Log'!$Q$2:$Q$500,0))="","",INDEX('Task Log'!$E$2:$E$500,MATCH(45,'Task Log'!$Q$2:$Q$500,0))),"") | E49: =IFERROR(IF(INDEX('Task Log'!$G$2:$G$500,MATCH(45,'Task Log'!$Q$2:$Q$500,0))="","",INDEX('Task Log'!$G$2:$G$500,MATCH(45,'Task Log'!$Q$2:$Q$500,0))),"") | F49: =IFERROR(IF(INDEX('Task Log'!$H$2:$H$500,MATCH(45,'Task Log'!$Q$2:$Q$500,0))="","",INDEX('Task Log'!$H$2:$H$500,MATCH(45,'Task Log'!$Q$2:$Q$500,0))),"") | G49: =IFERROR(IF(INDEX('Task Log'!$I$2:$I$500,MATCH(45,'Task Log'!$Q$2:$Q$500,0))="","",INDEX('Task Log'!$I$2:$I$500,MATCH(45,'Task Log'!$Q$2:$Q$500,0))),"") | H49: =IFERROR(IF(INDEX('Task Log'!$J$2:$J$500,MATCH(45,'Task Log'!$Q$2:$Q$500,0))="","",INDEX('Task Log'!$J$2:$J$500,MATCH(45,'Task Log'!$Q$2:$Q$500,0))),"") | I49: =IFERROR(IF(INDEX('Task Log'!$O$2:$O$500,MATCH(45,'Task Log'!$Q$2:$Q$500,0))="","",INDEX('Task Log'!$O$2:$O$500,MATCH(45,'Task Log'!$Q$2:$Q$500,0))),"") | J49: =IFERROR(IF(INDEX('Task Log'!$K$2:$K$500,MATCH(45,'Task Log'!$Q$2:$Q$500,0))="","",INDEX('Task Log'!$K$2:$K$500,MATCH(45,'Task Log'!$Q$2:$Q$500,0))),"") | K49: =IFERROR(IF(INDEX('Task Log'!$N$2:$N$500,MATCH(45,'Task Log'!$Q$2:$Q$500,0))="","",INDEX('Task Log'!$N$2:$N$500,MATCH(45,'Task Log'!$Q$2:$Q$500,0))),"") | L49: =IFERROR(IF(INDEX('Task Log'!$P$2:$P$500,MATCH(45,'Task Log'!$Q$2:$Q$500,0))="","",INDEX('Task Log'!$P$2:$P$500,MATCH(45,'Task Log'!$Q$2:$Q$500,0))),"")
A50: =IFERROR(IF(MATCH(46,'Task Log'!$Q$2:$Q$500,0)>0,46,""),"") | B50: =IFERROR(IF(INDEX('Task Log'!$C$2:$C$500,MATCH(46,'Task Log'!$Q$2:$Q$500,0))="","",INDEX('Task Log'!$C$2:$C$500,MATCH(46,'Task Log'!$Q$2:$Q$500,0))),"") | C50: =IFERROR(IF(INDEX('Task Log'!$D$2:$D$500,MATCH(46,'Task Log'!$Q$2:$Q$500,0))="","",INDEX('Task Log'!$D$2:$D$500,MATCH(46,'Task Log'!$Q$2:$Q$500,0))),"") | D50: =IFERROR(IF(INDEX('Task Log'!$E$2:$E$500,MATCH(46,'Task Log'!$Q$2:$Q$500,0))="","",INDEX('Task Log'!$E$2:$E$500,MATCH(46,'Task Log'!$Q$2:$Q$500,0))),"") | E50: =IFERROR(IF(INDEX('Task Log'!$G$2:$G$500,MATCH(46,'Task Log'!$Q$2:$Q$500,0))="","",INDEX('Task Log'!$G$2:$G$500,MATCH(46,'Task Log'!$Q$2:$Q$500,0))),"") | F50: =IFERROR(IF(INDEX('Task Log'!$H$2:$H$500,MATCH(46,'Task Log'!$Q$2:$Q$500,0))="","",INDEX('Task Log'!$H$2:$H$500,MATCH(46,'Task Log'!$Q$2:$Q$500,0))),"") | G50: =IFERROR(IF(INDEX('Task Log'!$I$2:$I$500,MATCH(46,'Task Log'!$Q$2:$Q$500,0))="","",INDEX('Task Log'!$I$2:$I$500,MATCH(46,'Task Log'!$Q$2:$Q$500,0))),"") | H50: =IFERROR(IF(INDEX('Task Log'!$J$2:$J$500,MATCH(46,'Task Log'!$Q$2:$Q$500,0))="","",INDEX('Task Log'!$J$2:$J$500,MATCH(46,'Task Log'!$Q$2:$Q$500,0))),"") | I50: =IFERROR(IF(INDEX('Task Log'!$O$2:$O$500,MATCH(46,'Task Log'!$Q$2:$Q$500,0))="","",INDEX('Task Log'!$O$2:$O$500,MATCH(46,'Task Log'!$Q$2:$Q$500,0))),"") | J50: =IFERROR(IF(INDEX('Task Log'!$K$2:$K$500,MATCH(46,'Task Log'!$Q$2:$Q$500,0))="","",INDEX('Task Log'!$K$2:$K$500,MATCH(46,'Task Log'!$Q$2:$Q$500,0))),"") | K50: =IFERROR(IF(INDEX('Task Log'!$N$2:$N$500,MATCH(46,'Task Log'!$Q$2:$Q$500,0))="","",INDEX('Task Log'!$N$2:$N$500,MATCH(46,'Task Log'!$Q$2:$Q$500,0))),"") | L50: =IFERROR(IF(INDEX('Task Log'!$P$2:$P$500,MATCH(46,'Task Log'!$Q$2:$Q$500,0))="","",INDEX('Task Log'!$P$2:$P$500,MATCH(46,'Task Log'!$Q$2:$Q$500,0))),"")
A51: =IFERROR(IF(MATCH(47,'Task Log'!$Q$2:$Q$500,0)>0,47,""),"") | B51: =IFERROR(IF(INDEX('Task Log'!$C$2:$C$500,MATCH(47,'Task Log'!$Q$2:$Q$500,0))="","",INDEX('Task Log'!$C$2:$C$500,MATCH(47,'Task Log'!$Q$2:$Q$500,0))),"") | C51: =IFERROR(IF(INDEX('Task Log'!$D$2:$D$500,MATCH(47,'Task Log'!$Q$2:$Q$500,0))="","",INDEX('Task Log'!$D$2:$D$500,MATCH(47,'Task Log'!$Q$2:$Q$500,0))),"") | D51: =IFERROR(IF(INDEX('Task Log'!$E$2:$E$500,MATCH(47,'Task Log'!$Q$2:$Q$500,0))="","",INDEX('Task Log'!$E$2:$E$500,MATCH(47,'Task Log'!$Q$2:$Q$500,0))),"") | E51: =IFERROR(IF(INDEX('Task Log'!$G$2:$G$500,MATCH(47,'Task Log'!$Q$2:$Q$500,0))="","",INDEX('Task Log'!$G$2:$G$500,MATCH(47,'Task Log'!$Q$2:$Q$500,0))),"") | F51: =IFERROR(IF(INDEX('Task Log'!$H$2:$H$500,MATCH(47,'Task Log'!$Q$2:$Q$500,0))="","",INDEX('Task Log'!$H$2:$H$500,MATCH(47,'Task Log'!$Q$2:$Q$500,0))),"") | G51: =IFERROR(IF(INDEX('Task Log'!$I$2:$I$500,MATCH(47,'Task Log'!$Q$2:$Q$500,0))="","",INDEX('Task Log'!$I$2:$I$500,MATCH(47,'Task Log'!$Q$2:$Q$500,0))),"") | H51: =IFERROR(IF(INDEX('Task Log'!$J$2:$J$500,MATCH(47,'Task Log'!$Q$2:$Q$500,0))="","",INDEX('Task Log'!$J$2:$J$500,MATCH(47,'Task Log'!$Q$2:$Q$500,0))),"") | I51: =IFERROR(IF(INDEX('Task Log'!$O$2:$O$500,MATCH(47,'Task Log'!$Q$2:$Q$500,0))="","",INDEX('Task Log'!$O$2:$O$500,MATCH(47,'Task Log'!$Q$2:$Q$500,0))),"") | J51: =IFERROR(IF(INDEX('Task Log'!$K$2:$K$500,MATCH(47,'Task Log'!$Q$2:$Q$500,0))="","",INDEX('Task Log'!$K$2:$K$500,MATCH(47,'Task Log'!$Q$2:$Q$500,0))),"") | K51: =IFERROR(IF(INDEX('Task Log'!$N$2:$N$500,MATCH(47,'Task Log'!$Q$2:$Q$500,0))="","",INDEX('Task Log'!$N$2:$N$500,MATCH(47,'Task Log'!$Q$2:$Q$500,0))),"") | L51: =IFERROR(IF(INDEX('Task Log'!$P$2:$P$500,MATCH(47,'Task Log'!$Q$2:$Q$500,0))="","",INDEX('Task Log'!$P$2:$P$500,MATCH(47,'Task Log'!$Q$2:$Q$500,0))),"")
A52: =IFERROR(IF(MATCH(48,'Task Log'!$Q$2:$Q$500,0)>0,48,""),"") | B52: =IFERROR(IF(INDEX('Task Log'!$C$2:$C$500,MATCH(48,'Task Log'!$Q$2:$Q$500,0))="","",INDEX('Task Log'!$C$2:$C$500,MATCH(48,'Task Log'!$Q$2:$Q$500,0))),"") | C52: =IFERROR(IF(INDEX('Task Log'!$D$2:$D$500,MATCH(48,'Task Log'!$Q$2:$Q$500,0))="","",INDEX('Task Log'!$D$2:$D$500,MATCH(48,'Task Log'!$Q$2:$Q$500,0))),"") | D52: =IFERROR(IF(INDEX('Task Log'!$E$2:$E$500,MATCH(48,'Task Log'!$Q$2:$Q$500,0))="","",INDEX('Task Log'!$E$2:$E$500,MATCH(48,'Task Log'!$Q$2:$Q$500,0))),"") | E52: =IFERROR(IF(INDEX('Task Log'!$G$2:$G$500,MATCH(48,'Task Log'!$Q$2:$Q$500,0))="","",INDEX('Task Log'!$G$2:$G$500,MATCH(48,'Task Log'!$Q$2:$Q$500,0))),"") | F52: =IFERROR(IF(INDEX('Task Log'!$H$2:$H$500,MATCH(48,'Task Log'!$Q$2:$Q$500,0))="","",INDEX('Task Log'!$H$2:$H$500,MATCH(48,'Task Log'!$Q$2:$Q$500,0))),"") | G52: =IFERROR(IF(INDEX('Task Log'!$I$2:$I$500,MATCH(48,'Task Log'!$Q$2:$Q$500,0))="","",INDEX('Task Log'!$I$2:$I$500,MATCH(48,'Task Log'!$Q$2:$Q$500,0))),"") | H52: =IFERROR(IF(INDEX('Task Log'!$J$2:$J$500,MATCH(48,'Task Log'!$Q$2:$Q$500,0))="","",INDEX('Task Log'!$J$2:$J$500,MATCH(48,'Task Log'!$Q$2:$Q$500,0))),"") | I52: =IFERROR(IF(INDEX('Task Log'!$O$2:$O$500,MATCH(48,'Task Log'!$Q$2:$Q$500,0))="","",INDEX('Task Log'!$O$2:$O$500,MATCH(48,'Task Log'!$Q$2:$Q$500,0))),"") | J52: =IFERROR(IF(INDEX('Task Log'!$K$2:$K$500,MATCH(48,'Task Log'!$Q$2:$Q$500,0))="","",INDEX('Task Log'!$K$2:$K$500,MATCH(48,'Task Log'!$Q$2:$Q$500,0))),"") | K52: =IFERROR(IF(INDEX('Task Log'!$N$2:$N$500,MATCH(48,'Task Log'!$Q$2:$Q$500,0))="","",INDEX('Task Log'!$N$2:$N$500,MATCH(48,'Task Log'!$Q$2:$Q$500,0))),"") | L52: =IFERROR(IF(INDEX('Task Log'!$P$2:$P$500,MATCH(48,'Task Log'!$Q$2:$Q$500,0))="","",INDEX('Task Log'!$P$2:$P$500,MATCH(48,'Task Log'!$Q$2:$Q$500,0))),"")
A53: =IFERROR(IF(MATCH(49,'Task Log'!$Q$2:$Q$500,0)>0,49,""),"") | B53: =IFERROR(IF(INDEX('Task Log'!$C$2:$C$500,MATCH(49,'Task Log'!$Q$2:$Q$500,0))="","",INDEX('Task Log'!$C$2:$C$500,MATCH(49,'Task Log'!$Q$2:$Q$500,0))),"") | C53: =IFERROR(IF(INDEX('Task Log'!$D$2:$D$500,MATCH(49,'Task Log'!$Q$2:$Q$500,0))="","",INDEX('Task Log'!$D$2:$D$500,MATCH(49,'Task Log'!$Q$2:$Q$500,0))),"") | D53: =IFERROR(IF(INDEX('Task Log'!$E$2:$E$500,MATCH(49,'Task Log'!$Q$2:$Q$500,0))="","",INDEX('Task Log'!$E$2:$E$500,MATCH(49,'Task Log'!$Q$2:$Q$500,0))),"") | E53: =IFERROR(IF(INDEX('Task Log'!$G$2:$G$500,MATCH(49,'Task Log'!$Q$2:$Q$500,0))="","",INDEX('Task Log'!$G$2:$G$500,MATCH(49,'Task Log'!$Q$2:$Q$500,0))),"") | F53: =IFERROR(IF(INDEX('Task Log'!$H$2:$H$500,MATCH(49,'Task Log'!$Q$2:$Q$500,0))="","",INDEX('Task Log'!$H$2:$H$500,MATCH(49,'Task Log'!$Q$2:$Q$500,0))),"") | G53: =IFERROR(IF(INDEX('Task Log'!$I$2:$I$500,MATCH(49,'Task Log'!$Q$2:$Q$500,0))="","",INDEX('Task Log'!$I$2:$I$500,MATCH(49,'Task Log'!$Q$2:$Q$500,0))),"") | H53: =IFERROR(IF(INDEX('Task Log'!$J$2:$J$500,MATCH(49,'Task Log'!$Q$2:$Q$500,0))="","",INDEX('Task Log'!$J$2:$J$500,MATCH(49,'Task Log'!$Q$2:$Q$500,0))),"") | I53: =IFERROR(IF(INDEX('Task Log'!$O$2:$O$500,MATCH(49,'Task Log'!$Q$2:$Q$500,0))="","",INDEX('Task Log'!$O$2:$O$500,MATCH(49,'Task Log'!$Q$2:$Q$500,0))),"") | J53: =IFERROR(IF(INDEX('Task Log'!$K$2:$K$500,MATCH(49,'Task Log'!$Q$2:$Q$500,0))="","",INDEX('Task Log'!$K$2:$K$500,MATCH(49,'Task Log'!$Q$2:$Q$500,0))),"") | K53: =IFERROR(IF(INDEX('Task Log'!$N$2:$N$500,MATCH(49,'Task Log'!$Q$2:$Q$500,0))="","",INDEX('Task Log'!$N$2:$N$500,MATCH(49,'Task Log'!$Q$2:$Q$500,0))),"") | L53: =IFERROR(IF(INDEX('Task Log'!$P$2:$P$500,MATCH(49,'Task Log'!$Q$2:$Q$500,0))="","",INDEX('Task Log'!$P$2:$P$500,MATCH(49,'Task Log'!$Q$2:$Q$500,0))),"")
A54: =IFERROR(IF(MATCH(50,'Task Log'!$Q$2:$Q$500,0)>0,50,""),"") | B54: =IFERROR(IF(INDEX('Task Log'!$C$2:$C$500,MATCH(50,'Task Log'!$Q$2:$Q$500,0))="","",INDEX('Task Log'!$C$2:$C$500,MATCH(50,'Task Log'!$Q$2:$Q$500,0))),"") | C54: =IFERROR(IF(INDEX('Task Log'!$D$2:$D$500,MATCH(50,'Task Log'!$Q$2:$Q$500,0))="","",INDEX('Task Log'!$D$2:$D$500,MATCH(50,'Task Log'!$Q$2:$Q$500,0))),"") | D54: =IFERROR(IF(INDEX('Task Log'!$E$2:$E$500,MATCH(50,'Task Log'!$Q$2:$Q$500,0))="","",INDEX('Task Log'!$E$2:$E$500,MATCH(50,'Task Log'!$Q$2:$Q$500,0))),"") | E54: =IFERROR(IF(INDEX('Task Log'!$G$2:$G$500,MATCH(50,'Task Log'!$Q$2:$Q$500,0))="","",INDEX('Task Log'!$G$2:$G$500,MATCH(50,'Task Log'!$Q$2:$Q$500,0))),"") | F54: =IFERROR(IF(INDEX('Task Log'!$H$2:$H$500,MATCH(50,'Task Log'!$Q$2:$Q$500,0))="","",INDEX('Task Log'!$H$2:$H$500,MATCH(50,'Task Log'!$Q$2:$Q$500,0))),"") | G54: =IFERROR(IF(INDEX('Task Log'!$I$2:$I$500,MATCH(50,'Task Log'!$Q$2:$Q$500,0))="","",INDEX('Task Log'!$I$2:$I$500,MATCH(50,'Task Log'!$Q$2:$Q$500,0))),"") | H54: =IFERROR(IF(INDEX('Task Log'!$J$2:$J$500,MATCH(50,'Task Log'!$Q$2:$Q$500,0))="","",INDEX('Task Log'!$J$2:$J$500,MATCH(50,'Task Log'!$Q$2:$Q$500,0))),"") | I54: =IFERROR(IF(INDEX('Task Log'!$O$2:$O$500,MATCH(50,'Task Log'!$Q$2:$Q$500,0))="","",INDEX('Task Log'!$O$2:$O$500,MATCH(50,'Task Log'!$Q$2:$Q$500,0))),"") | J54: =IFERROR(IF(INDEX('Task Log'!$K$2:$K$500,MATCH(50,'Task Log'!$Q$2:$Q$500,0))="","",INDEX('Task Log'!$K$2:$K$500,MATCH(50,'Task Log'!$Q$2:$Q$500,0))),"") | K54: =IFERROR(IF(INDEX('Task Log'!$N$2:$N$500,MATCH(50,'Task Log'!$Q$2:$Q$500,0))="","",INDEX('Task Log'!$N$2:$N$500,MATCH(50,'Task Log'!$Q$2:$Q$500,0))),"") | L54: =IFERROR(IF(INDEX('Task Log'!$P$2:$P$500,MATCH(50,'Task Log'!$Q$2:$Q$500,0))="","",INDEX('Task Log'!$P$2:$P$500,MATCH(50,'Task Log'!$Q$2:$Q$500,0))),"")
A55: =IFERROR(IF(MATCH(51,'Task Log'!$Q$2:$Q$500,0)>0,51,""),"") | B55: =IFERROR(IF(INDEX('Task Log'!$C$2:$C$500,MATCH(51,'Task Log'!$Q$2:$Q$500,0))="","",INDEX('Task Log'!$C$2:$C$500,MATCH(51,'Task Log'!$Q$2:$Q$500,0))),"") | C55: =IFERROR(IF(INDEX('Task Log'!$D$2:$D$500,MATCH(51,'Task Log'!$Q$2:$Q$500,0))="","",INDEX('Task Log'!$D$2:$D$500,MATCH(51,'Task Log'!$Q$2:$Q$500,0))),"") | D55: =IFERROR(IF(INDEX('Task Log'!$E$2:$E$500,MATCH(51,'Task Log'!$Q$2:$Q$500,0))="","",INDEX('Task Log'!$E$2:$E$500,MATCH(51,'Task Log'!$Q$2:$Q$500,0))),"") | E55: =IFERROR(IF(INDEX('Task Log'!$G$2:$G$500,MATCH(51,'Task Log'!$Q$2:$Q$500,0))="","",INDEX('Task Log'!$G$2:$G$500,MATCH(51,'Task Log'!$Q$2:$Q$500,0))),"") | F55: =IFERROR(IF(INDEX('Task Log'!$H$2:$H$500,MATCH(51,'Task Log'!$Q$2:$Q$500,0))="","",INDEX('Task Log'!$H$2:$H$500,MATCH(51,'Task Log'!$Q$2:$Q$500,0))),"") | G55: =IFERROR(IF(INDEX('Task Log'!$I$2:$I$500,MATCH(51,'Task Log'!$Q$2:$Q$500,0))="","",INDEX('Task Log'!$I$2:$I$500,MATCH(51,'Task Log'!$Q$2:$Q$500,0))),"") | H55: =IFERROR(IF(INDEX('Task Log'!$J$2:$J$500,MATCH(51,'Task Log'!$Q$2:$Q$500,0))="","",INDEX('Task Log'!$J$2:$J$500,MATCH(51,'Task Log'!$Q$2:$Q$500,0))),"") | I55: =IFERROR(IF(INDEX('Task Log'!$O$2:$O$500,MATCH(51,'Task Log'!$Q$2:$Q$500,0))="","",INDEX('Task Log'!$O$2:$O$500,MATCH(51,'Task Log'!$Q$2:$Q$500,0))),"") | J55: =IFERROR(IF(INDEX('Task Log'!$K$2:$K$500,MATCH(51,'Task Log'!$Q$2:$Q$500,0))="","",INDEX('Task Log'!$K$2:$K$500,MATCH(51,'Task Log'!$Q$2:$Q$500,0))),"") | K55: =IFERROR(IF(INDEX('Task Log'!$N$2:$N$500,MATCH(51,'Task Log'!$Q$2:$Q$500,0))="","",INDEX('Task Log'!$N$2:$N$500,MATCH(51,'Task Log'!$Q$2:$Q$500,0))),"") | L55: =IFERROR(IF(INDEX('Task Log'!$P$2:$P$500,MATCH(51,'Task Log'!$Q$2:$Q$500,0))="","",INDEX('Task Log'!$P$2:$P$500,MATCH(51,'Task Log'!$Q$2:$Q$500,0))),"")
A56: =IFERROR(IF(MATCH(52,'Task Log'!$Q$2:$Q$500,0)>0,52,""),"") | B56: =IFERROR(IF(INDEX('Task Log'!$C$2:$C$500,MATCH(52,'Task Log'!$Q$2:$Q$500,0))="","",INDEX('Task Log'!$C$2:$C$500,MATCH(52,'Task Log'!$Q$2:$Q$500,0))),"") | C56: =IFERROR(IF(INDEX('Task Log'!$D$2:$D$500,MATCH(52,'Task Log'!$Q$2:$Q$500,0))="","",INDEX('Task Log'!$D$2:$D$500,MATCH(52,'Task Log'!$Q$2:$Q$500,0))),"") | D56: =IFERROR(IF(INDEX('Task Log'!$E$2:$E$500,MATCH(52,'Task Log'!$Q$2:$Q$500,0))="","",INDEX('Task Log'!$E$2:$E$500,MATCH(52,'Task Log'!$Q$2:$Q$500,0))),"") | E56: =IFERROR(IF(INDEX('Task Log'!$G$2:$G$500,MATCH(52,'Task Log'!$Q$2:$Q$500,0))="","",INDEX('Task Log'!$G$2:$G$500,MATCH(52,'Task Log'!$Q$2:$Q$500,0))),"") | F56: =IFERROR(IF(INDEX('Task Log'!$H$2:$H$500,MATCH(52,'Task Log'!$Q$2:$Q$500,0))="","",INDEX('Task Log'!$H$2:$H$500,MATCH(52,'Task Log'!$Q$2:$Q$500,0))),"") | G56: =IFERROR(IF(INDEX('Task Log'!$I$2:$I$500,MATCH(52,'Task Log'!$Q$2:$Q$500,0))="","",INDEX('Task Log'!$I$2:$I$500,MATCH(52,'Task Log'!$Q$2:$Q$500,0))),"") | H56: =IFERROR(IF(INDEX('Task Log'!$J$2:$J$500,MATCH(52,'Task Log'!$Q$2:$Q$500,0))="","",INDEX('Task Log'!$J$2:$J$500,MATCH(52,'Task Log'!$Q$2:$Q$500,0))),"") | I56: =IFERROR(IF(INDEX('Task Log'!$O$2:$O$500,MATCH(52,'Task Log'!$Q$2:$Q$500,0))="","",INDEX('Task Log'!$O$2:$O$500,MATCH(52,'Task Log'!$Q$2:$Q$500,0))),"") | J56: =IFERROR(IF(INDEX('Task Log'!$K$2:$K$500,MATCH(52,'Task Log'!$Q$2:$Q$500,0))="","",INDEX('Task Log'!$K$2:$K$500,MATCH(52,'Task Log'!$Q$2:$Q$500,0))),"") | K56: =IFERROR(IF(INDEX('Task Log'!$N$2:$N$500,MATCH(52,'Task Log'!$Q$2:$Q$500,0))="","",INDEX('Task Log'!$N$2:$N$500,MATCH(52,'Task Log'!$Q$2:$Q$500,0))),"") | L56: =IFERROR(IF(INDEX('Task Log'!$P$2:$P$500,MATCH(52,'Task Log'!$Q$2:$Q$500,0))="","",INDEX('Task Log'!$P$2:$P$500,MATCH(52,'Task Log'!$Q$2:$Q$500,0))),"")
A57: =IFERROR(IF(MATCH(53,'Task Log'!$Q$2:$Q$500,0)>0,53,""),"") | B57: =IFERROR(IF(INDEX('Task Log'!$C$2:$C$500,MATCH(53,'Task Log'!$Q$2:$Q$500,0))="","",INDEX('Task Log'!$C$2:$C$500,MATCH(53,'Task Log'!$Q$2:$Q$500,0))),"") | C57: =IFERROR(IF(INDEX('Task Log'!$D$2:$D$500,MATCH(53,'Task Log'!$Q$2:$Q$500,0))="","",INDEX('Task Log'!$D$2:$D$500,MATCH(53,'Task Log'!$Q$2:$Q$500,0))),"") | D57: =IFERROR(IF(INDEX('Task Log'!$E$2:$E$500,MATCH(53,'Task Log'!$Q$2:$Q$500,0))="","",INDEX('Task Log'!$E$2:$E$500,MATCH(53,'Task Log'!$Q$2:$Q$500,0))),"") | E57: =IFERROR(IF(INDEX('Task Log'!$G$2:$G$500,MATCH(53,'Task Log'!$Q$2:$Q$500,0))="","",INDEX('Task Log'!$G$2:$G$500,MATCH(53,'Task Log'!$Q$2:$Q$500,0))),"") | F57: =IFERROR(IF(INDEX('Task Log'!$H$2:$H$500,MATCH(53,'Task Log'!$Q$2:$Q$500,0))="","",INDEX('Task Log'!$H$2:$H$500,MATCH(53,'Task Log'!$Q$2:$Q$500,0))),"") | G57: =IFERROR(IF(INDEX('Task Log'!$I$2:$I$500,MATCH(53,'Task Log'!$Q$2:$Q$500,0))="","",INDEX('Task Log'!$I$2:$I$500,MATCH(53,'Task Log'!$Q$2:$Q$500,0))),"") | H57: =IFERROR(IF(INDEX('Task Log'!$J$2:$J$500,MATCH(53,'Task Log'!$Q$2:$Q$500,0))="","",INDEX('Task Log'!$J$2:$J$500,MATCH(53,'Task Log'!$Q$2:$Q$500,0))),"") | I57: =IFERROR(IF(INDEX('Task Log'!$O$2:$O$500,MATCH(53,'Task Log'!$Q$2:$Q$500,0))="","",INDEX('Task Log'!$O$2:$O$500,MATCH(53,'Task Log'!$Q$2:$Q$500,0))),"") | J57: =IFERROR(IF(INDEX('Task Log'!$K$2:$K$500,MATCH(53,'Task Log'!$Q$2:$Q$500,0))="","",INDEX('Task Log'!$K$2:$K$500,MATCH(53,'Task Log'!$Q$2:$Q$500,0))),"") | K57: =IFERROR(IF(INDEX('Task Log'!$N$2:$N$500,MATCH(53,'Task Log'!$Q$2:$Q$500,0))="","",INDEX('Task Log'!$N$2:$N$500,MATCH(53,'Task Log'!$Q$2:$Q$500,0))),"") | L57: =IFERROR(IF(INDEX('Task Log'!$P$2:$P$500,MATCH(53,'Task Log'!$Q$2:$Q$500,0))="","",INDEX('Task Log'!$P$2:$P$500,MATCH(53,'Task Log'!$Q$2:$Q$500,0))),"")
A58: =IFERROR(IF(MATCH(54,'Task Log'!$Q$2:$Q$500,0)>0,54,""),"") | B58: =IFERROR(IF(INDEX('Task Log'!$C$2:$C$500,MATCH(54,'Task Log'!$Q$2:$Q$500,0))="","",INDEX('Task Log'!$C$2:$C$500,MATCH(54,'Task Log'!$Q$2:$Q$500,0))),"") | C58: =IFERROR(IF(INDEX('Task Log'!$D$2:$D$500,MATCH(54,'Task Log'!$Q$2:$Q$500,0))="","",INDEX('Task Log'!$D$2:$D$500,MATCH(54,'Task Log'!$Q$2:$Q$500,0))),"") | D58: =IFERROR(IF(INDEX('Task Log'!$E$2:$E$500,MATCH(54,'Task Log'!$Q$2:$Q$500,0))="","",INDEX('Task Log'!$E$2:$E$500,MATCH(54,'Task Log'!$Q$2:$Q$500,0))),"") | E58: =IFERROR(IF(INDEX('Task Log'!$G$2:$G$500,MATCH(54,'Task Log'!$Q$2:$Q$500,0))="","",INDEX('Task Log'!$G$2:$G$500,MATCH(54,'Task Log'!$Q$2:$Q$500,0))),"") | F58: =IFERROR(IF(INDEX('Task Log'!$H$2:$H$500,MATCH(54,'Task Log'!$Q$2:$Q$500,0))="","",INDEX('Task Log'!$H$2:$H$500,MATCH(54,'Task Log'!$Q$2:$Q$500,0))),"") | G58: =IFERROR(IF(INDEX('Task Log'!$I$2:$I$500,MATCH(54,'Task Log'!$Q$2:$Q$500,0))="","",INDEX('Task Log'!$I$2:$I$500,MATCH(54,'Task Log'!$Q$2:$Q$500,0))),"") | H58: =IFERROR(IF(INDEX('Task Log'!$J$2:$J$500,MATCH(54,'Task Log'!$Q$2:$Q$500,0))="","",INDEX('Task Log'!$J$2:$J$500,MATCH(54,'Task Log'!$Q$2:$Q$500,0))),"") | I58: =IFERROR(IF(INDEX('Task Log'!$O$2:$O$500,MATCH(54,'Task Log'!$Q$2:$Q$500,0))="","",INDEX('Task Log'!$O$2:$O$500,MATCH(54,'Task Log'!$Q$2:$Q$500,0))),"") | J58: =IFERROR(IF(INDEX('Task Log'!$K$2:$K$500,MATCH(54,'Task Log'!$Q$2:$Q$500,0))="","",INDEX('Task Log'!$K$2:$K$500,MATCH(54,'Task Log'!$Q$2:$Q$500,0))),"") | K58: =IFERROR(IF(INDEX('Task Log'!$N$2:$N$500,MATCH(54,'Task Log'!$Q$2:$Q$500,0))="","",INDEX('Task Log'!$N$2:$N$500,MATCH(54,'Task Log'!$Q$2:$Q$500,0))),"") | L58: =IFERROR(IF(INDEX('Task Log'!$P$2:$P$500,MATCH(54,'Task Log'!$Q$2:$Q$500,0))="","",INDEX('Task Log'!$P$2:$P$500,MATCH(54,'Task Log'!$Q$2:$Q$500,0))),"")
A59: =IFERROR(IF(MATCH(55,'Task Log'!$Q$2:$Q$500,0)>0,55,""),"") | B59: =IFERROR(IF(INDEX('Task Log'!$C$2:$C$500,MATCH(55,'Task Log'!$Q$2:$Q$500,0))="","",INDEX('Task Log'!$C$2:$C$500,MATCH(55,'Task Log'!$Q$2:$Q$500,0))),"") | C59: =IFERROR(IF(INDEX('Task Log'!$D$2:$D$500,MATCH(55,'Task Log'!$Q$2:$Q$500,0))="","",INDEX('Task Log'!$D$2:$D$500,MATCH(55,'Task Log'!$Q$2:$Q$500,0))),"") | D59: =IFERROR(IF(INDEX('Task Log'!$E$2:$E$500,MATCH(55,'Task Log'!$Q$2:$Q$500,0))="","",INDEX('Task Log'!$E$2:$E$500,MATCH(55,'Task Log'!$Q$2:$Q$500,0))),"") | E59: =IFERROR(IF(INDEX('Task Log'!$G$2:$G$500,MATCH(55,'Task Log'!$Q$2:$Q$500,0))="","",INDEX('Task Log'!$G$2:$G$500,MATCH(55,'Task Log'!$Q$2:$Q$500,0))),"") | F59: =IFERROR(IF(INDEX('Task Log'!$H$2:$H$500,MATCH(55,'Task Log'!$Q$2:$Q$500,0))="","",INDEX('Task Log'!$H$2:$H$500,MATCH(55,'Task Log'!$Q$2:$Q$500,0))),"") | G59: =IFERROR(IF(INDEX('Task Log'!$I$2:$I$500,MATCH(55,'Task Log'!$Q$2:$Q$500,0))="","",INDEX('Task Log'!$I$2:$I$500,MATCH(55,'Task Log'!$Q$2:$Q$500,0))),"") | H59: =IFERROR(IF(INDEX('Task Log'!$J$2:$J$500,MATCH(55,'Task Log'!$Q$2:$Q$500,0))="","",INDEX('Task Log'!$J$2:$J$500,MATCH(55,'Task Log'!$Q$2:$Q$500,0))),"") | I59: =IFERROR(IF(INDEX('Task Log'!$O$2:$O$500,MATCH(55,'Task Log'!$Q$2:$Q$500,0))="","",INDEX('Task Log'!$O$2:$O$500,MATCH(55,'Task Log'!$Q$2:$Q$500,0))),"") | J59: =IFERROR(IF(INDEX('Task Log'!$K$2:$K$500,MATCH(55,'Task Log'!$Q$2:$Q$500,0))="","",INDEX('Task Log'!$K$2:$K$500,MATCH(55,'Task Log'!$Q$2:$Q$500,0))),"") | K59: =IFERROR(IF(INDEX('Task Log'!$N$2:$N$500,MATCH(55,'Task Log'!$Q$2:$Q$500,0))="","",INDEX('Task Log'!$N$2:$N$500,MATCH(55,'Task Log'!$Q$2:$Q$500,0))),"") | L59: =IFERROR(IF(INDEX('Task Log'!$P$2:$P$500,MATCH(55,'Task Log'!$Q$2:$Q$500,0))="","",INDEX('Task Log'!$P$2:$P$500,MATCH(55,'Task Log'!$Q$2:$Q$500,0))),"")
A60: =IFERROR(IF(MATCH(56,'Task Log'!$Q$2:$Q$500,0)>0,56,""),"") | B60: =IFERROR(IF(INDEX('Task Log'!$C$2:$C$500,MATCH(56,'Task Log'!$Q$2:$Q$500,0))="","",INDEX('Task Log'!$C$2:$C$500,MATCH(56,'Task Log'!$Q$2:$Q$500,0))),"") | C60: =IFERROR(IF(INDEX('Task Log'!$D$2:$D$500,MATCH(56,'Task Log'!$Q$2:$Q$500,0))="","",INDEX('Task Log'!$D$2:$D$500,MATCH(56,'Task Log'!$Q$2:$Q$500,0))),"") | D60: =IFERROR(IF(INDEX('Task Log'!$E$2:$E$500,MATCH(56,'Task Log'!$Q$2:$Q$500,0))="","",INDEX('Task Log'!$E$2:$E$500,MATCH(56,'Task Log'!$Q$2:$Q$500,0))),"") | E60: =IFERROR(IF(INDEX('Task Log'!$G$2:$G$500,MATCH(56,'Task Log'!$Q$2:$Q$500,0))="","",INDEX('Task Log'!$G$2:$G$500,MATCH(56,'Task Log'!$Q$2:$Q$500,0))),"") | F60: =IFERROR(IF(INDEX('Task Log'!$H$2:$H$500,MATCH(56,'Task Log'!$Q$2:$Q$500,0))="","",INDEX('Task Log'!$H$2:$H$500,MATCH(56,'Task Log'!$Q$2:$Q$500,0))),"") | G60: =IFERROR(IF(INDEX('Task Log'!$I$2:$I$500,MATCH(56,'Task Log'!$Q$2:$Q$500,0))="","",INDEX('Task Log'!$I$2:$I$500,MATCH(56,'Task Log'!$Q$2:$Q$500,0))),"") | H60: =IFERROR(IF(INDEX('Task Log'!$J$2:$J$500,MATCH(56,'Task Log'!$Q$2:$Q$500,0))="","",INDEX('Task Log'!$J$2:$J$500,MATCH(56,'Task Log'!$Q$2:$Q$500,0))),"") | I60: =IFERROR(IF(INDEX('Task Log'!$O$2:$O$500,MATCH(56,'Task Log'!$Q$2:$Q$500,0))="","",INDEX('Task Log'!$O$2:$O$500,MATCH(56,'Task Log'!$Q$2:$Q$500,0))),"") | J60: =IFERROR(IF(INDEX('Task Log'!$K$2:$K$500,MATCH(56,'Task Log'!$Q$2:$Q$500,0))="","",INDEX('Task Log'!$K$2:$K$500,MATCH(56,'Task Log'!$Q$2:$Q$500,0))),"") | K60: =IFERROR(IF(INDEX('Task Log'!$N$2:$N$500,MATCH(56,'Task Log'!$Q$2:$Q$500,0))="","",INDEX('Task Log'!$N$2:$N$500,MATCH(56,'Task Log'!$Q$2:$Q$500,0))),"") | L60: =IFERROR(IF(INDEX('Task Log'!$P$2:$P$500,MATCH(56,'Task Log'!$Q$2:$Q$500,0))="","",INDEX('Task Log'!$P$2:$P$500,MATCH(56,'Task Log'!$Q$2:$Q$500,0))),"")
A61: =IFERROR(IF(MATCH(57,'Task Log'!$Q$2:$Q$500,0)>0,57,""),"") | B61: =IFERROR(IF(INDEX('Task Log'!$C$2:$C$500,MATCH(57,'Task Log'!$Q$2:$Q$500,0))="","",INDEX('Task Log'!$C$2:$C$500,MATCH(57,'Task Log'!$Q$2:$Q$500,0))),"") | C61: =IFERROR(IF(INDEX('Task Log'!$D$2:$D$500,MATCH(57,'Task Log'!$Q$2:$Q$500,0))="","",INDEX('Task Log'!$D$2:$D$500,MATCH(57,'Task Log'!$Q$2:$Q$500,0))),"") | D61: =IFERROR(IF(INDEX('Task Log'!$E$2:$E$500,MATCH(57,'Task Log'!$Q$2:$Q$500,0))="","",INDEX('Task Log'!$E$2:$E$500,MATCH(57,'Task Log'!$Q$2:$Q$500,0))),"") | E61: =IFERROR(IF(INDEX('Task Log'!$G$2:$G$500,MATCH(57,'Task Log'!$Q$2:$Q$500,0))="","",INDEX('Task Log'!$G$2:$G$500,MATCH(57,'Task Log'!$Q$2:$Q$500,0))),"") | F61: =IFERROR(IF(INDEX('Task Log'!$H$2:$H$500,MATCH(57,'Task Log'!$Q$2:$Q$500,0))="","",INDEX('Task Log'!$H$2:$H$500,MATCH(57,'Task Log'!$Q$2:$Q$500,0))),"") | G61: =IFERROR(IF(INDEX('Task Log'!$I$2:$I$500,MATCH(57,'Task Log'!$Q$2:$Q$500,0))="","",INDEX('Task Log'!$I$2:$I$500,MATCH(57,'Task Log'!$Q$2:$Q$500,0))),"") | H61: =IFERROR(IF(INDEX('Task Log'!$J$2:$J$500,MATCH(57,'Task Log'!$Q$2:$Q$500,0))="","",INDEX('Task Log'!$J$2:$J$500,MATCH(57,'Task Log'!$Q$2:$Q$500,0))),"") | I61: =IFERROR(IF(INDEX('Task Log'!$O$2:$O$500,MATCH(57,'Task Log'!$Q$2:$Q$500,0))="","",INDEX('Task Log'!$O$2:$O$500,MATCH(57,'Task Log'!$Q$2:$Q$500,0))),"") | J61: =IFERROR(IF(INDEX('Task Log'!$K$2:$K$500,MATCH(57,'Task Log'!$Q$2:$Q$500,0))="","",INDEX('Task Log'!$K$2:$K$500,MATCH(57,'Task Log'!$Q$2:$Q$500,0))),"") | K61: =IFERROR(IF(INDEX('Task Log'!$N$2:$N$500,MATCH(57,'Task Log'!$Q$2:$Q$500,0))="","",INDEX('Task Log'!$N$2:$N$500,MATCH(57,'Task Log'!$Q$2:$Q$500,0))),"") | L61: =IFERROR(IF(INDEX('Task Log'!$P$2:$P$500,MATCH(57,'Task Log'!$Q$2:$Q$500,0))="","",INDEX('Task Log'!$P$2:$P$500,MATCH(57,'Task Log'!$Q$2:$Q$500,0))),"")
A62: =IFERROR(IF(MATCH(58,'Task Log'!$Q$2:$Q$500,0)>0,58,""),"") | B62: =IFERROR(IF(INDEX('Task Log'!$C$2:$C$500,MATCH(58,'Task Log'!$Q$2:$Q$500,0))="","",INDEX('Task Log'!$C$2:$C$500,MATCH(58,'Task Log'!$Q$2:$Q$500,0))),"") | C62: =IFERROR(IF(INDEX('Task Log'!$D$2:$D$500,MATCH(58,'Task Log'!$Q$2:$Q$500,0))="","",INDEX('Task Log'!$D$2:$D$500,MATCH(58,'Task Log'!$Q$2:$Q$500,0))),"") | D62: =IFERROR(IF(INDEX('Task Log'!$E$2:$E$500,MATCH(58,'Task Log'!$Q$2:$Q$500,0))="","",INDEX('Task Log'!$E$2:$E$500,MATCH(58,'Task Log'!$Q$2:$Q$500,0))),"") | E62: =IFERROR(IF(INDEX('Task Log'!$G$2:$G$500,MATCH(58,'Task Log'!$Q$2:$Q$500,0))="","",INDEX('Task Log'!$G$2:$G$500,MATCH(58,'Task Log'!$Q$2:$Q$500,0))),"") | F62: =IFERROR(IF(INDEX('Task Log'!$H$2:$H$500,MATCH(58,'Task Log'!$Q$2:$Q$500,0))="","",INDEX('Task Log'!$H$2:$H$500,MATCH(58,'Task Log'!$Q$2:$Q$500,0))),"") | G62: =IFERROR(IF(INDEX('Task Log'!$I$2:$I$500,MATCH(58,'Task Log'!$Q$2:$Q$500,0))="","",INDEX('Task Log'!$I$2:$I$500,MATCH(58,'Task Log'!$Q$2:$Q$500,0))),"") | H62: =IFERROR(IF(INDEX('Task Log'!$J$2:$J$500,MATCH(58,'Task Log'!$Q$2:$Q$500,0))="","",INDEX('Task Log'!$J$2:$J$500,MATCH(58,'Task Log'!$Q$2:$Q$500,0))),"") | I62: =IFERROR(IF(INDEX('Task Log'!$O$2:$O$500,MATCH(58,'Task Log'!$Q$2:$Q$500,0))="","",INDEX('Task Log'!$O$2:$O$500,MATCH(58,'Task Log'!$Q$2:$Q$500,0))),"") | J62: =IFERROR(IF(INDEX('Task Log'!$K$2:$K$500,MATCH(58,'Task Log'!$Q$2:$Q$500,0))="","",INDEX('Task Log'!$K$2:$K$500,MATCH(58,'Task Log'!$Q$2:$Q$500,0))),"") | K62: =IFERROR(IF(INDEX('Task Log'!$N$2:$N$500,MATCH(58,'Task Log'!$Q$2:$Q$500,0))="","",INDEX('Task Log'!$N$2:$N$500,MATCH(58,'Task Log'!$Q$2:$Q$500,0))),"") | L62: =IFERROR(IF(INDEX('Task Log'!$P$2:$P$500,MATCH(58,'Task Log'!$Q$2:$Q$500,0))="","",INDEX('Task Log'!$P$2:$P$500,MATCH(58,'Task Log'!$Q$2:$Q$500,0))),"")
A63: =IFERROR(IF(MATCH(59,'Task Log'!$Q$2:$Q$500,0)>0,59,""),"") | B63: =IFERROR(IF(INDEX('Task Log'!$C$2:$C$500,MATCH(59,'Task Log'!$Q$2:$Q$500,0))="","",INDEX('Task Log'!$C$2:$C$500,MATCH(59,'Task Log'!$Q$2:$Q$500,0))),"") | C63: =IFERROR(IF(INDEX('Task Log'!$D$2:$D$500,MATCH(59,'Task Log'!$Q$2:$Q$500,0))="","",INDEX('Task Log'!$D$2:$D$500,MATCH(59,'Task Log'!$Q$2:$Q$500,0))),"") | D63: =IFERROR(IF(INDEX('Task Log'!$E$2:$E$500,MATCH(59,'Task Log'!$Q$2:$Q$500,0))="","",INDEX('Task Log'!$E$2:$E$500,MATCH(59,'Task Log'!$Q$2:$Q$500,0))),"") | E63: =IFERROR(IF(INDEX('Task Log'!$G$2:$G$500,MATCH(59,'Task Log'!$Q$2:$Q$500,0))="","",INDEX('Task Log'!$G$2:$G$500,MATCH(59,'Task Log'!$Q$2:$Q$500,0))),"") | F63: =IFERROR(IF(INDEX('Task Log'!$H$2:$H$500,MATCH(59,'Task Log'!$Q$2:$Q$500,0))="","",INDEX('Task Log'!$H$2:$H$500,MATCH(59,'Task Log'!$Q$2:$Q$500,0))),"") | G63: =IFERROR(IF(INDEX('Task Log'!$I$2:$I$500,MATCH(59,'Task Log'!$Q$2:$Q$500,0))="","",INDEX('Task Log'!$I$2:$I$500,MATCH(59,'Task Log'!$Q$2:$Q$500,0))),"") | H63: =IFERROR(IF(INDEX('Task Log'!$J$2:$J$500,MATCH(59,'Task Log'!$Q$2:$Q$500,0))="","",INDEX('Task Log'!$J$2:$J$500,MATCH(59,'Task Log'!$Q$2:$Q$500,0))),"") | I63: =IFERROR(IF(INDEX('Task Log'!$O$2:$O$500,MATCH(59,'Task Log'!$Q$2:$Q$500,0))="","",INDEX('Task Log'!$O$2:$O$500,MATCH(59,'Task Log'!$Q$2:$Q$500,0))),"") | J63: =IFERROR(IF(INDEX('Task Log'!$K$2:$K$500,MATCH(59,'Task Log'!$Q$2:$Q$500,0))="","",INDEX('Task Log'!$K$2:$K$500,MATCH(59,'Task Log'!$Q$2:$Q$500,0))),"") | K63: =IFERROR(IF(INDEX('Task Log'!$N$2:$N$500,MATCH(59,'Task Log'!$Q$2:$Q$500,0))="","",INDEX('Task Log'!$N$2:$N$500,MATCH(59,'Task Log'!$Q$2:$Q$500,0))),"") | L63: =IFERROR(IF(INDEX('Task Log'!$P$2:$P$500,MATCH(59,'Task Log'!$Q$2:$Q$500,0))="","",INDEX('Task Log'!$P$2:$P$500,MATCH(59,'Task Log'!$Q$2:$Q$500,0))),"")
A64: =IFERROR(IF(MATCH(60,'Task Log'!$Q$2:$Q$500,0)>0,60,""),"") | B64: =IFERROR(IF(INDEX('Task Log'!$C$2:$C$500,MATCH(60,'Task Log'!$Q$2:$Q$500,0))="","",INDEX('Task Log'!$C$2:$C$500,MATCH(60,'Task Log'!$Q$2:$Q$500,0))),"") | C64: =IFERROR(IF(INDEX('Task Log'!$D$2:$D$500,MATCH(60,'Task Log'!$Q$2:$Q$500,0))="","",INDEX('Task Log'!$D$2:$D$500,MATCH(60,'Task Log'!$Q$2:$Q$500,0))),"") | D64: =IFERROR(IF(INDEX('Task Log'!$E$2:$E$500,MATCH(60,'Task Log'!$Q$2:$Q$500,0))="","",INDEX('Task Log'!$E$2:$E$500,MATCH(60,'Task Log'!$Q$2:$Q$500,0))),"") | E64: =IFERROR(IF(INDEX('Task Log'!$G$2:$G$500,MATCH(60,'Task Log'!$Q$2:$Q$500,0))="","",INDEX('Task Log'!$G$2:$G$500,MATCH(60,'Task Log'!$Q$2:$Q$500,0))),"") | F64: =IFERROR(IF(INDEX('Task Log'!$H$2:$H$500,MATCH(60,'Task Log'!$Q$2:$Q$500,0))="","",INDEX('Task Log'!$H$2:$H$500,MATCH(60,'Task Log'!$Q$2:$Q$500,0))),"") | G64: =IFERROR(IF(INDEX('Task Log'!$I$2:$I$500,MATCH(60,'Task Log'!$Q$2:$Q$500,0))="","",INDEX('Task Log'!$I$2:$I$500,MATCH(60,'Task Log'!$Q$2:$Q$500,0))),"") | H64: =IFERROR(IF(INDEX('Task Log'!$J$2:$J$500,MATCH(60,'Task Log'!$Q$2:$Q$500,0))="","",INDEX('Task Log'!$J$2:$J$500,MATCH(60,'Task Log'!$Q$2:$Q$500,0))),"") | I64: =IFERROR(IF(INDEX('Task Log'!$O$2:$O$500,MATCH(60,'Task Log'!$Q$2:$Q$500,0))="","",INDEX('Task Log'!$O$2:$O$500,MATCH(60,'Task Log'!$Q$2:$Q$500,0))),"") | J64: =IFERROR(IF(INDEX('Task Log'!$K$2:$K$500,MATCH(60,'Task Log'!$Q$2:$Q$500,0))="","",INDEX('Task Log'!$K$2:$K$500,MATCH(60,'Task Log'!$Q$2:$Q$500,0))),"") | K64: =IFERROR(IF(INDEX('Task Log'!$N$2:$N$500,MATCH(60,'Task Log'!$Q$2:$Q$500,0))="","",INDEX('Task Log'!$N$2:$N$500,MATCH(60,'Task Log'!$Q$2:$Q$500,0))),"") | L64: =IFERROR(IF(INDEX('Task Log'!$P$2:$P$500,MATCH(60,'Task Log'!$Q$2:$Q$500,0))="","",INDEX('Task Log'!$P$2:$P$500,MATCH(60,'Task Log'!$Q$2:$Q$500,0))),"")
A65: =IFERROR(IF(MATCH(61,'Task Log'!$Q$2:$Q$500,0)>0,61,""),"") | B65: =IFERROR(IF(INDEX('Task Log'!$C$2:$C$500,MATCH(61,'Task Log'!$Q$2:$Q$500,0))="","",INDEX('Task Log'!$C$2:$C$500,MATCH(61,'Task Log'!$Q$2:$Q$500,0))),"") | C65: =IFERROR(IF(INDEX('Task Log'!$D$2:$D$500,MATCH(61,'Task Log'!$Q$2:$Q$500,0))="","",INDEX('Task Log'!$D$2:$D$500,MATCH(61,'Task Log'!$Q$2:$Q$500,0))),"") | D65: =IFERROR(IF(INDEX('Task Log'!$E$2:$E$500,MATCH(61,'Task Log'!$Q$2:$Q$500,0))="","",INDEX('Task Log'!$E$2:$E$500,MATCH(61,'Task Log'!$Q$2:$Q$500,0))),"") | E65: =IFERROR(IF(INDEX('Task Log'!$G$2:$G$500,MATCH(61,'Task Log'!$Q$2:$Q$500,0))="","",INDEX('Task Log'!$G$2:$G$500,MATCH(61,'Task Log'!$Q$2:$Q$500,0))),"") | F65: =IFERROR(IF(INDEX('Task Log'!$H$2:$H$500,MATCH(61,'Task Log'!$Q$2:$Q$500,0))="","",INDEX('Task Log'!$H$2:$H$500,MATCH(61,'Task Log'!$Q$2:$Q$500,0))),"") | G65: =IFERROR(IF(INDEX('Task Log'!$I$2:$I$500,MATCH(61,'Task Log'!$Q$2:$Q$500,0))="","",INDEX('Task Log'!$I$2:$I$500,MATCH(61,'Task Log'!$Q$2:$Q$500,0))),"") | H65: =IFERROR(IF(INDEX('Task Log'!$J$2:$J$500,MATCH(61,'Task Log'!$Q$2:$Q$500,0))="","",INDEX('Task Log'!$J$2:$J$500,MATCH(61,'Task Log'!$Q$2:$Q$500,0))),"") | I65: =IFERROR(IF(INDEX('Task Log'!$O$2:$O$500,MATCH(61,'Task Log'!$Q$2:$Q$500,0))="","",INDEX('Task Log'!$O$2:$O$500,MATCH(61,'Task Log'!$Q$2:$Q$500,0))),"") | J65: =IFERROR(IF(INDEX('Task Log'!$K$2:$K$500,MATCH(61,'Task Log'!$Q$2:$Q$500,0))="","",INDEX('Task Log'!$K$2:$K$500,MATCH(61,'Task Log'!$Q$2:$Q$500,0))),"") | K65: =IFERROR(IF(INDEX('Task Log'!$N$2:$N$500,MATCH(61,'Task Log'!$Q$2:$Q$500,0))="","",INDEX('Task Log'!$N$2:$N$500,MATCH(61,'Task Log'!$Q$2:$Q$500,0))),"") | L65: =IFERROR(IF(INDEX('Task Log'!$P$2:$P$500,MATCH(61,'Task Log'!$Q$2:$Q$500,0))="","",INDEX('Task Log'!$P$2:$P$500,MATCH(61,'Task Log'!$Q$2:$Q$500,0))),"")
A66: =IFERROR(IF(MATCH(62,'Task Log'!$Q$2:$Q$500,0)>0,62,""),"") | B66: =IFERROR(IF(INDEX('Task Log'!$C$2:$C$500,MATCH(62,'Task Log'!$Q$2:$Q$500,0))="","",INDEX('Task Log'!$C$2:$C$500,MATCH(62,'Task Log'!$Q$2:$Q$500,0))),"") | C66: =IFERROR(IF(INDEX('Task Log'!$D$2:$D$500,MATCH(62,'Task Log'!$Q$2:$Q$500,0))="","",INDEX('Task Log'!$D$2:$D$500,MATCH(62,'Task Log'!$Q$2:$Q$500,0))),"") | D66: =IFERROR(IF(INDEX('Task Log'!$E$2:$E$500,MATCH(62,'Task Log'!$Q$2:$Q$500,0))="","",INDEX('Task Log'!$E$2:$E$500,MATCH(62,'Task Log'!$Q$2:$Q$500,0))),"") | E66: =IFERROR(IF(INDEX('Task Log'!$G$2:$G$500,MATCH(62,'Task Log'!$Q$2:$Q$500,0))="","",INDEX('Task Log'!$G$2:$G$500,MATCH(62,'Task Log'!$Q$2:$Q$500,0))),"") | F66: =IFERROR(IF(INDEX('Task Log'!$H$2:$H$500,MATCH(62,'Task Log'!$Q$2:$Q$500,0))="","",INDEX('Task Log'!$H$2:$H$500,MATCH(62,'Task Log'!$Q$2:$Q$500,0))),"") | G66: =IFERROR(IF(INDEX('Task Log'!$I$2:$I$500,MATCH(62,'Task Log'!$Q$2:$Q$500,0))="","",INDEX('Task Log'!$I$2:$I$500,MATCH(62,'Task Log'!$Q$2:$Q$500,0))),"") | H66: =IFERROR(IF(INDEX('Task Log'!$J$2:$J$500,MATCH(62,'Task Log'!$Q$2:$Q$500,0))="","",INDEX('Task Log'!$J$2:$J$500,MATCH(62,'Task Log'!$Q$2:$Q$500,0))),"") | I66: =IFERROR(IF(INDEX('Task Log'!$O$2:$O$500,MATCH(62,'Task Log'!$Q$2:$Q$500,0))="","",INDEX('Task Log'!$O$2:$O$500,MATCH(62,'Task Log'!$Q$2:$Q$500,0))),"") | J66: =IFERROR(IF(INDEX('Task Log'!$K$2:$K$500,MATCH(62,'Task Log'!$Q$2:$Q$500,0))="","",INDEX('Task Log'!$K$2:$K$500,MATCH(62,'Task Log'!$Q$2:$Q$500,0))),"") | K66: =IFERROR(IF(INDEX('Task Log'!$N$2:$N$500,MATCH(62,'Task Log'!$Q$2:$Q$500,0))="","",INDEX('Task Log'!$N$2:$N$500,MATCH(62,'Task Log'!$Q$2:$Q$500,0))),"") | L66: =IFERROR(IF(INDEX('Task Log'!$P$2:$P$500,MATCH(62,'Task Log'!$Q$2:$Q$500,0))="","",INDEX('Task Log'!$P$2:$P$500,MATCH(62,'Task Log'!$Q$2:$Q$500,0))),"")
A67: =IFERROR(IF(MATCH(63,'Task Log'!$Q$2:$Q$500,0)>0,63,""),"") | B67: =IFERROR(IF(INDEX('Task Log'!$C$2:$C$500,MATCH(63,'Task Log'!$Q$2:$Q$500,0))="","",INDEX('Task Log'!$C$2:$C$500,MATCH(63,'Task Log'!$Q$2:$Q$500,0))),"") | C67: =IFERROR(IF(INDEX('Task Log'!$D$2:$D$500,MATCH(63,'Task Log'!$Q$2:$Q$500,0))="","",INDEX('Task Log'!$D$2:$D$500,MATCH(63,'Task Log'!$Q$2:$Q$500,0))),"") | D67: =IFERROR(IF(INDEX('Task Log'!$E$2:$E$500,MATCH(63,'Task Log'!$Q$2:$Q$500,0))="","",INDEX('Task Log'!$E$2:$E$500,MATCH(63,'Task Log'!$Q$2:$Q$500,0))),"") | E67: =IFERROR(IF(INDEX('Task Log'!$G$2:$G$500,MATCH(63,'Task Log'!$Q$2:$Q$500,0))="","",INDEX('Task Log'!$G$2:$G$500,MATCH(63,'Task Log'!$Q$2:$Q$500,0))),"") | F67: =IFERROR(IF(INDEX('Task Log'!$H$2:$H$500,MATCH(63,'Task Log'!$Q$2:$Q$500,0))="","",INDEX('Task Log'!$H$2:$H$500,MATCH(63,'Task Log'!$Q$2:$Q$500,0))),"") | G67: =IFERROR(IF(INDEX('Task Log'!$I$2:$I$500,MATCH(63,'Task Log'!$Q$2:$Q$500,0))="","",INDEX('Task Log'!$I$2:$I$500,MATCH(63,'Task Log'!$Q$2:$Q$500,0))),"") | H67: =IFERROR(IF(INDEX('Task Log'!$J$2:$J$500,MATCH(63,'Task Log'!$Q$2:$Q$500,0))="","",INDEX('Task Log'!$J$2:$J$500,MATCH(63,'Task Log'!$Q$2:$Q$500,0))),"") | I67: =IFERROR(IF(INDEX('Task Log'!$O$2:$O$500,MATCH(63,'Task Log'!$Q$2:$Q$500,0))="","",INDEX('Task Log'!$O$2:$O$500,MATCH(63,'Task Log'!$Q$2:$Q$500,0))),"") | J67: =IFERROR(IF(INDEX('Task Log'!$K$2:$K$500,MATCH(63,'Task Log'!$Q$2:$Q$500,0))="","",INDEX('Task Log'!$K$2:$K$500,MATCH(63,'Task Log'!$Q$2:$Q$500,0))),"") | K67: =IFERROR(IF(INDEX('Task Log'!$N$2:$N$500,MATCH(63,'Task Log'!$Q$2:$Q$500,0))="","",INDEX('Task Log'!$N$2:$N$500,MATCH(63,'Task Log'!$Q$2:$Q$500,0))),"") | L67: =IFERROR(IF(INDEX('Task Log'!$P$2:$P$500,MATCH(63,'Task Log'!$Q$2:$Q$500,0))="","",INDEX('Task Log'!$P$2:$P$500,MATCH(63,'Task Log'!$Q$2:$Q$500,0))),"")
A68: =IFERROR(IF(MATCH(64,'Task Log'!$Q$2:$Q$500,0)>0,64,""),"") | B68: =IFERROR(IF(INDEX('Task Log'!$C$2:$C$500,MATCH(64,'Task Log'!$Q$2:$Q$500,0))="","",INDEX('Task Log'!$C$2:$C$500,MATCH(64,'Task Log'!$Q$2:$Q$500,0))),"") | C68: =IFERROR(IF(INDEX('Task Log'!$D$2:$D$500,MATCH(64,'Task Log'!$Q$2:$Q$500,0))="","",INDEX('Task Log'!$D$2:$D$500,MATCH(64,'Task Log'!$Q$2:$Q$500,0))),"") | D68: =IFERROR(IF(INDEX('Task Log'!$E$2:$E$500,MATCH(64,'Task Log'!$Q$2:$Q$500,0))="","",INDEX('Task Log'!$E$2:$E$500,MATCH(64,'Task Log'!$Q$2:$Q$500,0))),"") | E68: =IFERROR(IF(INDEX('Task Log'!$G$2:$G$500,MATCH(64,'Task Log'!$Q$2:$Q$500,0))="","",INDEX('Task Log'!$G$2:$G$500,MATCH(64,'Task Log'!$Q$2:$Q$500,0))),"") | F68: =IFERROR(IF(INDEX('Task Log'!$H$2:$H$500,MATCH(64,'Task Log'!$Q$2:$Q$500,0))="","",INDEX('Task Log'!$H$2:$H$500,MATCH(64,'Task Log'!$Q$2:$Q$500,0))),"") | G68: =IFERROR(IF(INDEX('Task Log'!$I$2:$I$500,MATCH(64,'Task Log'!$Q$2:$Q$500,0))="","",INDEX('Task Log'!$I$2:$I$500,MATCH(64,'Task Log'!$Q$2:$Q$500,0))),"") | H68: =IFERROR(IF(INDEX('Task Log'!$J$2:$J$500,MATCH(64,'Task Log'!$Q$2:$Q$500,0))="","",INDEX('Task Log'!$J$2:$J$500,MATCH(64,'Task Log'!$Q$2:$Q$500,0))),"") | I68: =IFERROR(IF(INDEX('Task Log'!$O$2:$O$500,MATCH(64,'Task Log'!$Q$2:$Q$500,0))="","",INDEX('Task Log'!$O$2:$O$500,MATCH(64,'Task Log'!$Q$2:$Q$500,0))),"") | J68: =IFERROR(IF(INDEX('Task Log'!$K$2:$K$500,MATCH(64,'Task Log'!$Q$2:$Q$500,0))="","",INDEX('Task Log'!$K$2:$K$500,MATCH(64,'Task Log'!$Q$2:$Q$500,0))),"") | K68: =IFERROR(IF(INDEX('Task Log'!$N$2:$N$500,MATCH(64,'Task Log'!$Q$2:$Q$500,0))="","",INDEX('Task Log'!$N$2:$N$500,MATCH(64,'Task Log'!$Q$2:$Q$500,0))),"") | L68: =IFERROR(IF(INDEX('Task Log'!$P$2:$P$500,MATCH(64,'Task Log'!$Q$2:$Q$500,0))="","",INDEX('Task Log'!$P$2:$P$500,MATCH(64,'Task Log'!$Q$2:$Q$500,0))),"")
A69: =IFERROR(IF(MATCH(65,'Task Log'!$Q$2:$Q$500,0)>0,65,""),"") | B69: =IFERROR(IF(INDEX('Task Log'!$C$2:$C$500,MATCH(65,'Task Log'!$Q$2:$Q$500,0))="","",INDEX('Task Log'!$C$2:$C$500,MATCH(65,'Task Log'!$Q$2:$Q$500,0))),"") | C69: =IFERROR(IF(INDEX('Task Log'!$D$2:$D$500,MATCH(65,'Task Log'!$Q$2:$Q$500,0))="","",INDEX('Task Log'!$D$2:$D$500,MATCH(65,'Task Log'!$Q$2:$Q$500,0))),"") | D69: =IFERROR(IF(INDEX('Task Log'!$E$2:$E$500,MATCH(65,'Task Log'!$Q$2:$Q$500,0))="","",INDEX('Task Log'!$E$2:$E$500,MATCH(65,'Task Log'!$Q$2:$Q$500,0))),"") | E69: =IFERROR(IF(INDEX('Task Log'!$G$2:$G$500,MATCH(65,'Task Log'!$Q$2:$Q$500,0))="","",INDEX('Task Log'!$G$2:$G$500,MATCH(65,'Task Log'!$Q$2:$Q$500,0))),"") | F69: =IFERROR(IF(INDEX('Task Log'!$H$2:$H$500,MATCH(65,'Task Log'!$Q$2:$Q$500,0))="","",INDEX('Task Log'!$H$2:$H$500,MATCH(65,'Task Log'!$Q$2:$Q$500,0))),"") | G69: =IFERROR(IF(INDEX('Task Log'!$I$2:$I$500,MATCH(65,'Task Log'!$Q$2:$Q$500,0))="","",INDEX('Task Log'!$I$2:$I$500,MATCH(65,'Task Log'!$Q$2:$Q$500,0))),"") | H69: =IFERROR(IF(INDEX('Task Log'!$J$2:$J$500,MATCH(65,'Task Log'!$Q$2:$Q$500,0))="","",INDEX('Task Log'!$J$2:$J$500,MATCH(65,'Task Log'!$Q$2:$Q$500,0))),"") | I69: =IFERROR(IF(INDEX('Task Log'!$O$2:$O$500,MATCH(65,'Task Log'!$Q$2:$Q$500,0))="","",INDEX('Task Log'!$O$2:$O$500,MATCH(65,'Task Log'!$Q$2:$Q$500,0))),"") | J69: =IFERROR(IF(INDEX('Task Log'!$K$2:$K$500,MATCH(65,'Task Log'!$Q$2:$Q$500,0))="","",INDEX('Task Log'!$K$2:$K$500,MATCH(65,'Task Log'!$Q$2:$Q$500,0))),"") | K69: =IFERROR(IF(INDEX('Task Log'!$N$2:$N$500,MATCH(65,'Task Log'!$Q$2:$Q$500,0))="","",INDEX('Task Log'!$N$2:$N$500,MATCH(65,'Task Log'!$Q$2:$Q$500,0))),"") | L69: =IFERROR(IF(INDEX('Task Log'!$P$2:$P$500,MATCH(65,'Task Log'!$Q$2:$Q$500,0))="","",INDEX('Task Log'!$P$2:$P$500,MATCH(65,'Task Log'!$Q$2:$Q$500,0))),"")
A70: =IFERROR(IF(MATCH(66,'Task Log'!$Q$2:$Q$500,0)>0,66,""),"") | B70: =IFERROR(IF(INDEX('Task Log'!$C$2:$C$500,MATCH(66,'Task Log'!$Q$2:$Q$500,0))="","",INDEX('Task Log'!$C$2:$C$500,MATCH(66,'Task Log'!$Q$2:$Q$500,0))),"") | C70: =IFERROR(IF(INDEX('Task Log'!$D$2:$D$500,MATCH(66,'Task Log'!$Q$2:$Q$500,0))="","",INDEX('Task Log'!$D$2:$D$500,MATCH(66,'Task Log'!$Q$2:$Q$500,0))),"") | D70: =IFERROR(IF(INDEX('Task Log'!$E$2:$E$500,MATCH(66,'Task Log'!$Q$2:$Q$500,0))="","",INDEX('Task Log'!$E$2:$E$500,MATCH(66,'Task Log'!$Q$2:$Q$500,0))),"") | E70: =IFERROR(IF(INDEX('Task Log'!$G$2:$G$500,MATCH(66,'Task Log'!$Q$2:$Q$500,0))="","",INDEX('Task Log'!$G$2:$G$500,MATCH(66,'Task Log'!$Q$2:$Q$500,0))),"") | F70: =IFERROR(IF(INDEX('Task Log'!$H$2:$H$500,MATCH(66,'Task Log'!$Q$2:$Q$500,0))="","",INDEX('Task Log'!$H$2:$H$500,MATCH(66,'Task Log'!$Q$2:$Q$500,0))),"") | G70: =IFERROR(IF(INDEX('Task Log'!$I$2:$I$500,MATCH(66,'Task Log'!$Q$2:$Q$500,0))="","",INDEX('Task Log'!$I$2:$I$500,MATCH(66,'Task Log'!$Q$2:$Q$500,0))),"") | H70: =IFERROR(IF(INDEX('Task Log'!$J$2:$J$500,MATCH(66,'Task Log'!$Q$2:$Q$500,0))="","",INDEX('Task Log'!$J$2:$J$500,MATCH(66,'Task Log'!$Q$2:$Q$500,0))),"") | I70: =IFERROR(IF(INDEX('Task Log'!$O$2:$O$500,MATCH(66,'Task Log'!$Q$2:$Q$500,0))="","",INDEX('Task Log'!$O$2:$O$500,MATCH(66,'Task Log'!$Q$2:$Q$500,0))),"") | J70: =IFERROR(IF(INDEX('Task Log'!$K$2:$K$500,MATCH(66,'Task Log'!$Q$2:$Q$500,0))="","",INDEX('Task Log'!$K$2:$K$500,MATCH(66,'Task Log'!$Q$2:$Q$500,0))),"") | K70: =IFERROR(IF(INDEX('Task Log'!$N$2:$N$500,MATCH(66,'Task Log'!$Q$2:$Q$500,0))="","",INDEX('Task Log'!$N$2:$N$500,MATCH(66,'Task Log'!$Q$2:$Q$500,0))),"") | L70: =IFERROR(IF(INDEX('Task Log'!$P$2:$P$500,MATCH(66,'Task Log'!$Q$2:$Q$500,0))="","",INDEX('Task Log'!$P$2:$P$500,MATCH(66,'Task Log'!$Q$2:$Q$500,0))),"")
A71: =IFERROR(IF(MATCH(67,'Task Log'!$Q$2:$Q$500,0)>0,67,""),"") | B71: =IFERROR(IF(INDEX('Task Log'!$C$2:$C$500,MATCH(67,'Task Log'!$Q$2:$Q$500,0))="","",INDEX('Task Log'!$C$2:$C$500,MATCH(67,'Task Log'!$Q$2:$Q$500,0))),"") | C71: =IFERROR(IF(INDEX('Task Log'!$D$2:$D$500,MATCH(67,'Task Log'!$Q$2:$Q$500,0))="","",INDEX('Task Log'!$D$2:$D$500,MATCH(67,'Task Log'!$Q$2:$Q$500,0))),"") | D71: =IFERROR(IF(INDEX('Task Log'!$E$2:$E$500,MATCH(67,'Task Log'!$Q$2:$Q$500,0))="","",INDEX('Task Log'!$E$2:$E$500,MATCH(67,'Task Log'!$Q$2:$Q$500,0))),"") | E71: =IFERROR(IF(INDEX('Task Log'!$G$2:$G$500,MATCH(67,'Task Log'!$Q$2:$Q$500,0))="","",INDEX('Task Log'!$G$2:$G$500,MATCH(67,'Task Log'!$Q$2:$Q$500,0))),"") | F71: =IFERROR(IF(INDEX('Task Log'!$H$2:$H$500,MATCH(67,'Task Log'!$Q$2:$Q$500,0))="","",INDEX('Task Log'!$H$2:$H$500,MATCH(67,'Task Log'!$Q$2:$Q$500,0))),"") | G71: =IFERROR(IF(INDEX('Task Log'!$I$2:$I$500,MATCH(67,'Task Log'!$Q$2:$Q$500,0))="","",INDEX('Task Log'!$I$2:$I$500,MATCH(67,'Task Log'!$Q$2:$Q$500,0))),"") | H71: =IFERROR(IF(INDEX('Task Log'!$J$2:$J$500,MATCH(67,'Task Log'!$Q$2:$Q$500,0))="","",INDEX('Task Log'!$J$2:$J$500,MATCH(67,'Task Log'!$Q$2:$Q$500,0))),"") | I71: =IFERROR(IF(INDEX('Task Log'!$O$2:$O$500,MATCH(67,'Task Log'!$Q$2:$Q$500,0))="","",INDEX('Task Log'!$O$2:$O$500,MATCH(67,'Task Log'!$Q$2:$Q$500,0))),"") | J71: =IFERROR(IF(INDEX('Task Log'!$K$2:$K$500,MATCH(67,'Task Log'!$Q$2:$Q$500,0))="","",INDEX('Task Log'!$K$2:$K$500,MATCH(67,'Task Log'!$Q$2:$Q$500,0))),"") | K71: =IFERROR(IF(INDEX('Task Log'!$N$2:$N$500,MATCH(67,'Task Log'!$Q$2:$Q$500,0))="","",INDEX('Task Log'!$N$2:$N$500,MATCH(67,'Task Log'!$Q$2:$Q$500,0))),"") | L71: =IFERROR(IF(INDEX('Task Log'!$P$2:$P$500,MATCH(67,'Task Log'!$Q$2:$Q$500,0))="","",INDEX('Task Log'!$P$2:$P$500,MATCH(67,'Task Log'!$Q$2:$Q$500,0))),"")
A72: =IFERROR(IF(MATCH(68,'Task Log'!$Q$2:$Q$500,0)>0,68,""),"") | B72: =IFERROR(IF(INDEX('Task Log'!$C$2:$C$500,MATCH(68,'Task Log'!$Q$2:$Q$500,0))="","",INDEX('Task Log'!$C$2:$C$500,MATCH(68,'Task Log'!$Q$2:$Q$500,0))),"") | C72: =IFERROR(IF(INDEX('Task Log'!$D$2:$D$500,MATCH(68,'Task Log'!$Q$2:$Q$500,0))="","",INDEX('Task Log'!$D$2:$D$500,MATCH(68,'Task Log'!$Q$2:$Q$500,0))),"") | D72: =IFERROR(IF(INDEX('Task Log'!$E$2:$E$500,MATCH(68,'Task Log'!$Q$2:$Q$500,0))="","",INDEX('Task Log'!$E$2:$E$500,MATCH(68,'Task Log'!$Q$2:$Q$500,0))),"") | E72: =IFERROR(IF(INDEX('Task Log'!$G$2:$G$500,MATCH(68,'Task Log'!$Q$2:$Q$500,0))="","",INDEX('Task Log'!$G$2:$G$500,MATCH(68,'Task Log'!$Q$2:$Q$500,0))),"") | F72: =IFERROR(IF(INDEX('Task Log'!$H$2:$H$500,MATCH(68,'Task Log'!$Q$2:$Q$500,0))="","",INDEX('Task Log'!$H$2:$H$500,MATCH(68,'Task Log'!$Q$2:$Q$500,0))),"") | G72: =IFERROR(IF(INDEX('Task Log'!$I$2:$I$500,MATCH(68,'Task Log'!$Q$2:$Q$500,0))="","",INDEX('Task Log'!$I$2:$I$500,MATCH(68,'Task Log'!$Q$2:$Q$500,0))),"") | H72: =IFERROR(IF(INDEX('Task Log'!$J$2:$J$500,MATCH(68,'Task Log'!$Q$2:$Q$500,0))="","",INDEX('Task Log'!$J$2:$J$500,MATCH(68,'Task Log'!$Q$2:$Q$500,0))),"") | I72: =IFERROR(IF(INDEX('Task Log'!$O$2:$O$500,MATCH(68,'Task Log'!$Q$2:$Q$500,0))="","",INDEX('Task Log'!$O$2:$O$500,MATCH(68,'Task Log'!$Q$2:$Q$500,0))),"") | J72: =IFERROR(IF(INDEX('Task Log'!$K$2:$K$500,MATCH(68,'Task Log'!$Q$2:$Q$500,0))="","",INDEX('Task Log'!$K$2:$K$500,MATCH(68,'Task Log'!$Q$2:$Q$500,0))),"") | K72: =IFERROR(IF(INDEX('Task Log'!$N$2:$N$500,MATCH(68,'Task Log'!$Q$2:$Q$500,0))="","",INDEX('Task Log'!$N$2:$N$500,MATCH(68,'Task Log'!$Q$2:$Q$500,0))),"") | L72: =IFERROR(IF(INDEX('Task Log'!$P$2:$P$500,MATCH(68,'Task Log'!$Q$2:$Q$500,0))="","",INDEX('Task Log'!$P$2:$P$500,MATCH(68,'Task Log'!$Q$2:$Q$500,0))),"")
A73: =IFERROR(IF(MATCH(69,'Task Log'!$Q$2:$Q$500,0)>0,69,""),"") | B73: =IFERROR(IF(INDEX('Task Log'!$C$2:$C$500,MATCH(69,'Task Log'!$Q$2:$Q$500,0))="","",INDEX('Task Log'!$C$2:$C$500,MATCH(69,'Task Log'!$Q$2:$Q$500,0))),"") | C73: =IFERROR(IF(INDEX('Task Log'!$D$2:$D$500,MATCH(69,'Task Log'!$Q$2:$Q$500,0))="","",INDEX('Task Log'!$D$2:$D$500,MATCH(69,'Task Log'!$Q$2:$Q$500,0))),"") | D73: =IFERROR(IF(INDEX('Task Log'!$E$2:$E$500,MATCH(69,'Task Log'!$Q$2:$Q$500,0))="","",INDEX('Task Log'!$E$2:$E$500,MATCH(69,'Task Log'!$Q$2:$Q$500,0))),"") | E73: =IFERROR(IF(INDEX('Task Log'!$G$2:$G$500,MATCH(69,'Task Log'!$Q$2:$Q$500,0))="","",INDEX('Task Log'!$G$2:$G$500,MATCH(69,'Task Log'!$Q$2:$Q$500,0))),"") | F73: =IFERROR(IF(INDEX('Task Log'!$H$2:$H$500,MATCH(69,'Task Log'!$Q$2:$Q$500,0))="","",INDEX('Task Log'!$H$2:$H$500,MATCH(69,'Task Log'!$Q$2:$Q$500,0))),"") | G73: =IFERROR(IF(INDEX('Task Log'!$I$2:$I$500,MATCH(69,'Task Log'!$Q$2:$Q$500,0))="","",INDEX('Task Log'!$I$2:$I$500,MATCH(69,'Task Log'!$Q$2:$Q$500,0))),"") | H73: =IFERROR(IF(INDEX('Task Log'!$J$2:$J$500,MATCH(69,'Task Log'!$Q$2:$Q$500,0))="","",INDEX('Task Log'!$J$2:$J$500,MATCH(69,'Task Log'!$Q$2:$Q$500,0))),"") | I73: =IFERROR(IF(INDEX('Task Log'!$O$2:$O$500,MATCH(69,'Task Log'!$Q$2:$Q$500,0))="","",INDEX('Task Log'!$O$2:$O$500,MATCH(69,'Task Log'!$Q$2:$Q$500,0))),"") | J73: =IFERROR(IF(INDEX('Task Log'!$K$2:$K$500,MATCH(69,'Task Log'!$Q$2:$Q$500,0))="","",INDEX('Task Log'!$K$2:$K$500,MATCH(69,'Task Log'!$Q$2:$Q$500,0))),"") | K73: =IFERROR(IF(INDEX('Task Log'!$N$2:$N$500,MATCH(69,'Task Log'!$Q$2:$Q$500,0))="","",INDEX('Task Log'!$N$2:$N$500,MATCH(69,'Task Log'!$Q$2:$Q$500,0))),"") | L73: =IFERROR(IF(INDEX('Task Log'!$P$2:$P$500,MATCH(69,'Task Log'!$Q$2:$Q$500,0))="","",INDEX('Task Log'!$P$2:$P$500,MATCH(69,'Task Log'!$Q$2:$Q$500,0))),"")
A74: =IFERROR(IF(MATCH(70,'Task Log'!$Q$2:$Q$500,0)>0,70,""),"") | B74: =IFERROR(IF(INDEX('Task Log'!$C$2:$C$500,MATCH(70,'Task Log'!$Q$2:$Q$500,0))="","",INDEX('Task Log'!$C$2:$C$500,MATCH(70,'Task Log'!$Q$2:$Q$500,0))),"") | C74: =IFERROR(IF(INDEX('Task Log'!$D$2:$D$500,MATCH(70,'Task Log'!$Q$2:$Q$500,0))="","",INDEX('Task Log'!$D$2:$D$500,MATCH(70,'Task Log'!$Q$2:$Q$500,0))),"") | D74: =IFERROR(IF(INDEX('Task Log'!$E$2:$E$500,MATCH(70,'Task Log'!$Q$2:$Q$500,0))="","",INDEX('Task Log'!$E$2:$E$500,MATCH(70,'Task Log'!$Q$2:$Q$500,0))),"") | E74: =IFERROR(IF(INDEX('Task Log'!$G$2:$G$500,MATCH(70,'Task Log'!$Q$2:$Q$500,0))="","",INDEX('Task Log'!$G$2:$G$500,MATCH(70,'Task Log'!$Q$2:$Q$500,0))),"") | F74: =IFERROR(IF(INDEX('Task Log'!$H$2:$H$500,MATCH(70,'Task Log'!$Q$2:$Q$500,0))="","",INDEX('Task Log'!$H$2:$H$500,MATCH(70,'Task Log'!$Q$2:$Q$500,0))),"") | G74: =IFERROR(IF(INDEX('Task Log'!$I$2:$I$500,MATCH(70,'Task Log'!$Q$2:$Q$500,0))="","",INDEX('Task Log'!$I$2:$I$500,MATCH(70,'Task Log'!$Q$2:$Q$500,0))),"") | H74: =IFERROR(IF(INDEX('Task Log'!$J$2:$J$500,MATCH(70,'Task Log'!$Q$2:$Q$500,0))="","",INDEX('Task Log'!$J$2:$J$500,MATCH(70,'Task Log'!$Q$2:$Q$500,0))),"") | I74: =IFERROR(IF(INDEX('Task Log'!$O$2:$O$500,MATCH(70,'Task Log'!$Q$2:$Q$500,0))="","",INDEX('Task Log'!$O$2:$O$500,MATCH(70,'Task Log'!$Q$2:$Q$500,0))),"") | J74: =IFERROR(IF(INDEX('Task Log'!$K$2:$K$500,MATCH(70,'Task Log'!$Q$2:$Q$500,0))="","",INDEX('Task Log'!$K$2:$K$500,MATCH(70,'Task Log'!$Q$2:$Q$500,0))),"") | K74: =IFERROR(IF(INDEX('Task Log'!$N$2:$N$500,MATCH(70,'Task Log'!$Q$2:$Q$500,0))="","",INDEX('Task Log'!$N$2:$N$500,MATCH(70,'Task Log'!$Q$2:$Q$500,0))),"") | L74: =IFERROR(IF(INDEX('Task Log'!$P$2:$P$500,MATCH(70,'Task Log'!$Q$2:$Q$500,0))="","",INDEX('Task Log'!$P$2:$P$500,MATCH(70,'Task Log'!$Q$2:$Q$500,0))),"")
A75: =IFERROR(IF(MATCH(71,'Task Log'!$Q$2:$Q$500,0)>0,71,""),"") | B75: =IFERROR(IF(INDEX('Task Log'!$C$2:$C$500,MATCH(71,'Task Log'!$Q$2:$Q$500,0))="","",INDEX('Task Log'!$C$2:$C$500,MATCH(71,'Task Log'!$Q$2:$Q$500,0))),"") | C75: =IFERROR(IF(INDEX('Task Log'!$D$2:$D$500,MATCH(71,'Task Log'!$Q$2:$Q$500,0))="","",INDEX('Task Log'!$D$2:$D$500,MATCH(71,'Task Log'!$Q$2:$Q$500,0))),"") | D75: =IFERROR(IF(INDEX('Task Log'!$E$2:$E$500,MATCH(71,'Task Log'!$Q$2:$Q$500,0))="","",INDEX('Task Log'!$E$2:$E$500,MATCH(71,'Task Log'!$Q$2:$Q$500,0))),"") | E75: =IFERROR(IF(INDEX('Task Log'!$G$2:$G$500,MATCH(71,'Task Log'!$Q$2:$Q$500,0))="","",INDEX('Task Log'!$G$2:$G$500,MATCH(71,'Task Log'!$Q$2:$Q$500,0))),"") | F75: =IFERROR(IF(INDEX('Task Log'!$H$2:$H$500,MATCH(71,'Task Log'!$Q$2:$Q$500,0))="","",INDEX('Task Log'!$H$2:$H$500,MATCH(71,'Task Log'!$Q$2:$Q$500,0))),"") | G75: =IFERROR(IF(INDEX('Task Log'!$I$2:$I$500,MATCH(71,'Task Log'!$Q$2:$Q$500,0))="","",INDEX('Task Log'!$I$2:$I$500,MATCH(71,'Task Log'!$Q$2:$Q$500,0))),"") | H75: =IFERROR(IF(INDEX('Task Log'!$J$2:$J$500,MATCH(71,'Task Log'!$Q$2:$Q$500,0))="","",INDEX('Task Log'!$J$2:$J$500,MATCH(71,'Task Log'!$Q$2:$Q$500,0))),"") | I75: =IFERROR(IF(INDEX('Task Log'!$O$2:$O$500,MATCH(71,'Task Log'!$Q$2:$Q$500,0))="","",INDEX('Task Log'!$O$2:$O$500,MATCH(71,'Task Log'!$Q$2:$Q$500,0))),"") | J75: =IFERROR(IF(INDEX('Task Log'!$K$2:$K$500,MATCH(71,'Task Log'!$Q$2:$Q$500,0))="","",INDEX('Task Log'!$K$2:$K$500,MATCH(71,'Task Log'!$Q$2:$Q$500,0))),"") | K75: =IFERROR(IF(INDEX('Task Log'!$N$2:$N$500,MATCH(71,'Task Log'!$Q$2:$Q$500,0))="","",INDEX('Task Log'!$N$2:$N$500,MATCH(71,'Task Log'!$Q$2:$Q$500,0))),"") | L75: =IFERROR(IF(INDEX('Task Log'!$P$2:$P$500,MATCH(71,'Task Log'!$Q$2:$Q$500,0))="","",INDEX('Task Log'!$P$2:$P$500,MATCH(71,'Task Log'!$Q$2:$Q$500,0))),"")
A76: =IFERROR(IF(MATCH(72,'Task Log'!$Q$2:$Q$500,0)>0,72,""),"") | B76: =IFERROR(IF(INDEX('Task Log'!$C$2:$C$500,MATCH(72,'Task Log'!$Q$2:$Q$500,0))="","",INDEX('Task Log'!$C$2:$C$500,MATCH(72,'Task Log'!$Q$2:$Q$500,0))),"") | C76: =IFERROR(IF(INDEX('Task Log'!$D$2:$D$500,MATCH(72,'Task Log'!$Q$2:$Q$500,0))="","",INDEX('Task Log'!$D$2:$D$500,MATCH(72,'Task Log'!$Q$2:$Q$500,0))),"") | D76: =IFERROR(IF(INDEX('Task Log'!$E$2:$E$500,MATCH(72,'Task Log'!$Q$2:$Q$500,0))="","",INDEX('Task Log'!$E$2:$E$500,MATCH(72,'Task Log'!$Q$2:$Q$500,0))),"") | E76: =IFERROR(IF(INDEX('Task Log'!$G$2:$G$500,MATCH(72,'Task Log'!$Q$2:$Q$500,0))="","",INDEX('Task Log'!$G$2:$G$500,MATCH(72,'Task Log'!$Q$2:$Q$500,0))),"") | F76: =IFERROR(IF(INDEX('Task Log'!$H$2:$H$500,MATCH(72,'Task Log'!$Q$2:$Q$500,0))="","",INDEX('Task Log'!$H$2:$H$500,MATCH(72,'Task Log'!$Q$2:$Q$500,0))),"") | G76: =IFERROR(IF(INDEX('Task Log'!$I$2:$I$500,MATCH(72,'Task Log'!$Q$2:$Q$500,0))="","",INDEX('Task Log'!$I$2:$I$500,MATCH(72,'Task Log'!$Q$2:$Q$500,0))),"") | H76: =IFERROR(IF(INDEX('Task Log'!$J$2:$J$500,MATCH(72,'Task Log'!$Q$2:$Q$500,0))="","",INDEX('Task Log'!$J$2:$J$500,MATCH(72,'Task Log'!$Q$2:$Q$500,0))),"") | I76: =IFERROR(IF(INDEX('Task Log'!$O$2:$O$500,MATCH(72,'Task Log'!$Q$2:$Q$500,0))="","",INDEX('Task Log'!$O$2:$O$500,MATCH(72,'Task Log'!$Q$2:$Q$500,0))),"") | J76: =IFERROR(IF(INDEX('Task Log'!$K$2:$K$500,MATCH(72,'Task Log'!$Q$2:$Q$500,0))="","",INDEX('Task Log'!$K$2:$K$500,MATCH(72,'Task Log'!$Q$2:$Q$500,0))),"") | K76: =IFERROR(IF(INDEX('Task Log'!$N$2:$N$500,MATCH(72,'Task Log'!$Q$2:$Q$500,0))="","",INDEX('Task Log'!$N$2:$N$500,MATCH(72,'Task Log'!$Q$2:$Q$500,0))),"") | L76: =IFERROR(IF(INDEX('Task Log'!$P$2:$P$500,MATCH(72,'Task Log'!$Q$2:$Q$500,0))="","",INDEX('Task Log'!$P$2:$P$500,MATCH(72,'Task Log'!$Q$2:$Q$500,0))),"")
A77: =IFERROR(IF(MATCH(73,'Task Log'!$Q$2:$Q$500,0)>0,73,""),"") | B77: =IFERROR(IF(INDEX('Task Log'!$C$2:$C$500,MATCH(73,'Task Log'!$Q$2:$Q$500,0))="","",INDEX('Task Log'!$C$2:$C$500,MATCH(73,'Task Log'!$Q$2:$Q$500,0))),"") | C77: =IFERROR(IF(INDEX('Task Log'!$D$2:$D$500,MATCH(73,'Task Log'!$Q$2:$Q$500,0))="","",INDEX('Task Log'!$D$2:$D$500,MATCH(73,'Task Log'!$Q$2:$Q$500,0))),"") | D77: =IFERROR(IF(INDEX('Task Log'!$E$2:$E$500,MATCH(73,'Task Log'!$Q$2:$Q$500,0))="","",INDEX('Task Log'!$E$2:$E$500,MATCH(73,'Task Log'!$Q$2:$Q$500,0))),"") | E77: =IFERROR(IF(INDEX('Task Log'!$G$2:$G$500,MATCH(73,'Task Log'!$Q$2:$Q$500,0))="","",INDEX('Task Log'!$G$2:$G$500,MATCH(73,'Task Log'!$Q$2:$Q$500,0))),"") | F77: =IFERROR(IF(INDEX('Task Log'!$H$2:$H$500,MATCH(73,'Task Log'!$Q$2:$Q$500,0))="","",INDEX('Task Log'!$H$2:$H$500,MATCH(73,'Task Log'!$Q$2:$Q$500,0))),"") | G77: =IFERROR(IF(INDEX('Task Log'!$I$2:$I$500,MATCH(73,'Task Log'!$Q$2:$Q$500,0))="","",INDEX('Task Log'!$I$2:$I$500,MATCH(73,'Task Log'!$Q$2:$Q$500,0))),"") | H77: =IFERROR(IF(INDEX('Task Log'!$J$2:$J$500,MATCH(73,'Task Log'!$Q$2:$Q$500,0))="","",INDEX('Task Log'!$J$2:$J$500,MATCH(73,'Task Log'!$Q$2:$Q$500,0))),"") | I77: =IFERROR(IF(INDEX('Task Log'!$O$2:$O$500,MATCH(73,'Task Log'!$Q$2:$Q$500,0))="","",INDEX('Task Log'!$O$2:$O$500,MATCH(73,'Task Log'!$Q$2:$Q$500,0))),"") | J77: =IFERROR(IF(INDEX('Task Log'!$K$2:$K$500,MATCH(73,'Task Log'!$Q$2:$Q$500,0))="","",INDEX('Task Log'!$K$2:$K$500,MATCH(73,'Task Log'!$Q$2:$Q$500,0))),"") | K77: =IFERROR(IF(INDEX('Task Log'!$N$2:$N$500,MATCH(73,'Task Log'!$Q$2:$Q$500,0))="","",INDEX('Task Log'!$N$2:$N$500,MATCH(73,'Task Log'!$Q$2:$Q$500,0))),"") | L77: =IFERROR(IF(INDEX('Task Log'!$P$2:$P$500,MATCH(73,'Task Log'!$Q$2:$Q$500,0))="","",INDEX('Task Log'!$P$2:$P$500,MATCH(73,'Task Log'!$Q$2:$Q$500,0))),"")
A78: =IFERROR(IF(MATCH(74,'Task Log'!$Q$2:$Q$500,0)>0,74,""),"") | B78: =IFERROR(IF(INDEX('Task Log'!$C$2:$C$500,MATCH(74,'Task Log'!$Q$2:$Q$500,0))="","",INDEX('Task Log'!$C$2:$C$500,MATCH(74,'Task Log'!$Q$2:$Q$500,0))),"") | C78: =IFERROR(IF(INDEX('Task Log'!$D$2:$D$500,MATCH(74,'Task Log'!$Q$2:$Q$500,0))="","",INDEX('Task Log'!$D$2:$D$500,MATCH(74,'Task Log'!$Q$2:$Q$500,0))),"") | D78: =IFERROR(IF(INDEX('Task Log'!$E$2:$E$500,MATCH(74,'Task Log'!$Q$2:$Q$500,0))="","",INDEX('Task Log'!$E$2:$E$500,MATCH(74,'Task Log'!$Q$2:$Q$500,0))),"") | E78: =IFERROR(IF(INDEX('Task Log'!$G$2:$G$500,MATCH(74,'Task Log'!$Q$2:$Q$500,0))="","",INDEX('Task Log'!$G$2:$G$500,MATCH(74,'Task Log'!$Q$2:$Q$500,0))),"") | F78: =IFERROR(IF(INDEX('Task Log'!$H$2:$H$500,MATCH(74,'Task Log'!$Q$2:$Q$500,0))="","",INDEX('Task Log'!$H$2:$H$500,MATCH(74,'Task Log'!$Q$2:$Q$500,0))),"") | G78: =IFERROR(IF(INDEX('Task Log'!$I$2:$I$500,MATCH(74,'Task Log'!$Q$2:$Q$500,0))="","",INDEX('Task Log'!$I$2:$I$500,MATCH(74,'Task Log'!$Q$2:$Q$500,0))),"") | H78: =IFERROR(IF(INDEX('Task Log'!$J$2:$J$500,MATCH(74,'Task Log'!$Q$2:$Q$500,0))="","",INDEX('Task Log'!$J$2:$J$500,MATCH(74,'Task Log'!$Q$2:$Q$500,0))),"") | I78: =IFERROR(IF(INDEX('Task Log'!$O$2:$O$500,MATCH(74,'Task Log'!$Q$2:$Q$500,0))="","",INDEX('Task Log'!$O$2:$O$500,MATCH(74,'Task Log'!$Q$2:$Q$500,0))),"") | J78: =IFERROR(IF(INDEX('Task Log'!$K$2:$K$500,MATCH(74,'Task Log'!$Q$2:$Q$500,0))="","",INDEX('Task Log'!$K$2:$K$500,MATCH(74,'Task Log'!$Q$2:$Q$500,0))),"") | K78: =IFERROR(IF(INDEX('Task Log'!$N$2:$N$500,MATCH(74,'Task Log'!$Q$2:$Q$500,0))="","",INDEX('Task Log'!$N$2:$N$500,MATCH(74,'Task Log'!$Q$2:$Q$500,0))),"") | L78: =IFERROR(IF(INDEX('Task Log'!$P$2:$P$500,MATCH(74,'Task Log'!$Q$2:$Q$500,0))="","",INDEX('Task Log'!$P$2:$P$500,MATCH(74,'Task Log'!$Q$2:$Q$500,0))),"")
A79: =IFERROR(IF(MATCH(75,'Task Log'!$Q$2:$Q$500,0)>0,75,""),"") | B79: =IFERROR(IF(INDEX('Task Log'!$C$2:$C$500,MATCH(75,'Task Log'!$Q$2:$Q$500,0))="","",INDEX('Task Log'!$C$2:$C$500,MATCH(75,'Task Log'!$Q$2:$Q$500,0))),"") | C79: =IFERROR(IF(INDEX('Task Log'!$D$2:$D$500,MATCH(75,'Task Log'!$Q$2:$Q$500,0))="","",INDEX('Task Log'!$D$2:$D$500,MATCH(75,'Task Log'!$Q$2:$Q$500,0))),"") | D79: =IFERROR(IF(INDEX('Task Log'!$E$2:$E$500,MATCH(75,'Task Log'!$Q$2:$Q$500,0))="","",INDEX('Task Log'!$E$2:$E$500,MATCH(75,'Task Log'!$Q$2:$Q$500,0))),"") | E79: =IFERROR(IF(INDEX('Task Log'!$G$2:$G$500,MATCH(75,'Task Log'!$Q$2:$Q$500,0))="","",INDEX('Task Log'!$G$2:$G$500,MATCH(75,'Task Log'!$Q$2:$Q$500,0))),"") | F79: =IFERROR(IF(INDEX('Task Log'!$H$2:$H$500,MATCH(75,'Task Log'!$Q$2:$Q$500,0))="","",INDEX('Task Log'!$H$2:$H$500,MATCH(75,'Task Log'!$Q$2:$Q$500,0))),"") | G79: =IFERROR(IF(INDEX('Task Log'!$I$2:$I$500,MATCH(75,'Task Log'!$Q$2:$Q$500,0))="","",INDEX('Task Log'!$I$2:$I$500,MATCH(75,'Task Log'!$Q$2:$Q$500,0))),"") | H79: =IFERROR(IF(INDEX('Task Log'!$J$2:$J$500,MATCH(75,'Task Log'!$Q$2:$Q$500,0))="","",INDEX('Task Log'!$J$2:$J$500,MATCH(75,'Task Log'!$Q$2:$Q$500,0))),"") | I79: =IFERROR(IF(INDEX('Task Log'!$O$2:$O$500,MATCH(75,'Task Log'!$Q$2:$Q$500,0))="","",INDEX('Task Log'!$O$2:$O$500,MATCH(75,'Task Log'!$Q$2:$Q$500,0))),"") | J79: =IFERROR(IF(INDEX('Task Log'!$K$2:$K$500,MATCH(75,'Task Log'!$Q$2:$Q$500,0))="","",INDEX('Task Log'!$K$2:$K$500,MATCH(75,'Task Log'!$Q$2:$Q$500,0))),"") | K79: =IFERROR(IF(INDEX('Task Log'!$N$2:$N$500,MATCH(75,'Task Log'!$Q$2:$Q$500,0))="","",INDEX('Task Log'!$N$2:$N$500,MATCH(75,'Task Log'!$Q$2:$Q$500,0))),"") | L79: =IFERROR(IF(INDEX('Task Log'!$P$2:$P$500,MATCH(75,'Task Log'!$Q$2:$Q$500,0))="","",INDEX('Task Log'!$P$2:$P$500,MATCH(75,'Task Log'!$Q$2:$Q$500,0))),"")
A80: =IFERROR(IF(MATCH(76,'Task Log'!$Q$2:$Q$500,0)>0,76,""),"") | B80: =IFERROR(IF(INDEX('Task Log'!$C$2:$C$500,MATCH(76,'Task Log'!$Q$2:$Q$500,0))="","",INDEX('Task Log'!$C$2:$C$500,MATCH(76,'Task Log'!$Q$2:$Q$500,0))),"") | C80: =IFERROR(IF(INDEX('Task Log'!$D$2:$D$500,MATCH(76,'Task Log'!$Q$2:$Q$500,0))="","",INDEX('Task Log'!$D$2:$D$500,MATCH(76,'Task Log'!$Q$2:$Q$500,0))),"") | D80: =IFERROR(IF(INDEX('Task Log'!$E$2:$E$500,MATCH(76,'Task Log'!$Q$2:$Q$500,0))="","",INDEX('Task Log'!$E$2:$E$500,MATCH(76,'Task Log'!$Q$2:$Q$500,0))),"") | E80: =IFERROR(IF(INDEX('Task Log'!$G$2:$G$500,MATCH(76,'Task Log'!$Q$2:$Q$500,0))="","",INDEX('Task Log'!$G$2:$G$500,MATCH(76,'Task Log'!$Q$2:$Q$500,0))),"") | F80: =IFERROR(IF(INDEX('Task Log'!$H$2:$H$500,MATCH(76,'Task Log'!$Q$2:$Q$500,0))="","",INDEX('Task Log'!$H$2:$H$500,MATCH(76,'Task Log'!$Q$2:$Q$500,0))),"") | G80: =IFERROR(IF(INDEX('Task Log'!$I$2:$I$500,MATCH(76,'Task Log'!$Q$2:$Q$500,0))="","",INDEX('Task Log'!$I$2:$I$500,MATCH(76,'Task Log'!$Q$2:$Q$500,0))),"") | H80: =IFERROR(IF(INDEX('Task Log'!$J$2:$J$500,MATCH(76,'Task Log'!$Q$2:$Q$500,0))="","",INDEX('Task Log'!$J$2:$J$500,MATCH(76,'Task Log'!$Q$2:$Q$500,0))),"") | I80: =IFERROR(IF(INDEX('Task Log'!$O$2:$O$500,MATCH(76,'Task Log'!$Q$2:$Q$500,0))="","",INDEX('Task Log'!$O$2:$O$500,MATCH(76,'Task Log'!$Q$2:$Q$500,0))),"") | J80: =IFERROR(IF(INDEX('Task Log'!$K$2:$K$500,MATCH(76,'Task Log'!$Q$2:$Q$500,0))="","",INDEX('Task Log'!$K$2:$K$500,MATCH(76,'Task Log'!$Q$2:$Q$500,0))),"") | K80: =IFERROR(IF(INDEX('Task Log'!$N$2:$N$500,MATCH(76,'Task Log'!$Q$2:$Q$500,0))="","",INDEX('Task Log'!$N$2:$N$500,MATCH(76,'Task Log'!$Q$2:$Q$500,0))),"") | L80: =IFERROR(IF(INDEX('Task Log'!$P$2:$P$500,MATCH(76,'Task Log'!$Q$2:$Q$500,0))="","",INDEX('Task Log'!$P$2:$P$500,MATCH(76,'Task Log'!$Q$2:$Q$500,0))),"")
A81: =IFERROR(IF(MATCH(77,'Task Log'!$Q$2:$Q$500,0)>0,77,""),"") | B81: =IFERROR(IF(INDEX('Task Log'!$C$2:$C$500,MATCH(77,'Task Log'!$Q$2:$Q$500,0))="","",INDEX('Task Log'!$C$2:$C$500,MATCH(77,'Task Log'!$Q$2:$Q$500,0))),"") | C81: =IFERROR(IF(INDEX('Task Log'!$D$2:$D$500,MATCH(77,'Task Log'!$Q$2:$Q$500,0))="","",INDEX('Task Log'!$D$2:$D$500,MATCH(77,'Task Log'!$Q$2:$Q$500,0))),"") | D81: =IFERROR(IF(INDEX('Task Log'!$E$2:$E$500,MATCH(77,'Task Log'!$Q$2:$Q$500,0))="","",INDEX('Task Log'!$E$2:$E$500,MATCH(77,'Task Log'!$Q$2:$Q$500,0))),"") | E81: =IFERROR(IF(INDEX('Task Log'!$G$2:$G$500,MATCH(77,'Task Log'!$Q$2:$Q$500,0))="","",INDEX('Task Log'!$G$2:$G$500,MATCH(77,'Task Log'!$Q$2:$Q$500,0))),"") | F81: =IFERROR(IF(INDEX('Task Log'!$H$2:$H$500,MATCH(77,'Task Log'!$Q$2:$Q$500,0))="","",INDEX('Task Log'!$H$2:$H$500,MATCH(77,'Task Log'!$Q$2:$Q$500,0))),"") | G81: =IFERROR(IF(INDEX('Task Log'!$I$2:$I$500,MATCH(77,'Task Log'!$Q$2:$Q$500,0))="","",INDEX('Task Log'!$I$2:$I$500,MATCH(77,'Task Log'!$Q$2:$Q$500,0))),"") | H81: =IFERROR(IF(INDEX('Task Log'!$J$2:$J$500,MATCH(77,'Task Log'!$Q$2:$Q$500,0))="","",INDEX('Task Log'!$J$2:$J$500,MATCH(77,'Task Log'!$Q$2:$Q$500,0))),"") | I81: =IFERROR(IF(INDEX('Task Log'!$O$2:$O$500,MATCH(77,'Task Log'!$Q$2:$Q$500,0))="","",INDEX('Task Log'!$O$2:$O$500,MATCH(77,'Task Log'!$Q$2:$Q$500,0))),"") | J81: =IFERROR(IF(INDEX('Task Log'!$K$2:$K$500,MATCH(77,'Task Log'!$Q$2:$Q$500,0))="","",INDEX('Task Log'!$K$2:$K$500,MATCH(77,'Task Log'!$Q$2:$Q$500,0))),"") | K81: =IFERROR(IF(INDEX('Task Log'!$N$2:$N$500,MATCH(77,'Task Log'!$Q$2:$Q$500,0))="","",INDEX('Task Log'!$N$2:$N$500,MATCH(77,'Task Log'!$Q$2:$Q$500,0))),"") | L81: =IFERROR(IF(INDEX('Task Log'!$P$2:$P$500,MATCH(77,'Task Log'!$Q$2:$Q$500,0))="","",INDEX('Task Log'!$P$2:$P$500,MATCH(77,'Task Log'!$Q$2:$Q$500,0))),"")
A82: =IFERROR(IF(MATCH(78,'Task Log'!$Q$2:$Q$500,0)>0,78,""),"") | B82: =IFERROR(IF(INDEX('Task Log'!$C$2:$C$500,MATCH(78,'Task Log'!$Q$2:$Q$500,0))="","",INDEX('Task Log'!$C$2:$C$500,MATCH(78,'Task Log'!$Q$2:$Q$500,0))),"") | C82: =IFERROR(IF(INDEX('Task Log'!$D$2:$D$500,MATCH(78,'Task Log'!$Q$2:$Q$500,0))="","",INDEX('Task Log'!$D$2:$D$500,MATCH(78,'Task Log'!$Q$2:$Q$500,0))),"") | D82: =IFERROR(IF(INDEX('Task Log'!$E$2:$E$500,MATCH(78,'Task Log'!$Q$2:$Q$500,0))="","",INDEX('Task Log'!$E$2:$E$500,MATCH(78,'Task Log'!$Q$2:$Q$500,0))),"") | E82: =IFERROR(IF(INDEX('Task Log'!$G$2:$G$500,MATCH(78,'Task Log'!$Q$2:$Q$500,0))="","",INDEX('Task Log'!$G$2:$G$500,MATCH(78,'Task Log'!$Q$2:$Q$500,0))),"") | F82: =IFERROR(IF(INDEX('Task Log'!$H$2:$H$500,MATCH(78,'Task Log'!$Q$2:$Q$500,0))="","",INDEX('Task Log'!$H$2:$H$500,MATCH(78,'Task Log'!$Q$2:$Q$500,0))),"") | G82: =IFERROR(IF(INDEX('Task Log'!$I$2:$I$500,MATCH(78,'Task Log'!$Q$2:$Q$500,0))="","",INDEX('Task Log'!$I$2:$I$500,MATCH(78,'Task Log'!$Q$2:$Q$500,0))),"") | H82: =IFERROR(IF(INDEX('Task Log'!$J$2:$J$500,MATCH(78,'Task Log'!$Q$2:$Q$500,0))="","",INDEX('Task Log'!$J$2:$J$500,MATCH(78,'Task Log'!$Q$2:$Q$500,0))),"") | I82: =IFERROR(IF(INDEX('Task Log'!$O$2:$O$500,MATCH(78,'Task Log'!$Q$2:$Q$500,0))="","",INDEX('Task Log'!$O$2:$O$500,MATCH(78,'Task Log'!$Q$2:$Q$500,0))),"") | J82: =IFERROR(IF(INDEX('Task Log'!$K$2:$K$500,MATCH(78,'Task Log'!$Q$2:$Q$500,0))="","",INDEX('Task Log'!$K$2:$K$500,MATCH(78,'Task Log'!$Q$2:$Q$500,0))),"") | K82: =IFERROR(IF(INDEX('Task Log'!$N$2:$N$500,MATCH(78,'Task Log'!$Q$2:$Q$500,0))="","",INDEX('Task Log'!$N$2:$N$500,MATCH(78,'Task Log'!$Q$2:$Q$500,0))),"") | L82: =IFERROR(IF(INDEX('Task Log'!$P$2:$P$500,MATCH(78,'Task Log'!$Q$2:$Q$500,0))="","",INDEX('Task Log'!$P$2:$P$500,MATCH(78,'Task Log'!$Q$2:$Q$500,0))),"")
A83: =IFERROR(IF(MATCH(79,'Task Log'!$Q$2:$Q$500,0)>0,79,""),"") | B83: =IFERROR(IF(INDEX('Task Log'!$C$2:$C$500,MATCH(79,'Task Log'!$Q$2:$Q$500,0))="","",INDEX('Task Log'!$C$2:$C$500,MATCH(79,'Task Log'!$Q$2:$Q$500,0))),"") | C83: =IFERROR(IF(INDEX('Task Log'!$D$2:$D$500,MATCH(79,'Task Log'!$Q$2:$Q$500,0))="","",INDEX('Task Log'!$D$2:$D$500,MATCH(79,'Task Log'!$Q$2:$Q$500,0))),"") | D83: =IFERROR(IF(INDEX('Task Log'!$E$2:$E$500,MATCH(79,'Task Log'!$Q$2:$Q$500,0))="","",INDEX('Task Log'!$E$2:$E$500,MATCH(79,'Task Log'!$Q$2:$Q$500,0))),"") | E83: =IFERROR(IF(INDEX('Task Log'!$G$2:$G$500,MATCH(79,'Task Log'!$Q$2:$Q$500,0))="","",INDEX('Task Log'!$G$2:$G$500,MATCH(79,'Task Log'!$Q$2:$Q$500,0))),"") | F83: =IFERROR(IF(INDEX('Task Log'!$H$2:$H$500,MATCH(79,'Task Log'!$Q$2:$Q$500,0))="","",INDEX('Task Log'!$H$2:$H$500,MATCH(79,'Task Log'!$Q$2:$Q$500,0))),"") | G83: =IFERROR(IF(INDEX('Task Log'!$I$2:$I$500,MATCH(79,'Task Log'!$Q$2:$Q$500,0))="","",INDEX('Task Log'!$I$2:$I$500,MATCH(79,'Task Log'!$Q$2:$Q$500,0))),"") | H83: =IFERROR(IF(INDEX('Task Log'!$J$2:$J$500,MATCH(79,'Task Log'!$Q$2:$Q$500,0))="","",INDEX('Task Log'!$J$2:$J$500,MATCH(79,'Task Log'!$Q$2:$Q$500,0))),"") | I83: =IFERROR(IF(INDEX('Task Log'!$O$2:$O$500,MATCH(79,'Task Log'!$Q$2:$Q$500,0))="","",INDEX('Task Log'!$O$2:$O$500,MATCH(79,'Task Log'!$Q$2:$Q$500,0))),"") | J83: =IFERROR(IF(INDEX('Task Log'!$K$2:$K$500,MATCH(79,'Task Log'!$Q$2:$Q$500,0))="","",INDEX('Task Log'!$K$2:$K$500,MATCH(79,'Task Log'!$Q$2:$Q$500,0))),"") | K83: =IFERROR(IF(INDEX('Task Log'!$N$2:$N$500,MATCH(79,'Task Log'!$Q$2:$Q$500,0))="","",INDEX('Task Log'!$N$2:$N$500,MATCH(79,'Task Log'!$Q$2:$Q$500,0))),"") | L83: =IFERROR(IF(INDEX('Task Log'!$P$2:$P$500,MATCH(79,'Task Log'!$Q$2:$Q$500,0))="","",INDEX('Task Log'!$P$2:$P$500,MATCH(79,'Task Log'!$Q$2:$Q$500,0))),"")
A84: =IFERROR(IF(MATCH(80,'Task Log'!$Q$2:$Q$500,0)>0,80,""),"") | B84: =IFERROR(IF(INDEX('Task Log'!$C$2:$C$500,MATCH(80,'Task Log'!$Q$2:$Q$500,0))="","",INDEX('Task Log'!$C$2:$C$500,MATCH(80,'Task Log'!$Q$2:$Q$500,0))),"") | C84: =IFERROR(IF(INDEX('Task Log'!$D$2:$D$500,MATCH(80,'Task Log'!$Q$2:$Q$500,0))="","",INDEX('Task Log'!$D$2:$D$500,MATCH(80,'Task Log'!$Q$2:$Q$500,0))),"") | D84: =IFERROR(IF(INDEX('Task Log'!$E$2:$E$500,MATCH(80,'Task Log'!$Q$2:$Q$500,0))="","",INDEX('Task Log'!$E$2:$E$500,MATCH(80,'Task Log'!$Q$2:$Q$500,0))),"") | E84: =IFERROR(IF(INDEX('Task Log'!$G$2:$G$500,MATCH(80,'Task Log'!$Q$2:$Q$500,0))="","",INDEX('Task Log'!$G$2:$G$500,MATCH(80,'Task Log'!$Q$2:$Q$500,0))),"") | F84: =IFERROR(IF(INDEX('Task Log'!$H$2:$H$500,MATCH(80,'Task Log'!$Q$2:$Q$500,0))="","",INDEX('Task Log'!$H$2:$H$500,MATCH(80,'Task Log'!$Q$2:$Q$500,0))),"") | G84: =IFERROR(IF(INDEX('Task Log'!$I$2:$I$500,MATCH(80,'Task Log'!$Q$2:$Q$500,0))="","",INDEX('Task Log'!$I$2:$I$500,MATCH(80,'Task Log'!$Q$2:$Q$500,0))),"") | H84: =IFERROR(IF(INDEX('Task Log'!$J$2:$J$500,MATCH(80,'Task Log'!$Q$2:$Q$500,0))="","",INDEX('Task Log'!$J$2:$J$500,MATCH(80,'Task Log'!$Q$2:$Q$500,0))),"") | I84: =IFERROR(IF(INDEX('Task Log'!$O$2:$O$500,MATCH(80,'Task Log'!$Q$2:$Q$500,0))="","",INDEX('Task Log'!$O$2:$O$500,MATCH(80,'Task Log'!$Q$2:$Q$500,0))),"") | J84: =IFERROR(IF(INDEX('Task Log'!$K$2:$K$500,MATCH(80,'Task Log'!$Q$2:$Q$500,0))="","",INDEX('Task Log'!$K$2:$K$500,MATCH(80,'Task Log'!$Q$2:$Q$500,0))),"") | K84: =IFERROR(IF(INDEX('Task Log'!$N$2:$N$500,MATCH(80,'Task Log'!$Q$2:$Q$500,0))="","",INDEX('Task Log'!$N$2:$N$500,MATCH(80,'Task Log'!$Q$2:$Q$500,0))),"") | L84: =IFERROR(IF(INDEX('Task Log'!$P$2:$P$500,MATCH(80,'Task Log'!$Q$2:$Q$500,0))="","",INDEX('Task Log'!$P$2:$P$500,MATCH(80,'Task Log'!$Q$2:$Q$500,0))),"")
A85: =IFERROR(IF(MATCH(81,'Task Log'!$Q$2:$Q$500,0)>0,81,""),"") | B85: =IFERROR(IF(INDEX('Task Log'!$C$2:$C$500,MATCH(81,'Task Log'!$Q$2:$Q$500,0))="","",INDEX('Task Log'!$C$2:$C$500,MATCH(81,'Task Log'!$Q$2:$Q$500,0))),"") | C85: =IFERROR(IF(INDEX('Task Log'!$D$2:$D$500,MATCH(81,'Task Log'!$Q$2:$Q$500,0))="","",INDEX('Task Log'!$D$2:$D$500,MATCH(81,'Task Log'!$Q$2:$Q$500,0))),"") | D85: =IFERROR(IF(INDEX('Task Log'!$E$2:$E$500,MATCH(81,'Task Log'!$Q$2:$Q$500,0))="","",INDEX('Task Log'!$E$2:$E$500,MATCH(81,'Task Log'!$Q$2:$Q$500,0))),"") | E85: =IFERROR(IF(INDEX('Task Log'!$G$2:$G$500,MATCH(81,'Task Log'!$Q$2:$Q$500,0))="","",INDEX('Task Log'!$G$2:$G$500,MATCH(81,'Task Log'!$Q$2:$Q$500,0))),"") | F85: =IFERROR(IF(INDEX('Task Log'!$H$2:$H$500,MATCH(81,'Task Log'!$Q$2:$Q$500,0))="","",INDEX('Task Log'!$H$2:$H$500,MATCH(81,'Task Log'!$Q$2:$Q$500,0))),"") | G85: =IFERROR(IF(INDEX('Task Log'!$I$2:$I$500,MATCH(81,'Task Log'!$Q$2:$Q$500,0))="","",INDEX('Task Log'!$I$2:$I$500,MATCH(81,'Task Log'!$Q$2:$Q$500,0))),"") | H85: =IFERROR(IF(INDEX('Task Log'!$J$2:$J$500,MATCH(81,'Task Log'!$Q$2:$Q$500,0))="","",INDEX('Task Log'!$J$2:$J$500,MATCH(81,'Task Log'!$Q$2:$Q$500,0))),"") | I85: =IFERROR(IF(INDEX('Task Log'!$O$2:$O$500,MATCH(81,'Task Log'!$Q$2:$Q$500,0))="","",INDEX('Task Log'!$O$2:$O$500,MATCH(81,'Task Log'!$Q$2:$Q$500,0))),"") | J85: =IFERROR(IF(INDEX('Task Log'!$K$2:$K$500,MATCH(81,'Task Log'!$Q$2:$Q$500,0))="","",INDEX('Task Log'!$K$2:$K$500,MATCH(81,'Task Log'!$Q$2:$Q$500,0))),"") | K85: =IFERROR(IF(INDEX('Task Log'!$N$2:$N$500,MATCH(81,'Task Log'!$Q$2:$Q$500,0))="","",INDEX('Task Log'!$N$2:$N$500,MATCH(81,'Task Log'!$Q$2:$Q$500,0))),"") | L85: =IFERROR(IF(INDEX('Task Log'!$P$2:$P$500,MATCH(81,'Task Log'!$Q$2:$Q$500,0))="","",INDEX('Task Log'!$P$2:$P$500,MATCH(81,'Task Log'!$Q$2:$Q$500,0))),"")
A86: =IFERROR(IF(MATCH(82,'Task Log'!$Q$2:$Q$500,0)>0,82,""),"") | B86: =IFERROR(IF(INDEX('Task Log'!$C$2:$C$500,MATCH(82,'Task Log'!$Q$2:$Q$500,0))="","",INDEX('Task Log'!$C$2:$C$500,MATCH(82,'Task Log'!$Q$2:$Q$500,0))),"") | C86: =IFERROR(IF(INDEX('Task Log'!$D$2:$D$500,MATCH(82,'Task Log'!$Q$2:$Q$500,0))="","",INDEX('Task Log'!$D$2:$D$500,MATCH(82,'Task Log'!$Q$2:$Q$500,0))),"") | D86: =IFERROR(IF(INDEX('Task Log'!$E$2:$E$500,MATCH(82,'Task Log'!$Q$2:$Q$500,0))="","",INDEX('Task Log'!$E$2:$E$500,MATCH(82,'Task Log'!$Q$2:$Q$500,0))),"") | E86: =IFERROR(IF(INDEX('Task Log'!$G$2:$G$500,MATCH(82,'Task Log'!$Q$2:$Q$500,0))="","",INDEX('Task Log'!$G$2:$G$500,MATCH(82,'Task Log'!$Q$2:$Q$500,0))),"") | F86: =IFERROR(IF(INDEX('Task Log'!$H$2:$H$500,MATCH(82,'Task Log'!$Q$2:$Q$500,0))="","",INDEX('Task Log'!$H$2:$H$500,MATCH(82,'Task Log'!$Q$2:$Q$500,0))),"") | G86: =IFERROR(IF(INDEX('Task Log'!$I$2:$I$500,MATCH(82,'Task Log'!$Q$2:$Q$500,0))="","",INDEX('Task Log'!$I$2:$I$500,MATCH(82,'Task Log'!$Q$2:$Q$500,0))),"") | H86: =IFERROR(IF(INDEX('Task Log'!$J$2:$J$500,MATCH(82,'Task Log'!$Q$2:$Q$500,0))="","",INDEX('Task Log'!$J$2:$J$500,MATCH(82,'Task Log'!$Q$2:$Q$500,0))),"") | I86: =IFERROR(IF(INDEX('Task Log'!$O$2:$O$500,MATCH(82,'Task Log'!$Q$2:$Q$500,0))="","",INDEX('Task Log'!$O$2:$O$500,MATCH(82,'Task Log'!$Q$2:$Q$500,0))),"") | J86: =IFERROR(IF(INDEX('Task Log'!$K$2:$K$500,MATCH(82,'Task Log'!$Q$2:$Q$500,0))="","",INDEX('Task Log'!$K$2:$K$500,MATCH(82,'Task Log'!$Q$2:$Q$500,0))),"") | K86: =IFERROR(IF(INDEX('Task Log'!$N$2:$N$500,MATCH(82,'Task Log'!$Q$2:$Q$500,0))="","",INDEX('Task Log'!$N$2:$N$500,MATCH(82,'Task Log'!$Q$2:$Q$500,0))),"") | L86: =IFERROR(IF(INDEX('Task Log'!$P$2:$P$500,MATCH(82,'Task Log'!$Q$2:$Q$500,0))="","",INDEX('Task Log'!$P$2:$P$500,MATCH(82,'Task Log'!$Q$2:$Q$500,0))),"")
A87: =IFERROR(IF(MATCH(83,'Task Log'!$Q$2:$Q$500,0)>0,83,""),"") | B87: =IFERROR(IF(INDEX('Task Log'!$C$2:$C$500,MATCH(83,'Task Log'!$Q$2:$Q$500,0))="","",INDEX('Task Log'!$C$2:$C$500,MATCH(83,'Task Log'!$Q$2:$Q$500,0))),"") | C87: =IFERROR(IF(INDEX('Task Log'!$D$2:$D$500,MATCH(83,'Task Log'!$Q$2:$Q$500,0))="","",INDEX('Task Log'!$D$2:$D$500,MATCH(83,'Task Log'!$Q$2:$Q$500,0))),"") | D87: =IFERROR(IF(INDEX('Task Log'!$E$2:$E$500,MATCH(83,'Task Log'!$Q$2:$Q$500,0))="","",INDEX('Task Log'!$E$2:$E$500,MATCH(83,'Task Log'!$Q$2:$Q$500,0))),"") | E87: =IFERROR(IF(INDEX('Task Log'!$G$2:$G$500,MATCH(83,'Task Log'!$Q$2:$Q$500,0))="","",INDEX('Task Log'!$G$2:$G$500,MATCH(83,'Task Log'!$Q$2:$Q$500,0))),"") | F87: =IFERROR(IF(INDEX('Task Log'!$H$2:$H$500,MATCH(83,'Task Log'!$Q$2:$Q$500,0))="","",INDEX('Task Log'!$H$2:$H$500,MATCH(83,'Task Log'!$Q$2:$Q$500,0))),"") | G87: =IFERROR(IF(INDEX('Task Log'!$I$2:$I$500,MATCH(83,'Task Log'!$Q$2:$Q$500,0))="","",INDEX('Task Log'!$I$2:$I$500,MATCH(83,'Task Log'!$Q$2:$Q$500,0))),"") | H87: =IFERROR(IF(INDEX('Task Log'!$J$2:$J$500,MATCH(83,'Task Log'!$Q$2:$Q$500,0))="","",INDEX('Task Log'!$J$2:$J$500,MATCH(83,'Task Log'!$Q$2:$Q$500,0))),"") | I87: =IFERROR(IF(INDEX('Task Log'!$O$2:$O$500,MATCH(83,'Task Log'!$Q$2:$Q$500,0))="","",INDEX('Task Log'!$O$2:$O$500,MATCH(83,'Task Log'!$Q$2:$Q$500,0))),"") | J87: =IFERROR(IF(INDEX('Task Log'!$K$2:$K$500,MATCH(83,'Task Log'!$Q$2:$Q$500,0))="","",INDEX('Task Log'!$K$2:$K$500,MATCH(83,'Task Log'!$Q$2:$Q$500,0))),"") | K87: =IFERROR(IF(INDEX('Task Log'!$N$2:$N$500,MATCH(83,'Task Log'!$Q$2:$Q$500,0))="","",INDEX('Task Log'!$N$2:$N$500,MATCH(83,'Task Log'!$Q$2:$Q$500,0))),"") | L87: =IFERROR(IF(INDEX('Task Log'!$P$2:$P$500,MATCH(83,'Task Log'!$Q$2:$Q$500,0))="","",INDEX('Task Log'!$P$2:$P$500,MATCH(83,'Task Log'!$Q$2:$Q$500,0))),"")
A88: =IFERROR(IF(MATCH(84,'Task Log'!$Q$2:$Q$500,0)>0,84,""),"") | B88: =IFERROR(IF(INDEX('Task Log'!$C$2:$C$500,MATCH(84,'Task Log'!$Q$2:$Q$500,0))="","",INDEX('Task Log'!$C$2:$C$500,MATCH(84,'Task Log'!$Q$2:$Q$500,0))),"") | C88: =IFERROR(IF(INDEX('Task Log'!$D$2:$D$500,MATCH(84,'Task Log'!$Q$2:$Q$500,0))="","",INDEX('Task Log'!$D$2:$D$500,MATCH(84,'Task Log'!$Q$2:$Q$500,0))),"") | D88: =IFERROR(IF(INDEX('Task Log'!$E$2:$E$500,MATCH(84,'Task Log'!$Q$2:$Q$500,0))="","",INDEX('Task Log'!$E$2:$E$500,MATCH(84,'Task Log'!$Q$2:$Q$500,0))),"") | E88: =IFERROR(IF(INDEX('Task Log'!$G$2:$G$500,MATCH(84,'Task Log'!$Q$2:$Q$500,0))="","",INDEX('Task Log'!$G$2:$G$500,MATCH(84,'Task Log'!$Q$2:$Q$500,0))),"") | F88: =IFERROR(IF(INDEX('Task Log'!$H$2:$H$500,MATCH(84,'Task Log'!$Q$2:$Q$500,0))="","",INDEX('Task Log'!$H$2:$H$500,MATCH(84,'Task Log'!$Q$2:$Q$500,0))),"") | G88: =IFERROR(IF(INDEX('Task Log'!$I$2:$I$500,MATCH(84,'Task Log'!$Q$2:$Q$500,0))="","",INDEX('Task Log'!$I$2:$I$500,MATCH(84,'Task Log'!$Q$2:$Q$500,0))),"") | H88: =IFERROR(IF(INDEX('Task Log'!$J$2:$J$500,MATCH(84,'Task Log'!$Q$2:$Q$500,0))="","",INDEX('Task Log'!$J$2:$J$500,MATCH(84,'Task Log'!$Q$2:$Q$500,0))),"") | I88: =IFERROR(IF(INDEX('Task Log'!$O$2:$O$500,MATCH(84,'Task Log'!$Q$2:$Q$500,0))="","",INDEX('Task Log'!$O$2:$O$500,MATCH(84,'Task Log'!$Q$2:$Q$500,0))),"") | J88: =IFERROR(IF(INDEX('Task Log'!$K$2:$K$500,MATCH(84,'Task Log'!$Q$2:$Q$500,0))="","",INDEX('Task Log'!$K$2:$K$500,MATCH(84,'Task Log'!$Q$2:$Q$500,0))),"") | K88: =IFERROR(IF(INDEX('Task Log'!$N$2:$N$500,MATCH(84,'Task Log'!$Q$2:$Q$500,0))="","",INDEX('Task Log'!$N$2:$N$500,MATCH(84,'Task Log'!$Q$2:$Q$500,0))),"") | L88: =IFERROR(IF(INDEX('Task Log'!$P$2:$P$500,MATCH(84,'Task Log'!$Q$2:$Q$500,0))="","",INDEX('Task Log'!$P$2:$P$500,MATCH(84,'Task Log'!$Q$2:$Q$500,0))),"")
A89: =IFERROR(IF(MATCH(85,'Task Log'!$Q$2:$Q$500,0)>0,85,""),"") | B89: =IFERROR(IF(INDEX('Task Log'!$C$2:$C$500,MATCH(85,'Task Log'!$Q$2:$Q$500,0))="","",INDEX('Task Log'!$C$2:$C$500,MATCH(85,'Task Log'!$Q$2:$Q$500,0))),"") | C89: =IFERROR(IF(INDEX('Task Log'!$D$2:$D$500,MATCH(85,'Task Log'!$Q$2:$Q$500,0))="","",INDEX('Task Log'!$D$2:$D$500,MATCH(85,'Task Log'!$Q$2:$Q$500,0))),"") | D89: =IFERROR(IF(INDEX('Task Log'!$E$2:$E$500,MATCH(85,'Task Log'!$Q$2:$Q$500,0))="","",INDEX('Task Log'!$E$2:$E$500,MATCH(85,'Task Log'!$Q$2:$Q$500,0))),"") | E89: =IFERROR(IF(INDEX('Task Log'!$G$2:$G$500,MATCH(85,'Task Log'!$Q$2:$Q$500,0))="","",INDEX('Task Log'!$G$2:$G$500,MATCH(85,'Task Log'!$Q$2:$Q$500,0))),"") | F89: =IFERROR(IF(INDEX('Task Log'!$H$2:$H$500,MATCH(85,'Task Log'!$Q$2:$Q$500,0))="","",INDEX('Task Log'!$H$2:$H$500,MATCH(85,'Task Log'!$Q$2:$Q$500,0))),"") | G89: =IFERROR(IF(INDEX('Task Log'!$I$2:$I$500,MATCH(85,'Task Log'!$Q$2:$Q$500,0))="","",INDEX('Task Log'!$I$2:$I$500,MATCH(85,'Task Log'!$Q$2:$Q$500,0))),"") | H89: =IFERROR(IF(INDEX('Task Log'!$J$2:$J$500,MATCH(85,'Task Log'!$Q$2:$Q$500,0))="","",INDEX('Task Log'!$J$2:$J$500,MATCH(85,'Task Log'!$Q$2:$Q$500,0))),"") | I89: =IFERROR(IF(INDEX('Task Log'!$O$2:$O$500,MATCH(85,'Task Log'!$Q$2:$Q$500,0))="","",INDEX('Task Log'!$O$2:$O$500,MATCH(85,'Task Log'!$Q$2:$Q$500,0))),"") | J89: =IFERROR(IF(INDEX('Task Log'!$K$2:$K$500,MATCH(85,'Task Log'!$Q$2:$Q$500,0))="","",INDEX('Task Log'!$K$2:$K$500,MATCH(85,'Task Log'!$Q$2:$Q$500,0))),"") | K89: =IFERROR(IF(INDEX('Task Log'!$N$2:$N$500,MATCH(85,'Task Log'!$Q$2:$Q$500,0))="","",INDEX('Task Log'!$N$2:$N$500,MATCH(85,'Task Log'!$Q$2:$Q$500,0))),"") | L89: =IFERROR(IF(INDEX('Task Log'!$P$2:$P$500,MATCH(85,'Task Log'!$Q$2:$Q$500,0))="","",INDEX('Task Log'!$P$2:$P$500,MATCH(85,'Task Log'!$Q$2:$Q$500,0))),"")
A90: =IFERROR(IF(MATCH(86,'Task Log'!$Q$2:$Q$500,0)>0,86,""),"") | B90: =IFERROR(IF(INDEX('Task Log'!$C$2:$C$500,MATCH(86,'Task Log'!$Q$2:$Q$500,0))="","",INDEX('Task Log'!$C$2:$C$500,MATCH(86,'Task Log'!$Q$2:$Q$500,0))),"") | C90: =IFERROR(IF(INDEX('Task Log'!$D$2:$D$500,MATCH(86,'Task Log'!$Q$2:$Q$500,0))="","",INDEX('Task Log'!$D$2:$D$500,MATCH(86,'Task Log'!$Q$2:$Q$500,0))),"") | D90: =IFERROR(IF(INDEX('Task Log'!$E$2:$E$500,MATCH(86,'Task Log'!$Q$2:$Q$500,0))="","",INDEX('Task Log'!$E$2:$E$500,MATCH(86,'Task Log'!$Q$2:$Q$500,0))),"") | E90: =IFERROR(IF(INDEX('Task Log'!$G$2:$G$500,MATCH(86,'Task Log'!$Q$2:$Q$500,0))="","",INDEX('Task Log'!$G$2:$G$500,MATCH(86,'Task Log'!$Q$2:$Q$500,0))),"") | F90: =IFERROR(IF(INDEX('Task Log'!$H$2:$H$500,MATCH(86,'Task Log'!$Q$2:$Q$500,0))="","",INDEX('Task Log'!$H$2:$H$500,MATCH(86,'Task Log'!$Q$2:$Q$500,0))),"") | G90: =IFERROR(IF(INDEX('Task Log'!$I$2:$I$500,MATCH(86,'Task Log'!$Q$2:$Q$500,0))="","",INDEX('Task Log'!$I$2:$I$500,MATCH(86,'Task Log'!$Q$2:$Q$500,0))),"") | H90: =IFERROR(IF(INDEX('Task Log'!$J$2:$J$500,MATCH(86,'Task Log'!$Q$2:$Q$500,0))="","",INDEX('Task Log'!$J$2:$J$500,MATCH(86,'Task Log'!$Q$2:$Q$500,0))),"") | I90: =IFERROR(IF(INDEX('Task Log'!$O$2:$O$500,MATCH(86,'Task Log'!$Q$2:$Q$500,0))="","",INDEX('Task Log'!$O$2:$O$500,MATCH(86,'Task Log'!$Q$2:$Q$500,0))),"") | J90: =IFERROR(IF(INDEX('Task Log'!$K$2:$K$500,MATCH(86,'Task Log'!$Q$2:$Q$500,0))="","",INDEX('Task Log'!$K$2:$K$500,MATCH(86,'Task Log'!$Q$2:$Q$500,0))),"") | K90: =IFERROR(IF(INDEX('Task Log'!$N$2:$N$500,MATCH(86,'Task Log'!$Q$2:$Q$500,0))="","",INDEX('Task Log'!$N$2:$N$500,MATCH(86,'Task Log'!$Q$2:$Q$500,0))),"") | L90: =IFERROR(IF(INDEX('Task Log'!$P$2:$P$500,MATCH(86,'Task Log'!$Q$2:$Q$500,0))="","",INDEX('Task Log'!$P$2:$P$500,MATCH(86,'Task Log'!$Q$2:$Q$500,0))),"")
A91: =IFERROR(IF(MATCH(87,'Task Log'!$Q$2:$Q$500,0)>0,87,""),"") | B91: =IFERROR(IF(INDEX('Task Log'!$C$2:$C$500,MATCH(87,'Task Log'!$Q$2:$Q$500,0))="","",INDEX('Task Log'!$C$2:$C$500,MATCH(87,'Task Log'!$Q$2:$Q$500,0))),"") | C91: =IFERROR(IF(INDEX('Task Log'!$D$2:$D$500,MATCH(87,'Task Log'!$Q$2:$Q$500,0))="","",INDEX('Task Log'!$D$2:$D$500,MATCH(87,'Task Log'!$Q$2:$Q$500,0))),"") | D91: =IFERROR(IF(INDEX('Task Log'!$E$2:$E$500,MATCH(87,'Task Log'!$Q$2:$Q$500,0))="","",INDEX('Task Log'!$E$2:$E$500,MATCH(87,'Task Log'!$Q$2:$Q$500,0))),"") | E91: =IFERROR(IF(INDEX('Task Log'!$G$2:$G$500,MATCH(87,'Task Log'!$Q$2:$Q$500,0))="","",INDEX('Task Log'!$G$2:$G$500,MATCH(87,'Task Log'!$Q$2:$Q$500,0))),"") | F91: =IFERROR(IF(INDEX('Task Log'!$H$2:$H$500,MATCH(87,'Task Log'!$Q$2:$Q$500,0))="","",INDEX('Task Log'!$H$2:$H$500,MATCH(87,'Task Log'!$Q$2:$Q$500,0))),"") | G91: =IFERROR(IF(INDEX('Task Log'!$I$2:$I$500,MATCH(87,'Task Log'!$Q$2:$Q$500,0))="","",INDEX('Task Log'!$I$2:$I$500,MATCH(87,'Task Log'!$Q$2:$Q$500,0))),"") | H91: =IFERROR(IF(INDEX('Task Log'!$J$2:$J$500,MATCH(87,'Task Log'!$Q$2:$Q$500,0))="","",INDEX('Task Log'!$J$2:$J$500,MATCH(87,'Task Log'!$Q$2:$Q$500,0))),"") | I91: =IFERROR(IF(INDEX('Task Log'!$O$2:$O$500,MATCH(87,'Task Log'!$Q$2:$Q$500,0))="","",INDEX('Task Log'!$O$2:$O$500,MATCH(87,'Task Log'!$Q$2:$Q$500,0))),"") | J91: =IFERROR(IF(INDEX('Task Log'!$K$2:$K$500,MATCH(87,'Task Log'!$Q$2:$Q$500,0))="","",INDEX('Task Log'!$K$2:$K$500,MATCH(87,'Task Log'!$Q$2:$Q$500,0))),"") | K91: =IFERROR(IF(INDEX('Task Log'!$N$2:$N$500,MATCH(87,'Task Log'!$Q$2:$Q$500,0))="","",INDEX('Task Log'!$N$2:$N$500,MATCH(87,'Task Log'!$Q$2:$Q$500,0))),"") | L91: =IFERROR(IF(INDEX('Task Log'!$P$2:$P$500,MATCH(87,'Task Log'!$Q$2:$Q$500,0))="","",INDEX('Task Log'!$P$2:$P$500,MATCH(87,'Task Log'!$Q$2:$Q$500,0))),"")
A92: =IFERROR(IF(MATCH(88,'Task Log'!$Q$2:$Q$500,0)>0,88,""),"") | B92: =IFERROR(IF(INDEX('Task Log'!$C$2:$C$500,MATCH(88,'Task Log'!$Q$2:$Q$500,0))="","",INDEX('Task Log'!$C$2:$C$500,MATCH(88,'Task Log'!$Q$2:$Q$500,0))),"") | C92: =IFERROR(IF(INDEX('Task Log'!$D$2:$D$500,MATCH(88,'Task Log'!$Q$2:$Q$500,0))="","",INDEX('Task Log'!$D$2:$D$500,MATCH(88,'Task Log'!$Q$2:$Q$500,0))),"") | D92: =IFERROR(IF(INDEX('Task Log'!$E$2:$E$500,MATCH(88,'Task Log'!$Q$2:$Q$500,0))="","",INDEX('Task Log'!$E$2:$E$500,MATCH(88,'Task Log'!$Q$2:$Q$500,0))),"") | E92: =IFERROR(IF(INDEX('Task Log'!$G$2:$G$500,MATCH(88,'Task Log'!$Q$2:$Q$500,0))="","",INDEX('Task Log'!$G$2:$G$500,MATCH(88,'Task Log'!$Q$2:$Q$500,0))),"") | F92: =IFERROR(IF(INDEX('Task Log'!$H$2:$H$500,MATCH(88,'Task Log'!$Q$2:$Q$500,0))="","",INDEX('Task Log'!$H$2:$H$500,MATCH(88,'Task Log'!$Q$2:$Q$500,0))),"") | G92: =IFERROR(IF(INDEX('Task Log'!$I$2:$I$500,MATCH(88,'Task Log'!$Q$2:$Q$500,0))="","",INDEX('Task Log'!$I$2:$I$500,MATCH(88,'Task Log'!$Q$2:$Q$500,0))),"") | H92: =IFERROR(IF(INDEX('Task Log'!$J$2:$J$500,MATCH(88,'Task Log'!$Q$2:$Q$500,0))="","",INDEX('Task Log'!$J$2:$J$500,MATCH(88,'Task Log'!$Q$2:$Q$500,0))),"") | I92: =IFERROR(IF(INDEX('Task Log'!$O$2:$O$500,MATCH(88,'Task Log'!$Q$2:$Q$500,0))="","",INDEX('Task Log'!$O$2:$O$500,MATCH(88,'Task Log'!$Q$2:$Q$500,0))),"") | J92: =IFERROR(IF(INDEX('Task Log'!$K$2:$K$500,MATCH(88,'Task Log'!$Q$2:$Q$500,0))="","",INDEX('Task Log'!$K$2:$K$500,MATCH(88,'Task Log'!$Q$2:$Q$500,0))),"") | K92: =IFERROR(IF(INDEX('Task Log'!$N$2:$N$500,MATCH(88,'Task Log'!$Q$2:$Q$500,0))="","",INDEX('Task Log'!$N$2:$N$500,MATCH(88,'Task Log'!$Q$2:$Q$500,0))),"") | L92: =IFERROR(IF(INDEX('Task Log'!$P$2:$P$500,MATCH(88,'Task Log'!$Q$2:$Q$500,0))="","",INDEX('Task Log'!$P$2:$P$500,MATCH(88,'Task Log'!$Q$2:$Q$500,0))),"")
A93: =IFERROR(IF(MATCH(89,'Task Log'!$Q$2:$Q$500,0)>0,89,""),"") | B93: =IFERROR(IF(INDEX('Task Log'!$C$2:$C$500,MATCH(89,'Task Log'!$Q$2:$Q$500,0))="","",INDEX('Task Log'!$C$2:$C$500,MATCH(89,'Task Log'!$Q$2:$Q$500,0))),"") | C93: =IFERROR(IF(INDEX('Task Log'!$D$2:$D$500,MATCH(89,'Task Log'!$Q$2:$Q$500,0))="","",INDEX('Task Log'!$D$2:$D$500,MATCH(89,'Task Log'!$Q$2:$Q$500,0))),"") | D93: =IFERROR(IF(INDEX('Task Log'!$E$2:$E$500,MATCH(89,'Task Log'!$Q$2:$Q$500,0))="","",INDEX('Task Log'!$E$2:$E$500,MATCH(89,'Task Log'!$Q$2:$Q$500,0))),"") | E93: =IFERROR(IF(INDEX('Task Log'!$G$2:$G$500,MATCH(89,'Task Log'!$Q$2:$Q$500,0))="","",INDEX('Task Log'!$G$2:$G$500,MATCH(89,'Task Log'!$Q$2:$Q$500,0))),"") | F93: =IFERROR(IF(INDEX('Task Log'!$H$2:$H$500,MATCH(89,'Task Log'!$Q$2:$Q$500,0))="","",INDEX('Task Log'!$H$2:$H$500,MATCH(89,'Task Log'!$Q$2:$Q$500,0))),"") | G93: =IFERROR(IF(INDEX('Task Log'!$I$2:$I$500,MATCH(89,'Task Log'!$Q$2:$Q$500,0))="","",INDEX('Task Log'!$I$2:$I$500,MATCH(89,'Task Log'!$Q$2:$Q$500,0))),"") | H93: =IFERROR(IF(INDEX('Task Log'!$J$2:$J$500,MATCH(89,'Task Log'!$Q$2:$Q$500,0))="","",INDEX('Task Log'!$J$2:$J$500,MATCH(89,'Task Log'!$Q$2:$Q$500,0))),"") | I93: =IFERROR(IF(INDEX('Task Log'!$O$2:$O$500,MATCH(89,'Task Log'!$Q$2:$Q$500,0))="","",INDEX('Task Log'!$O$2:$O$500,MATCH(89,'Task Log'!$Q$2:$Q$500,0))),"") | J93: =IFERROR(IF(INDEX('Task Log'!$K$2:$K$500,MATCH(89,'Task Log'!$Q$2:$Q$500,0))="","",INDEX('Task Log'!$K$2:$K$500,MATCH(89,'Task Log'!$Q$2:$Q$500,0))),"") | K93: =IFERROR(IF(INDEX('Task Log'!$N$2:$N$500,MATCH(89,'Task Log'!$Q$2:$Q$500,0))="","",INDEX('Task Log'!$N$2:$N$500,MATCH(89,'Task Log'!$Q$2:$Q$500,0))),"") | L93: =IFERROR(IF(INDEX('Task Log'!$P$2:$P$500,MATCH(89,'Task Log'!$Q$2:$Q$500,0))="","",INDEX('Task Log'!$P$2:$P$500,MATCH(89,'Task Log'!$Q$2:$Q$500,0))),"")
A94: =IFERROR(IF(MATCH(90,'Task Log'!$Q$2:$Q$500,0)>0,90,""),"") | B94: =IFERROR(IF(INDEX('Task Log'!$C$2:$C$500,MATCH(90,'Task Log'!$Q$2:$Q$500,0))="","",INDEX('Task Log'!$C$2:$C$500,MATCH(90,'Task Log'!$Q$2:$Q$500,0))),"") | C94: =IFERROR(IF(INDEX('Task Log'!$D$2:$D$500,MATCH(90,'Task Log'!$Q$2:$Q$500,0))="","",INDEX('Task Log'!$D$2:$D$500,MATCH(90,'Task Log'!$Q$2:$Q$500,0))),"") | D94: =IFERROR(IF(INDEX('Task Log'!$E$2:$E$500,MATCH(90,'Task Log'!$Q$2:$Q$500,0))="","",INDEX('Task Log'!$E$2:$E$500,MATCH(90,'Task Log'!$Q$2:$Q$500,0))),"") | E94: =IFERROR(IF(INDEX('Task Log'!$G$2:$G$500,MATCH(90,'Task Log'!$Q$2:$Q$500,0))="","",INDEX('Task Log'!$G$2:$G$500,MATCH(90,'Task Log'!$Q$2:$Q$500,0))),"") | F94: =IFERROR(IF(INDEX('Task Log'!$H$2:$H$500,MATCH(90,'Task Log'!$Q$2:$Q$500,0))="","",INDEX('Task Log'!$H$2:$H$500,MATCH(90,'Task Log'!$Q$2:$Q$500,0))),"") | G94: =IFERROR(IF(INDEX('Task Log'!$I$2:$I$500,MATCH(90,'Task Log'!$Q$2:$Q$500,0))="","",INDEX('Task Log'!$I$2:$I$500,MATCH(90,'Task Log'!$Q$2:$Q$500,0))),"") | H94: =IFERROR(IF(INDEX('Task Log'!$J$2:$J$500,MATCH(90,'Task Log'!$Q$2:$Q$500,0))="","",INDEX('Task Log'!$J$2:$J$500,MATCH(90,'Task Log'!$Q$2:$Q$500,0))),"") | I94: =IFERROR(IF(INDEX('Task Log'!$O$2:$O$500,MATCH(90,'Task Log'!$Q$2:$Q$500,0))="","",INDEX('Task Log'!$O$2:$O$500,MATCH(90,'Task Log'!$Q$2:$Q$500,0))),"") | J94: =IFERROR(IF(INDEX('Task Log'!$K$2:$K$500,MATCH(90,'Task Log'!$Q$2:$Q$500,0))="","",INDEX('Task Log'!$K$2:$K$500,MATCH(90,'Task Log'!$Q$2:$Q$500,0))),"") | K94: =IFERROR(IF(INDEX('Task Log'!$N$2:$N$500,MATCH(90,'Task Log'!$Q$2:$Q$500,0))="","",INDEX('Task Log'!$N$2:$N$500,MATCH(90,'Task Log'!$Q$2:$Q$500,0))),"") | L94: =IFERROR(IF(INDEX('Task Log'!$P$2:$P$500,MATCH(90,'Task Log'!$Q$2:$Q$500,0))="","",INDEX('Task Log'!$P$2:$P$500,MATCH(90,'Task Log'!$Q$2:$Q$500,0))),"")
A95: =IFERROR(IF(MATCH(91,'Task Log'!$Q$2:$Q$500,0)>0,91,""),"") | B95: =IFERROR(IF(INDEX('Task Log'!$C$2:$C$500,MATCH(91,'Task Log'!$Q$2:$Q$500,0))="","",INDEX('Task Log'!$C$2:$C$500,MATCH(91,'Task Log'!$Q$2:$Q$500,0))),"") | C95: =IFERROR(IF(INDEX('Task Log'!$D$2:$D$500,MATCH(91,'Task Log'!$Q$2:$Q$500,0))="","",INDEX('Task Log'!$D$2:$D$500,MATCH(91,'Task Log'!$Q$2:$Q$500,0))),"") | D95: =IFERROR(IF(INDEX('Task Log'!$E$2:$E$500,MATCH(91,'Task Log'!$Q$2:$Q$500,0))="","",INDEX('Task Log'!$E$2:$E$500,MATCH(91,'Task Log'!$Q$2:$Q$500,0))),"") | E95: =IFERROR(IF(INDEX('Task Log'!$G$2:$G$500,MATCH(91,'Task Log'!$Q$2:$Q$500,0))="","",INDEX('Task Log'!$G$2:$G$500,MATCH(91,'Task Log'!$Q$2:$Q$500,0))),"") | F95: =IFERROR(IF(INDEX('Task Log'!$H$2:$H$500,MATCH(91,'Task Log'!$Q$2:$Q$500,0))="","",INDEX('Task Log'!$H$2:$H$500,MATCH(91,'Task Log'!$Q$2:$Q$500,0))),"") | G95: =IFERROR(IF(INDEX('Task Log'!$I$2:$I$500,MATCH(91,'Task Log'!$Q$2:$Q$500,0))="","",INDEX('Task Log'!$I$2:$I$500,MATCH(91,'Task Log'!$Q$2:$Q$500,0))),"") | H95: =IFERROR(IF(INDEX('Task Log'!$J$2:$J$500,MATCH(91,'Task Log'!$Q$2:$Q$500,0))="","",INDEX('Task Log'!$J$2:$J$500,MATCH(91,'Task Log'!$Q$2:$Q$500,0))),"") | I95: =IFERROR(IF(INDEX('Task Log'!$O$2:$O$500,MATCH(91,'Task Log'!$Q$2:$Q$500,0))="","",INDEX('Task Log'!$O$2:$O$500,MATCH(91,'Task Log'!$Q$2:$Q$500,0))),"") | J95: =IFERROR(IF(INDEX('Task Log'!$K$2:$K$500,MATCH(91,'Task Log'!$Q$2:$Q$500,0))="","",INDEX('Task Log'!$K$2:$K$500,MATCH(91,'Task Log'!$Q$2:$Q$500,0))),"") | K95: =IFERROR(IF(INDEX('Task Log'!$N$2:$N$500,MATCH(91,'Task Log'!$Q$2:$Q$500,0))="","",INDEX('Task Log'!$N$2:$N$500,MATCH(91,'Task Log'!$Q$2:$Q$500,0))),"") | L95: =IFERROR(IF(INDEX('Task Log'!$P$2:$P$500,MATCH(91,'Task Log'!$Q$2:$Q$500,0))="","",INDEX('Task Log'!$P$2:$P$500,MATCH(91,'Task Log'!$Q$2:$Q$500,0))),"")
A96: =IFERROR(IF(MATCH(92,'Task Log'!$Q$2:$Q$500,0)>0,92,""),"") | B96: =IFERROR(IF(INDEX('Task Log'!$C$2:$C$500,MATCH(92,'Task Log'!$Q$2:$Q$500,0))="","",INDEX('Task Log'!$C$2:$C$500,MATCH(92,'Task Log'!$Q$2:$Q$500,0))),"") | C96: =IFERROR(IF(INDEX('Task Log'!$D$2:$D$500,MATCH(92,'Task Log'!$Q$2:$Q$500,0))="","",INDEX('Task Log'!$D$2:$D$500,MATCH(92,'Task Log'!$Q$2:$Q$500,0))),"") | D96: =IFERROR(IF(INDEX('Task Log'!$E$2:$E$500,MATCH(92,'Task Log'!$Q$2:$Q$500,0))="","",INDEX('Task Log'!$E$2:$E$500,MATCH(92,'Task Log'!$Q$2:$Q$500,0))),"") | E96: =IFERROR(IF(INDEX('Task Log'!$G$2:$G$500,MATCH(92,'Task Log'!$Q$2:$Q$500,0))="","",INDEX('Task Log'!$G$2:$G$500,MATCH(92,'Task Log'!$Q$2:$Q$500,0))),"") | F96: =IFERROR(IF(INDEX('Task Log'!$H$2:$H$500,MATCH(92,'Task Log'!$Q$2:$Q$500,0))="","",INDEX('Task Log'!$H$2:$H$500,MATCH(92,'Task Log'!$Q$2:$Q$500,0))),"") | G96: =IFERROR(IF(INDEX('Task Log'!$I$2:$I$500,MATCH(92,'Task Log'!$Q$2:$Q$500,0))="","",INDEX('Task Log'!$I$2:$I$500,MATCH(92,'Task Log'!$Q$2:$Q$500,0))),"") | H96: =IFERROR(IF(INDEX('Task Log'!$J$2:$J$500,MATCH(92,'Task Log'!$Q$2:$Q$500,0))="","",INDEX('Task Log'!$J$2:$J$500,MATCH(92,'Task Log'!$Q$2:$Q$500,0))),"") | I96: =IFERROR(IF(INDEX('Task Log'!$O$2:$O$500,MATCH(92,'Task Log'!$Q$2:$Q$500,0))="","",INDEX('Task Log'!$O$2:$O$500,MATCH(92,'Task Log'!$Q$2:$Q$500,0))),"") | J96: =IFERROR(IF(INDEX('Task Log'!$K$2:$K$500,MATCH(92,'Task Log'!$Q$2:$Q$500,0))="","",INDEX('Task Log'!$K$2:$K$500,MATCH(92,'Task Log'!$Q$2:$Q$500,0))),"") | K96: =IFERROR(IF(INDEX('Task Log'!$N$2:$N$500,MATCH(92,'Task Log'!$Q$2:$Q$500,0))="","",INDEX('Task Log'!$N$2:$N$500,MATCH(92,'Task Log'!$Q$2:$Q$500,0))),"") | L96: =IFERROR(IF(INDEX('Task Log'!$P$2:$P$500,MATCH(92,'Task Log'!$Q$2:$Q$500,0))="","",INDEX('Task Log'!$P$2:$P$500,MATCH(92,'Task Log'!$Q$2:$Q$500,0))),"")
A97: =IFERROR(IF(MATCH(93,'Task Log'!$Q$2:$Q$500,0)>0,93,""),"") | B97: =IFERROR(IF(INDEX('Task Log'!$C$2:$C$500,MATCH(93,'Task Log'!$Q$2:$Q$500,0))="","",INDEX('Task Log'!$C$2:$C$500,MATCH(93,'Task Log'!$Q$2:$Q$500,0))),"") | C97: =IFERROR(IF(INDEX('Task Log'!$D$2:$D$500,MATCH(93,'Task Log'!$Q$2:$Q$500,0))="","",INDEX('Task Log'!$D$2:$D$500,MATCH(93,'Task Log'!$Q$2:$Q$500,0))),"") | D97: =IFERROR(IF(INDEX('Task Log'!$E$2:$E$500,MATCH(93,'Task Log'!$Q$2:$Q$500,0))="","",INDEX('Task Log'!$E$2:$E$500,MATCH(93,'Task Log'!$Q$2:$Q$500,0))),"") | E97: =IFERROR(IF(INDEX('Task Log'!$G$2:$G$500,MATCH(93,'Task Log'!$Q$2:$Q$500,0))="","",INDEX('Task Log'!$G$2:$G$500,MATCH(93,'Task Log'!$Q$2:$Q$500,0))),"") | F97: =IFERROR(IF(INDEX('Task Log'!$H$2:$H$500,MATCH(93,'Task Log'!$Q$2:$Q$500,0))="","",INDEX('Task Log'!$H$2:$H$500,MATCH(93,'Task Log'!$Q$2:$Q$500,0))),"") | G97: =IFERROR(IF(INDEX('Task Log'!$I$2:$I$500,MATCH(93,'Task Log'!$Q$2:$Q$500,0))="","",INDEX('Task Log'!$I$2:$I$500,MATCH(93,'Task Log'!$Q$2:$Q$500,0))),"") | H97: =IFERROR(IF(INDEX('Task Log'!$J$2:$J$500,MATCH(93,'Task Log'!$Q$2:$Q$500,0))="","",INDEX('Task Log'!$J$2:$J$500,MATCH(93,'Task Log'!$Q$2:$Q$500,0))),"") | I97: =IFERROR(IF(INDEX('Task Log'!$O$2:$O$500,MATCH(93,'Task Log'!$Q$2:$Q$500,0))="","",INDEX('Task Log'!$O$2:$O$500,MATCH(93,'Task Log'!$Q$2:$Q$500,0))),"") | J97: =IFERROR(IF(INDEX('Task Log'!$K$2:$K$500,MATCH(93,'Task Log'!$Q$2:$Q$500,0))="","",INDEX('Task Log'!$K$2:$K$500,MATCH(93,'Task Log'!$Q$2:$Q$500,0))),"") | K97: =IFERROR(IF(INDEX('Task Log'!$N$2:$N$500,MATCH(93,'Task Log'!$Q$2:$Q$500,0))="","",INDEX('Task Log'!$N$2:$N$500,MATCH(93,'Task Log'!$Q$2:$Q$500,0))),"") | L97: =IFERROR(IF(INDEX('Task Log'!$P$2:$P$500,MATCH(93,'Task Log'!$Q$2:$Q$500,0))="","",INDEX('Task Log'!$P$2:$P$500,MATCH(93,'Task Log'!$Q$2:$Q$500,0))),"")
A98: =IFERROR(IF(MATCH(94,'Task Log'!$Q$2:$Q$500,0)>0,94,""),"") | B98: =IFERROR(IF(INDEX('Task Log'!$C$2:$C$500,MATCH(94,'Task Log'!$Q$2:$Q$500,0))="","",INDEX('Task Log'!$C$2:$C$500,MATCH(94,'Task Log'!$Q$2:$Q$500,0))),"") | C98: =IFERROR(IF(INDEX('Task Log'!$D$2:$D$500,MATCH(94,'Task Log'!$Q$2:$Q$500,0))="","",INDEX('Task Log'!$D$2:$D$500,MATCH(94,'Task Log'!$Q$2:$Q$500,0))),"") | D98: =IFERROR(IF(INDEX('Task Log'!$E$2:$E$500,MATCH(94,'Task Log'!$Q$2:$Q$500,0))="","",INDEX('Task Log'!$E$2:$E$500,MATCH(94,'Task Log'!$Q$2:$Q$500,0))),"") | E98: =IFERROR(IF(INDEX('Task Log'!$G$2:$G$500,MATCH(94,'Task Log'!$Q$2:$Q$500,0))="","",INDEX('Task Log'!$G$2:$G$500,MATCH(94,'Task Log'!$Q$2:$Q$500,0))),"") | F98: =IFERROR(IF(INDEX('Task Log'!$H$2:$H$500,MATCH(94,'Task Log'!$Q$2:$Q$500,0))="","",INDEX('Task Log'!$H$2:$H$500,MATCH(94,'Task Log'!$Q$2:$Q$500,0))),"") | G98: =IFERROR(IF(INDEX('Task Log'!$I$2:$I$500,MATCH(94,'Task Log'!$Q$2:$Q$500,0))="","",INDEX('Task Log'!$I$2:$I$500,MATCH(94,'Task Log'!$Q$2:$Q$500,0))),"") | H98: =IFERROR(IF(INDEX('Task Log'!$J$2:$J$500,MATCH(94,'Task Log'!$Q$2:$Q$500,0))="","",INDEX('Task Log'!$J$2:$J$500,MATCH(94,'Task Log'!$Q$2:$Q$500,0))),"") | I98: =IFERROR(IF(INDEX('Task Log'!$O$2:$O$500,MATCH(94,'Task Log'!$Q$2:$Q$500,0))="","",INDEX('Task Log'!$O$2:$O$500,MATCH(94,'Task Log'!$Q$2:$Q$500,0))),"") | J98: =IFERROR(IF(INDEX('Task Log'!$K$2:$K$500,MATCH(94,'Task Log'!$Q$2:$Q$500,0))="","",INDEX('Task Log'!$K$2:$K$500,MATCH(94,'Task Log'!$Q$2:$Q$500,0))),"") | K98: =IFERROR(IF(INDEX('Task Log'!$N$2:$N$500,MATCH(94,'Task Log'!$Q$2:$Q$500,0))="","",INDEX('Task Log'!$N$2:$N$500,MATCH(94,'Task Log'!$Q$2:$Q$500,0))),"") | L98: =IFERROR(IF(INDEX('Task Log'!$P$2:$P$500,MATCH(94,'Task Log'!$Q$2:$Q$500,0))="","",INDEX('Task Log'!$P$2:$P$500,MATCH(94,'Task Log'!$Q$2:$Q$500,0))),"")
A99: =IFERROR(IF(MATCH(95,'Task Log'!$Q$2:$Q$500,0)>0,95,""),"") | B99: =IFERROR(IF(INDEX('Task Log'!$C$2:$C$500,MATCH(95,'Task Log'!$Q$2:$Q$500,0))="","",INDEX('Task Log'!$C$2:$C$500,MATCH(95,'Task Log'!$Q$2:$Q$500,0))),"") | C99: =IFERROR(IF(INDEX('Task Log'!$D$2:$D$500,MATCH(95,'Task Log'!$Q$2:$Q$500,0))="","",INDEX('Task Log'!$D$2:$D$500,MATCH(95,'Task Log'!$Q$2:$Q$500,0))),"") | D99: =IFERROR(IF(INDEX('Task Log'!$E$2:$E$500,MATCH(95,'Task Log'!$Q$2:$Q$500,0))="","",INDEX('Task Log'!$E$2:$E$500,MATCH(95,'Task Log'!$Q$2:$Q$500,0))),"") | E99: =IFERROR(IF(INDEX('Task Log'!$G$2:$G$500,MATCH(95,'Task Log'!$Q$2:$Q$500,0))="","",INDEX('Task Log'!$G$2:$G$500,MATCH(95,'Task Log'!$Q$2:$Q$500,0))),"") | F99: =IFERROR(IF(INDEX('Task Log'!$H$2:$H$500,MATCH(95,'Task Log'!$Q$2:$Q$500,0))="","",INDEX('Task Log'!$H$2:$H$500,MATCH(95,'Task Log'!$Q$2:$Q$500,0))),"") | G99: =IFERROR(IF(INDEX('Task Log'!$I$2:$I$500,MATCH(95,'Task Log'!$Q$2:$Q$500,0))="","",INDEX('Task Log'!$I$2:$I$500,MATCH(95,'Task Log'!$Q$2:$Q$500,0))),"") | H99: =IFERROR(IF(INDEX('Task Log'!$J$2:$J$500,MATCH(95,'Task Log'!$Q$2:$Q$500,0))="","",INDEX('Task Log'!$J$2:$J$500,MATCH(95,'Task Log'!$Q$2:$Q$500,0))),"") | I99: =IFERROR(IF(INDEX('Task Log'!$O$2:$O$500,MATCH(95,'Task Log'!$Q$2:$Q$500,0))="","",INDEX('Task Log'!$O$2:$O$500,MATCH(95,'Task Log'!$Q$2:$Q$500,0))),"") | J99: =IFERROR(IF(INDEX('Task Log'!$K$2:$K$500,MATCH(95,'Task Log'!$Q$2:$Q$500,0))="","",INDEX('Task Log'!$K$2:$K$500,MATCH(95,'Task Log'!$Q$2:$Q$500,0))),"") | K99: =IFERROR(IF(INDEX('Task Log'!$N$2:$N$500,MATCH(95,'Task Log'!$Q$2:$Q$500,0))="","",INDEX('Task Log'!$N$2:$N$500,MATCH(95,'Task Log'!$Q$2:$Q$500,0))),"") | L99: =IFERROR(IF(INDEX('Task Log'!$P$2:$P$500,MATCH(95,'Task Log'!$Q$2:$Q$500,0))="","",INDEX('Task Log'!$P$2:$P$500,MATCH(95,'Task Log'!$Q$2:$Q$500,0))),"")
A100: =IFERROR(IF(MATCH(96,'Task Log'!$Q$2:$Q$500,0)>0,96,""),"") | B100: =IFERROR(IF(INDEX('Task Log'!$C$2:$C$500,MATCH(96,'Task Log'!$Q$2:$Q$500,0))="","",INDEX('Task Log'!$C$2:$C$500,MATCH(96,'Task Log'!$Q$2:$Q$500,0))),"") | C100: =IFERROR(IF(INDEX('Task Log'!$D$2:$D$500,MATCH(96,'Task Log'!$Q$2:$Q$500,0))="","",INDEX('Task Log'!$D$2:$D$500,MATCH(96,'Task Log'!$Q$2:$Q$500,0))),"") | D100: =IFERROR(IF(INDEX('Task Log'!$E$2:$E$500,MATCH(96,'Task Log'!$Q$2:$Q$500,0))="","",INDEX('Task Log'!$E$2:$E$500,MATCH(96,'Task Log'!$Q$2:$Q$500,0))),"") | E100: =IFERROR(IF(INDEX('Task Log'!$G$2:$G$500,MATCH(96,'Task Log'!$Q$2:$Q$500,0))="","",INDEX('Task Log'!$G$2:$G$500,MATCH(96,'Task Log'!$Q$2:$Q$500,0))),"") | F100: =IFERROR(IF(INDEX('Task Log'!$H$2:$H$500,MATCH(96,'Task Log'!$Q$2:$Q$500,0))="","",INDEX('Task Log'!$H$2:$H$500,MATCH(96,'Task Log'!$Q$2:$Q$500,0))),"") | G100: =IFERROR(IF(INDEX('Task Log'!$I$2:$I$500,MATCH(96,'Task Log'!$Q$2:$Q$500,0))="","",INDEX('Task Log'!$I$2:$I$500,MATCH(96,'Task Log'!$Q$2:$Q$500,0))),"") | H100: =IFERROR(IF(INDEX('Task Log'!$J$2:$J$500,MATCH(96,'Task Log'!$Q$2:$Q$500,0))="","",INDEX('Task Log'!$J$2:$J$500,MATCH(96,'Task Log'!$Q$2:$Q$500,0))),"") | I100: =IFERROR(IF(INDEX('Task Log'!$O$2:$O$500,MATCH(96,'Task Log'!$Q$2:$Q$500,0))="","",INDEX('Task Log'!$O$2:$O$500,MATCH(96,'Task Log'!$Q$2:$Q$500,0))),"") | J100: =IFERROR(IF(INDEX('Task Log'!$K$2:$K$500,MATCH(96,'Task Log'!$Q$2:$Q$500,0))="","",INDEX('Task Log'!$K$2:$K$500,MATCH(96,'Task Log'!$Q$2:$Q$500,0))),"") | K100: =IFERROR(IF(INDEX('Task Log'!$N$2:$N$500,MATCH(96,'Task Log'!$Q$2:$Q$500,0))="","",INDEX('Task Log'!$N$2:$N$500,MATCH(96,'Task Log'!$Q$2:$Q$500,0))),"") | L100: =IFERROR(IF(INDEX('Task Log'!$P$2:$P$500,MATCH(96,'Task Log'!$Q$2:$Q$500,0))="","",INDEX('Task Log'!$P$2:$P$500,MATCH(96,'Task Log'!$Q$2:$Q$500,0))),"")
A101: =IFERROR(IF(MATCH(97,'Task Log'!$Q$2:$Q$500,0)>0,97,""),"") | B101: =IFERROR(IF(INDEX('Task Log'!$C$2:$C$500,MATCH(97,'Task Log'!$Q$2:$Q$500,0))="","",INDEX('Task Log'!$C$2:$C$500,MATCH(97,'Task Log'!$Q$2:$Q$500,0))),"") | C101: =IFERROR(IF(INDEX('Task Log'!$D$2:$D$500,MATCH(97,'Task Log'!$Q$2:$Q$500,0))="","",INDEX('Task Log'!$D$2:$D$500,MATCH(97,'Task Log'!$Q$2:$Q$500,0))),"") | D101: =IFERROR(IF(INDEX('Task Log'!$E$2:$E$500,MATCH(97,'Task Log'!$Q$2:$Q$500,0))="","",INDEX('Task Log'!$E$2:$E$500,MATCH(97,'Task Log'!$Q$2:$Q$500,0))),"") | E101: =IFERROR(IF(INDEX('Task Log'!$G$2:$G$500,MATCH(97,'Task Log'!$Q$2:$Q$500,0))="","",INDEX('Task Log'!$G$2:$G$500,MATCH(97,'Task Log'!$Q$2:$Q$500,0))),"") | F101: =IFERROR(IF(INDEX('Task Log'!$H$2:$H$500,MATCH(97,'Task Log'!$Q$2:$Q$500,0))="","",INDEX('Task Log'!$H$2:$H$500,MATCH(97,'Task Log'!$Q$2:$Q$500,0))),"") | G101: =IFERROR(IF(INDEX('Task Log'!$I$2:$I$500,MATCH(97,'Task Log'!$Q$2:$Q$500,0))="","",INDEX('Task Log'!$I$2:$I$500,MATCH(97,'Task Log'!$Q$2:$Q$500,0))),"") | H101: =IFERROR(IF(INDEX('Task Log'!$J$2:$J$500,MATCH(97,'Task Log'!$Q$2:$Q$500,0))="","",INDEX('Task Log'!$J$2:$J$500,MATCH(97,'Task Log'!$Q$2:$Q$500,0))),"") | I101: =IFERROR(IF(INDEX('Task Log'!$O$2:$O$500,MATCH(97,'Task Log'!$Q$2:$Q$500,0))="","",INDEX('Task Log'!$O$2:$O$500,MATCH(97,'Task Log'!$Q$2:$Q$500,0))),"") | J101: =IFERROR(IF(INDEX('Task Log'!$K$2:$K$500,MATCH(97,'Task Log'!$Q$2:$Q$500,0))="","",INDEX('Task Log'!$K$2:$K$500,MATCH(97,'Task Log'!$Q$2:$Q$500,0))),"") | K101: =IFERROR(IF(INDEX('Task Log'!$N$2:$N$500,MATCH(97,'Task Log'!$Q$2:$Q$500,0))="","",INDEX('Task Log'!$N$2:$N$500,MATCH(97,'Task Log'!$Q$2:$Q$500,0))),"") | L101: =IFERROR(IF(INDEX('Task Log'!$P$2:$P$500,MATCH(97,'Task Log'!$Q$2:$Q$500,0))="","",INDEX('Task Log'!$P$2:$P$500,MATCH(97,'Task Log'!$Q$2:$Q$500,0))),"")
...

Sheet Dashboard
A1: PROJECT TASK DASHBOARD
A2: ="Live as on "&TEXT(TODAY(),"DD-MMM-YYYY")&" - all figures recalculate automatically"
A3: SNAPSHOT
A4: Total Tasks | B4: =COUNTIF('Task Log'!$D$2:$D$500,"<>")
A5: Completed | B5: =COUNTIFS('Task Log'!$D$2:$D$500,"<>",'Task Log'!$K$2:$K$500,"Completed")
A6: Open | B6: =COUNTIFS('Task Log'!$D$2:$D$500,"<>",'Task Log'!$K$2:$K$500,"<>Completed")
A7: Carried Forward | B7: =COUNTIF('Task Log'!$N$2:$N$500,"Carried Forward")
A8: Due Today | B8: =COUNTIF('Task Log'!$N$2:$N$500,"Due Today")
A9: Events in next 7 days | B9: =COUNTIFS('Task Log'!$I$2:$I$500,">="&TODAY(),'Task Log'!$I$2:$I$500,"<="&(TODAY()+7),'Task Log'!$K$2:$K$500,"<>Completed")
A10: Event Dates Missed | B10: =COUNTIFS('Task Log'!$I$2:$I$500,"<"&TODAY(),'Task Log'!$I$2:$I$500,"<>",'Task Log'!$K$2:$K$500,"<>Completed")
A11: Completion % | B11: =IFERROR(B5/B4,0)
A14: TASKS BY VERTICAL | F14: TASKS BY STATUS | I14: LAST 14 DAYS - DUE vs COMPLETED | M14: UPCOMING EVENTS (NEXT 30 DAYS)
A15: Vertical | B15: Total | C15: Completed | D15: Open | F15: Status | G15: Count | I15: Date | J15: Tasks Due | K15: Completed | M15: Event Type | N15: Count
A16: Defence | B16: =COUNTIF('Task Log'!$C$2:$C$500,$A16) | C16: =COUNTIFS('Task Log'!$C$2:$C$500,$A16,'Task Log'!$K$2:$K$500,"Completed") | D16: =COUNTIFS('Task Log'!$C$2:$C$500,$A16,'Task Log'!$K$2:$K$500,"<>Completed") | F16: Not Started | G16: =COUNTIF('Task Log'!$K$2:$K$500,$F16) | I16: =TODAY()-13 | J16: =COUNTIF('Task Log'!$H$2:$H$500,$I16) | K16: =COUNTIF('Task Log'!$L$2:$L$500,$I16) | M16: Demo | N16: =COUNTIFS('Task Log'!$J$2:$J$500,$M16,'Task Log'!$I$2:$I$500,">="&TODAY(),'Task Log'!$I$2:$I$500,"<="&(TODAY()+30),'Task Log'!$K$2:$K$500,"<>Completed")
A17: Industry | B17: =COUNTIF('Task Log'!$C$2:$C$500,$A17) | C17: =COUNTIFS('Task Log'!$C$2:$C$500,$A17,'Task Log'!$K$2:$K$500,"Completed") | D17: =COUNTIFS('Task Log'!$C$2:$C$500,$A17,'Task Log'!$K$2:$K$500,"<>Completed") | F17: In Progress | G17: =COUNTIF('Task Log'!$K$2:$K$500,$F17) | I17: =TODAY()-12 | J17: =COUNTIF('Task Log'!$H$2:$H$500,$I17) | K17: =COUNTIF('Task Log'!$L$2:$L$500,$I17) | M17: Delivery / Dispatch | N17: =COUNTIFS('Task Log'!$J$2:$J$500,$M17,'Task Log'!$I$2:$I$500,">="&TODAY(),'Task Log'!$I$2:$I$500,"<="&(TODAY()+30),'Task Log'!$K$2:$K$500,"<>Completed")
A18: Tenders | B18: =COUNTIF('Task Log'!$C$2:$C$500,$A18) | C18: =COUNTIFS('Task Log'!$C$2:$C$500,$A18,'Task Log'!$K$2:$K$500,"Completed") | D18: =COUNTIFS('Task Log'!$C$2:$C$500,$A18,'Task Log'!$K$2:$K$500,"<>Completed") | F18: On Hold | G18: =COUNTIF('Task Log'!$K$2:$K$500,$F18) | I18: =TODAY()-11 | J18: =COUNTIF('Task Log'!$H$2:$H$500,$I18) | K18: =COUNTIF('Task Log'!$L$2:$L$500,$I18) | M18: Inspection | N18: =COUNTIFS('Task Log'!$J$2:$J$500,$M18,'Task Log'!$I$2:$I$500,">="&TODAY(),'Task Log'!$I$2:$I$500,"<="&(TODAY()+30),'Task Log'!$K$2:$K$500,"<>Completed")
A19: RPTO | B19: =COUNTIF('Task Log'!$C$2:$C$500,$A19) | C19: =COUNTIFS('Task Log'!$C$2:$C$500,$A19,'Task Log'!$K$2:$K$500,"Completed") | D19: =COUNTIFS('Task Log'!$C$2:$C$500,$A19,'Task Log'!$K$2:$K$500,"<>Completed") | F19: Completed | G19: =COUNTIF('Task Log'!$K$2:$K$500,$F19) | I19: =TODAY()-10 | J19: =COUNTIF('Task Log'!$H$2:$H$500,$I19) | K19: =COUNTIF('Task Log'!$L$2:$L$500,$I19) | M19: Tender Submission | N19: =COUNTIFS('Task Log'!$J$2:$J$500,$M19,'Task Log'!$I$2:$I$500,">="&TODAY(),'Task Log'!$I$2:$I$500,"<="&(TODAY()+30),'Task Log'!$K$2:$K$500,"<>Completed")
A20: RPTO Establishment | B20: =COUNTIF('Task Log'!$C$2:$C$500,$A20) | C20: =COUNTIFS('Task Log'!$C$2:$C$500,$A20,'Task Log'!$K$2:$K$500,"Completed") | D20: =COUNTIFS('Task Log'!$C$2:$C$500,$A20,'Task Log'!$K$2:$K$500,"<>Completed") | I20: =TODAY()-9 | J20: =COUNTIF('Task Log'!$H$2:$H$500,$I20) | K20: =COUNTIF('Task Log'!$L$2:$L$500,$I20) | M20: Training Batch | N20: =COUNTIFS('Task Log'!$J$2:$J$500,$M20,'Task Log'!$I$2:$I$500,">="&TODAY(),'Task Log'!$I$2:$I$500,"<="&(TODAY()+30),'Task Log'!$K$2:$K$500,"<>Completed")
A21: DaaS | B21: =COUNTIF('Task Log'!$C$2:$C$500,$A21) | C21: =COUNTIFS('Task Log'!$C$2:$C$500,$A21,'Task Log'!$K$2:$K$500,"Completed") | D21: =COUNTIFS('Task Log'!$C$2:$C$500,$A21,'Task Log'!$K$2:$K$500,"<>Completed") | I21: =TODAY()-8 | J21: =COUNTIF('Task Log'!$H$2:$H$500,$I21) | K21: =COUNTIF('Task Log'!$L$2:$L$500,$I21) | M21: Site Survey | N21: =COUNTIFS('Task Log'!$J$2:$J$500,$M21,'Task Log'!$I$2:$I$500,">="&TODAY(),'Task Log'!$I$2:$I$500,"<="&(TODAY()+30),'Task Log'!$K$2:$K$500,"<>Completed")
A22: V V Yatra | B22: =COUNTIF('Task Log'!$C$2:$C$500,$A22) | C22: =COUNTIFS('Task Log'!$C$2:$C$500,$A22,'Task Log'!$K$2:$K$500,"Completed") | D22: =COUNTIFS('Task Log'!$C$2:$C$500,$A22,'Task Log'!$K$2:$K$500,"<>Completed") | F22: OPEN TASKS BY PRIORITY | I22: =TODAY()-7 | J22: =COUNTIF('Task Log'!$H$2:$H$500,$I22) | K22: =COUNTIF('Task Log'!$L$2:$L$500,$I22) | M22: Go-Live | N22: =COUNTIFS('Task Log'!$J$2:$J$500,$M22,'Task Log'!$I$2:$I$500,">="&TODAY(),'Task Log'!$I$2:$I$500,"<="&(TODAY()+30),'Task Log'!$K$2:$K$500,"<>Completed")
A23: Redington | B23: =COUNTIF('Task Log'!$C$2:$C$500,$A23) | C23: =COUNTIFS('Task Log'!$C$2:$C$500,$A23,'Task Log'!$K$2:$K$500,"Completed") | D23: =COUNTIFS('Task Log'!$C$2:$C$500,$A23,'Task Log'!$K$2:$K$500,"<>Completed") | F23: Priority | G23: Open | I23: =TODAY()-6 | J23: =COUNTIF('Task Log'!$H$2:$H$500,$I23) | K23: =COUNTIF('Task Log'!$L$2:$L$500,$I23) | M23: Review Meeting | N23: =COUNTIFS('Task Log'!$J$2:$J$500,$M23,'Task Log'!$I$2:$I$500,">="&TODAY(),'Task Log'!$I$2:$I$500,"<="&(TODAY()+30),'Task Log'!$K$2:$K$500,"<>Completed")
A24: CoE | B24: =COUNTIF('Task Log'!$C$2:$C$500,$A24) | C24: =COUNTIFS('Task Log'!$C$2:$C$500,$A24,'Task Log'!$K$2:$K$500,"Completed") | D24: =COUNTIFS('Task Log'!$C$2:$C$500,$A24,'Task Log'!$K$2:$K$500,"<>Completed") | F24: High | G24: =COUNTIFS('Task Log'!$G$2:$G$500,$F24,'Task Log'!$K$2:$K$500,"<>Completed") | I24: =TODAY()-5 | J24: =COUNTIF('Task Log'!$H$2:$H$500,$I24) | K24: =COUNTIF('Task Log'!$L$2:$L$500,$I24) | M24: Payment / Invoice | N24: =COUNTIFS('Task Log'!$J$2:$J$500,$M24,'Task Log'!$I$2:$I$500,">="&TODAY(),'Task Log'!$I$2:$I$500,"<="&(TODAY()+30),'Task Log'!$K$2:$K$500,"<>Completed")
